Workbook
Name Slicer_Price_Category1: #N/A

Sheet Dashboard
A1: SEPHORA BEAUTY PRODUCTS DASHBOARD
A4: Total Products | H4: Average Rating | U4: Average Price
B5: =Data_quality!B2 -> 500 | J5: =Data_quality!B11 -> 4.1957166 | U5: =Data_quality!B8 -> 53.0727

Sheet excel project
A1: product_id | B1: product_name | C1: brand_id | D1: brand_name | E1: loves_count | F1: rating | G1: reviews | H1: size | I1: variation_type | J1: variation_value | K1: variation_desc | L1: ingredients | M1: price_usd | N1: value_price_usd | O1: sale_price_usd | P1: limited_edition | Q1: new | R1: online_only | S1: out_of_stock | T1: sephora_exclusive | U1: highlights | V1: primary_category | W1: secondary_category | X1: tertiary_category | Y1: child_count | Z1: child_max_price | AA1: child_min_price | AC1: Random_number
A2: P453279 | B2: Mini Intenso Smoothing Mask for Thick Hair | C2: 6159 | D2: Rossano Ferretti Parma | E2: 557 | F2: 3 | G2: 2 | H2: 1.7 oz/ 50 mL | I2: Size | J2: 1.7 oz/ 50 mL | M2: 18 | P2: 0 | Q2: 0 | R2: 1 | S2: 0 | T2: 0 | U2: ['Vegan', 'Hydrating', 'Clean at Sephora', 'Good for: Frizz', 'Good for: Dryness', 'Cruelty-Free'] | V2: Hair | W2: Hair Styling & Treatments | X2: Hair Masks | Y2: 0 | AC2: 0.00028886723
A3: P501449 | B3: PEPTIDE PREP Clarifying Detox Shampoo | C3: 6472 | D3: K18 Biomimetic Hairscience | E3: 24418 | F3: 4.7944 | G3: 603 | H3: 8.5 oz / 250 mL | I3: Size | J3: 8.5 oz / 250 mL | L3: ['Water (Aqua) (Eau), Sodium C14-16 Olefin Sulfonate, Cocamidopropyl Hydroxysultaine, Salicylic Acid, Charcoal Powder, sh-Oligopeptide-78, Panthenol,', 'Glycerin, Sodium Phytate, Guar Hydroxypropyltrimonium Chloride, Caprylyl Glycol, Caprylhydroxamic Acid, Citric Acid, Potassium Hydroxide, Sodium Hydroxide, Fragrance (Parfum), Benzyl Salicylate, Limonene.'] | M3: 38 | P3: 0 | Q3: 0 | R3: 0 | S3: 0 | T3: 1 | U3: ['Vegan', 'Good for: Color Care', 'Clean at Sephora', 'All Hair Types', 'Salicylic Acid', 'Good for: Oily Scalp'] | V3: Hair | W3: Shampoo & Conditioner | X3: Shampoo | Y3: 1 | Z3: 14 | AA3: 14 | AC3: 0.00034055583
A4: P501526 | B4: Even Better All-Over Primer + Color Corrector | C4: 1254 | D4: CLINIQUE | E4: 2159 | F4: 3.8 | G4: 5 | H4: 0.2 oz / 6 mL | I4: Color | J4: Peach | K4: very fair to moderately fair complexions | L4: ['Water/Aqua/Eau, Methyl Trimethicone, Trimethylsiloxysilicate, Dimethicone, Butylene Glycol, Phenyl Trimethicone, Neopentyl Glycol Diheptanoate, Niacinamide, Hydroxyethyl Urea, Lauryl PEG-9 Polydimethylsiloxyethyl Dimethicone, Glycerin, Sodium Polyaspartate, Ascorbyl Glucoside, Phytosphingosine, Palmitoyl Hexapeptide-12, Sodium Hyaluronate, Resveratrol, Acetyl Hexapeptide-8, Caffeine, Magnesium Ascorbyl Phosphate, Tetrahexyldecyl Ascorbate, Polygonum Cuspidatum Root Extract, Tocopheryl Acetate, PEG-10 Dimethicone, Triethyl Citrate, Sigesbeckia Orientalis (St. Paul Wort) Extract, Micrococcus Lysate, Isopropyl Isostearate, PPG-15 Stearyl Ether, Salicylic Acid, Trihydroxystearin, Caprylyl Glycol, Sorbitol, Trehalose, Silica, Dimethicone/PEG-10/15 Crosspolymer, Xanthan Gum, Magnesium Aluminum Silicate, Lecithin, Triethoxycaprylylsilane, Zinc Stearate, Laureth-7, PEG-8, Ammonium Acryloyldimethyltaurate/VP Copolymer, Glyceryl Polymethacrylate, Alumina, Propylene Glycol Caprylate, Polysilicone-11, Disteardimonium Hectorite, Citric Acid, Hexylene Glycol, Dipropylene Glycol, Vinyl Dimethicone/Methicone Silsesquioxane Crosspolymer, Sodium Chloride, Sodium Hydroxide, BHT, Disodium EDTA, Sodium Citrate, Potassium Sorbate, Phenoxyethanol, [+/- Mica, Titanium Dioxide (CI 77891), Iron Oxides (CI 77491), Iron Oxides (CI 77492), Iron Oxides (CI 77499), Bismuth Oxychloride (CI 77163), Ultramarines (CI 77007), Chromium Oxide Greens (CI 77288)].'] | M4: 29 | P4: 0 | Q4: 0 | R4: 1 | S4: 0 | T4: 0 | U4: ['Natural Finish', 'Hyaluronic Acid', 'Vitamin C', 'Good for: Dark Circles', 'Long-wearing', 'Niacinamide'] | V4: Makeup | W4: Face | X4: Face Primer | Y4: 1 | Z4: 29 | AA4: 29 | AC4: 0.00057713968
A5: P422093 | B5: Bloom Eau de Parfum For Her | C5: 1063 | D5: Gucci | E5: 69220 | F5: 4.1913 | G5: 1317 | H5: 1.6 oz/ 50 mL | I5: Size + Concentration + Formulation | J5: 1.6 oz/ 50 mL Eau de Parfum Spray | L5: ['Alcohol Denat., Fragrance, Water, Ethylhexyl Methoxycinnamate, Diethylamino Hydroxybenzoyl Hexyl Benzoate, Bht, Linalool, Benzyl Alcohol, Cinnamal, Hydroxycitronellal, Citronellol, Geraniol, Eugenol, Isoeugenol, Farnesol, Benzyl Benzoate, Hexyl Cinnamal, Citral.'] | M5: 123 | P5: 0 | Q5: 0 | R5: 0 | S5: 0 | T5: 0 | U5: ['Floral Scent', 'Layerable Scent'] | V5: Fragrance | W5: Women | X5: Perfume | Y5: 3 | Z5: 155 | AA5: 38 | AC5: 0.00088413043
A6: P9549 | B6: ALLURE Eau de Parfum | C6: 1065 | D6: CHANEL | E6: 7564 | F6: 4.3077 | G6: 26 | H6: 1.7 oz | I6: Size | J6: 1.7 oz | L6: ['Alcohol, Fragrance, Water, Linalool, Benzyl Salicylate, Limonene, Hexyl Cinnamal, Hydroxycitronellal, Citronellol, Geraniol, Alpha-Isomethyl Ionone, Coumarin, Citral, Benzyl Benzoate, Farnesol, Benzyl Alcohol, Amyl Cinnamal, Isoeugenol, Eugenol, Ethylhexyl Methoxycinnamate, Butyl Methoxydibenzoylmethane, Ethylhexyl Salicylate, Ci 14700 (Red 4), Ci 42090 (Blue 1), Ci 15985 (Yellow 6), Ci 19140 (Yellow 5), Il18-1.'] | M6: 122 | P6: 0 | Q6: 0 | R6: 0 | S6: 0 | T6: 0 | V6: Fragrance | W6: Women | X6: Perfume | Y6: 0 | AC6: 0.0010133058
A7: P408230 | B7: V-Facial Instant Depuffing Face Mask | C7: 2082 | D7: Clarins | E7: 26393 | F7: 4.7547 | G7: 159 | H7: 2.5 oz/ 74 mL | I7: Size | J7: 2.5 oz/ 74 mL | L7: ['Water, Glycerin, Kaolin, Alcohol, Cetearyl Ethylhexanoate, Cetearyl Alcohol, Betaine, Cetyl Alcohol, Polymethyl Methacrylate, Butylene Glycol, Caffeine, Glyceryl Stearate, Ci 77891/Titanium Dioxide, Gellan Gum, Dimethicone, Phenoxyisopropanol, Escin, Ethylhexylglycerin, Sodium Cetearyl Sulfate, Sodium Lauryl Sulfate, Sodium Acrylates Copolymer, Hydrogenated Polyisobutene, Disodium Edta, Zingiber Zerumbet Extract, Parfum/Fragrance, Phospholipids, Polyglyceryl-10 Stearate, Helianthus Annuus (Sunflower) Seed Oil, Tromethamine, Alumina, Ethylene Brassylate, Xylitol, Alchemilla Vulgaris Extract, Callicarpa Japonica Fruit Extract.'] | M7: 67 | P7: 0 | Q7: 0 | R7: 0 | S7: 0 | T7: 0 | U7: ['Good for: Dullness/Uneven Texture', 'Good for: Loss of firmness', 'Without Phthalates', 'Without Parabens', 'Best for Dry, Combo, Normal Skin'] | V7: Skincare | W7: Masks | X7: Face Masks | Y7: 0 | AC7: 0.001130951
A8: P500716 | B8: 10 Day Results Kit | C8: 6018 | D8: Algenist | E8: 3206 | F8: 4.8023 | G8: 258 | L8: ['GENIUS Liquid Collagen:', 'Collagen (Vegan), Water (Aqua, Eau), Propanediol, Isononyl Isononanoate, Butylene Glycol, Glycerin, Betaine, Pentylene Glycol, Dextrin Palmitate, Collagen Amino Acids (Vegan), Parachlorella Beijerinckii Exopolysaccharides, Chlorella Protothecoides Oil, Helichrysum Stoechas Flower Extract, Cylindrotheca Fusiformis Extract, Niacinamide, Tocopherol, Palmitoyl Tripeptide-1, Palmitoyl Tetrapeptide-7, Adenosine, Helianthus Annuus (Sunflower) Seed Oil, Leuconostoc/Radish Root Ferment Filtrate, Caprylic/Capric Triglyceride, Palmitic Acid, Disodium EDTA, Carbomer, Sodium Lactate, Amodimethicone, Homosalate, Polysorbate 20, Butyl Methoxydibenzoylmethane, 1,2-Hexanediol, Caprylyl Glycol, Octocrylene, Sodium Hydroxide, Phenoxyethanol, Fragrance (Parfum), Limonene, Beta-Carotene (CI 40800).', 'Triple Algae Eye Renewal Balm with Multi-Peptide Complex:', 'Aqua (Water/Eau), Stearic Acid, Isopropyl Isostearate, Dimethicone, Glycerin, Pentylene', 'Glycol, Glyceryl Stearate SE, Cetearyl Alcohol, Butyrospermum Parkii (Shea) Butter, C12-15 Alkyl Benzoate, Limnanthes Alba (Meadowfoam) Seed Oil, Parachlorella Beijerinckii Exopolysaccharides, Corallina Officinalis Extract, Dunaliella Salina Extract, Undaria Pinnatifida Extract, Dipeptide-2, Palmitoyl Tetrapeptide-7, Palmitoyl Hexapeptide-12, Palmitoyl Tripeptide-5, Sodium Hyaluronate, Caffeine, Coffea Arabica (Coffee) Seed Oil, Tribehenin, Ceramide NG, PEG-10 Phytosterol, Tetrahexyldecyl Ascorbate, Aloe Barbadensis Leaf Juice, Tocopheryl Acetate, Bambusa Vulgaris Leaf/Stem Extract, Pisum Sativum (Pea)', 'Extract, Glucosamine HCl, Leuconostoc/Radish Root Ferment Filtrate, Camellia Sinensis Leaf Extract, Cucumis Sativus (Cucumber) Fruit Extract, Dimethicone Crosspolymer, Panthenol, Pantolactone, Caprylyl/Capryl Glucoside, Pfaffia Paniculata Root Extract, Ptychopetalum Olacoides Bark/Stem Extract, Lilium Candidum Flower Extract, Rubus Idaeus (Raspberry) Leaf Extract, Aloe Barbadensis Leaf Juice Powder, Vinyl Dimethicone/Methicone Silsesquioxane Crosspolymer, Phospholipids, Ceteareth-20, Acrylates/C10-30 Alkyl Acrylate Crosspolymer, Disodium EDTA, Aminomethyl Propanol, Caprylyl Glycol, Lactic Acid, Ethylhexylglycerin, Hexylene Glycol, Hesperidin Methyl Chalcone, Steareth-20, Citric Acid, Sodium Citrate, Chlorhexidine Digluconate, Phenoxyethanol, Potassium Sorbate, Benzyl Alcohol, Sodium Benzoate.', 'GENIUS Ultimate Anti-Aging Cream:', 'Water (Aqua, Eau), Caprylic/Capric Triglyceride, Hydrogenated Polyisobutene, Glycerin, Chlorella Protothecoides Oil, Dimethicone, Butylene Glycol, Glyceryl Stearate, PEG-100 Stearate, Butyrospermum Parkii (Shea) Butter, Pentylene Glycol, Potassium Cetyl Phosphate, Parachlorella Beijerinckii Exopolysaccharides, Collagen (Vegan), Ceramide NP, Cynara Scolymus (Artichoke) Leaf Extract, Retinyl Palmitate, Astragalus Membranaceus Root Extract, Atractylodes Macrocephala Root Extract, Iris Florentina Root Extract, Bupleurum Falcatum Root Extract, Copper Lysinate/Prolinate, Methylglucoside Phosphate, Stearalkonium Bentonite, Acrylates/C10-30 Alkyl Acrylate Crosspolymer, Silica, Caprylyl Glycol, Sodium Hydroxide, Disodium EDTA, Ethylhexylglycerin, Cetyl Alcohol, Propylene Carbonate, Quartz, Phenoxyethanol, Leuconostoc/Radish Root Ferment Filtrate, Chlorphenesin, Fragrance (Parfum), Coumarin.'] | M8: 88 | N8: 142 | P8: 0 | Q8: 0 | R8: 0 | S8: 0 | T8: 1 | U8: ['Vegan', 'Good for: Loss of firmness', 'Good for: Dark Circles', 'Collagen', 'Hydrating', 'Good for: Anti-Aging'] | V8: Skincare | W8: Value & Gift Sets | Y8: 0 | AC8: 0.0012250293
A9: P502274 | B9: Paper- Personal | C9: 7095 | D9: Commodity | E9: 664 | F9: 3.5455 | G9: 11 | H9: 3.4 oz / 100 mL | I9: Size + Concentration + Formulation | J9: 3.4 oz / 100 mL perfume spray | L9: ['SD Alcohol 40-B (Alcohol Denat.), Parfum/Fragrance, Aqua/Water/Eau.'] | M9: 135 | P9: 0 | Q9: 0 | R9: 0 | S9: 0 | T9: 1 | U9: ['Vegan', 'Unisex/ Genderless Scent', 'Clean at Sephora', 'Cruelty-Free'] | V9: Fragrance | W9: Women | X9: Perfume | Y9: 1 | Z9: 25 | AA9: 25 | AC9: 0.0012972529
A10: P462706 | B10: Epic Curl Vegan Lash Primer | C10: 5905 | D10: KVD Beauty | E10: 2352 | F10: 2.9355 | G10: 31 | L10: ['Aqua/Water/Eau, Hydrogenated Olive Oil Stearyl Esters, Bambusa Arundinacea Stem Extract, Cera, Carnauba/Copernicia, Cerifera (Carnauba) Wax/Cire De Carnauba, Oryza Sativa Cera/Oryza Sativa (Rice) Bran Wax, Glyceryl Stearate, Helianthus Annuus Seed Cera/Helianthus Annuus (Sunflower) Seed Wax, Bis-Diglyceryl Polyacyladipate-2, Acacia Senegal Gum, Stearic Acid, Propanediol, Palmitic Acid, Aminomethyl Propanol, Hydrolyzed Jojoba Esters, Phenoxyethanol, Sodium Dehydroacetate, Galactoarabinan, Jojoba Esters, Xanthan Gum, Ethylhexylglycerin, Talc, Kaolin, Tocopherol, Ultramarines (Ci 77007), Iron Oxides (Ci 77499), Ferric Ammonium Ferrocianide (Ci 77510).'] | M10: 24 | P10: 0 | Q10: 0 | R10: 0 | S10: 0 | T10: 0 | U10: ['Vegan', 'Liquid Formula', 'Curling'] | V10: Makeup | W10: Eye | X10: Mascara | Y10: 0 | AC10: 0.0013004317
A11: P376726 | B11: Maracuja Oil | C11: 5648 | D11: tarte | E11: 79986 | F11: 4.396 | G11: 2419 | H11: 1.7 oz/ 50 mL | I11: Size | J11: 1.7 oz/ 50 mL | L11: ['Passiflora Edulis Seed Oil, Citrus Paradisi (Grapefruit) Peel Oil, Limonene, Tocopherol, Oryza Sativa (Rice) Bran Extract, Helianthus Annuus (Sunflower) Extract, Rosmarinus Officinalis (Rosemary) Leaf Extract, Citral, Linalool.'] | M11: 48 | P11: 0 | Q11: 0 | R11: 0 | S11: 0 | T11: 0 | V11: Skincare | W11: Moisturizers | X11: Face Oils | Y11: 1 | Z11: 16 | AA11: 16 | AC11: 0.0014339801
A12: P504146 | B12: Sunday Scalp Reset Foam Pre Shampoo | C12: 5995 | D12: Bumble and bumble | E12: 292 | F12: 4.766 | G12: 47 | H12: 3.5 oz / 150 mL | I12: Size | J12: 3.5 oz / 150 mL | L12: ['Butane, Water/Aqua/Eau, Alcohol Denat., Isobutane, Glycerin, Butylene Glycol, Dimethicone, Fragrance (Parfum), Caprylic/Capric Triglyceride, PPG-8-Ceteth-20, Salicylic Acid, Caffeine, Epilobium Angustifolium Flower/Leaf/Stem Extract, Sodium Lauroamphoacetate, Panthenol, Tocopheryl Acetate, Punica Granatum (Pomegranate) Extract, Honey Extract/Mel/Extrait De Miel, Leuconostoc/Radish Root Ferment Filtrate, Wheat Amino Acids, Aloe Barbadensis Leaf Juice, Gellidiella Acerosa Extract, Hypnea Musciformis (Algae) Extract, Sargassum Filipendula (Algae) Extract, Citrus Tangerina (Tangerine), Zingiber Officinale (Ginger) Root Extract, Rice Amino Acids, Glyceryl Polyacrylate, Hydroxyethylcellulose, Biotin, Cellulose, Cocamide Mipa, Sodium Lauroyl Methyl Isethionate, Citric Acid, Linalool, Benzyl Salicylate, Citronellol, Limonene, Alpha-Isomethyl Ionone, Phenoxyethanol, Sodium Benzoate.'] | M12: 34 | P12: 0 | Q12: 0 | R12: 0 | S12: 0 | T12: 1 | U12: ['Good for: Color Care', 'Salicylic Acid', 'Without Sulfates SLS & SLES', 'Good for: Oily Scalp', 'Cruelty-Free'] | V12: Hair | W12: Hair Styling & Treatments | X12: Scalp Treatments | Y12: 0 | AC12: 0.0015458561
A13: P462356 | B13: Mini Honey Infused Hair Perfume | C13: 6328 | D13: Gisou | E13: 70086 | F13: 4.0824 | G13: 425 | H13: 1.7 oz/ 50 mL | I13: Size | J13: 1.7 oz/ 50 mL | L13: ['Alcohol Denat., Parfum (Fragrance), Aqua (Water, Eau), Mel (Honey, Miel)*, Argania Spinosa Kernel Oil, Sodium Benzotriazolyl Butylphenol Sulfonate, Tris(Tetramethylhydroxypiperidinol) Citrate, Citral**, Coumarin**, Linalool**, Hexyl Cinnamal**, Limonene**, CI 19140 (Yellow 5), CI 14700 (Red 4).'] | M13: 44 | P13: 0 | Q13: 0 | R13: 0 | S13: 0 | T13: 0 | U13: ['Layerable Scent', 'Fresh Scent', 'Clean at Sephora', 'All Hair Types', 'Good for: Frizz'] | V13: Hair | W13: Hair Styling & Treatments | X13: Hair Styling Products | Y13: 0 | AC13: 0.0016757512
A14: P462386 | B14: Drying Cream | C14: 8017 | D14: Mario Badescu | E14: 1635 | F14: 3.75 | G14: 4 | H14: 0.5 oz/ 14 g | I14: Size | J14: 0.5 oz/ 14 g | L14: ['Aqua (Water, Eau), Zinc Oxide, Cetyl Alcohol, Aloe Barbadensis Leaf Juice, Cera Alba (Beeswax, Cire dÂ´abeille), Polysorbate 80, Glycerin, Ethylhexyl Palmitate, Propylene Glycol, Sulfur, Oleth-10, Paraffinum Liquidum (Mineral Oil, Huile MinÃ©rale), Ichthammol, Hydrolyzed Yeast Protein, Triticum Vulgare (Wheat) Starch, Arctium Lappa Root Extract, Cysteine, Niacinamide, Panthenol, Nasturtium Officinale Flower/Leaf Extract, Citrus Limon (Lemon) Fruit Extract, Allantoin, Biotin, Arginine, Leucine, Lysine, Tyrosine, Valine, Glutamic Acid, Cellulose Gum, Polysorbate 20, Maltodextrin, Zinc Chloride, Glyceryl Acrylate/Acrylic Acid Copolymer, Pyridoxine HCl, Parfum (Fragrance), Sodium Chloride, Methylparaben, Propylparaben, Potassium Sorbate, Citric Acid, Sodium Benzoate, Chlorphenesin, Disodium EDTA, Phenoxyethanol, Benzyl Benzoate, Alpha-Isomethyl Ionone, Limonene, Linalool, CI 77891 (Titanium Dioxide).'] | M14: 17 | P14: 0 | Q14: 0 | R14: 1 | S14: 0 | T14: 0 | V14: Skincare | W14: Treatments | X14: Blemish & Acne Treatments | Y14: 0 | AC14: 0.0017300769
A15: P437657 | B15: Scalp Care Dry Scalp Treatment | C15: 5936 | D15: Living Proof | E15: 33713 | F15: 4.301 | G15: 309 | H15: 3.4 oz/ 100 mL | I15: Size | J15: 3.4 oz/ 100 mL | L15: ['Water/Eau/Aqua, Glycerin, Niacinamide, Sodium Hyaluronate, Trehalose, Urea, Serine, Algin, Pentylene Glycol, Pullulan, Lecithin, Glyceryl Polyacrylate, C13-15 Alkane, Caprylyl Glycol, Disodium Phosphate, Potassium Phosphate, Hydroxyethyl Acrylate/Sodium Acryloyldimethyl Taurate Copolymer, Hydroxyacetophenone, Caesalpinia Spinosa Gum, Sclerotium Gum, Xanthan Gum, Isohexadecane, Ethylhexylglycerin, Polysorbate 60, Fragrance/Parfum.'] | M15: 37 | P15: 0 | Q15: 0 | R15: 0 | S15: 0 | T15: 0 | U15: ['Vegan', 'All Hair Types', 'Without Parabens', 'Without Silicones', 'Without Sulfates SLS & SLES', 'Good for: Flaky/Dry Scalp'] | V15: Hair | W15: Hair Styling & Treatments | X15: Scalp Treatments | Y15: 0 | AC15: 0.001922603
A16: P457245 | B16: Rose Perfecto Tinted Liquid Balm | C16: 1133 | D16: Givenchy | E16: 62416 | F16: 4.3079 | G16: 367 | H16: .2 oz/ 6mL | I16: Color | J16: 001 Pink Irresistible | K16: transparent pink, custom to your PH | L16: ['C10-30 Cholesterol/Lanosterol Esters, Isononyl Isononanoate, Polyglyceryl-2 Triisostearate, Hydrogenated Polyisobutene, Pentaerythrityl Tetraisostearate, Copernicia Cerifera (Carnauba) Wax, Ethylene/Propylene/Styrene Copolymer, Glyceryl Behenate/Eicosadioate, Ethylhexyl Palmitate, Butyrospermum Parkii (Shea) Butter, Butyrospermum Parkii (Shea) Butter Unsaponifiables, Menthoxypropanediol, Parfum (Fragrance), Butylene/Ethylene/Styrene Copolymer, Diisostearyl Malate, Ascorbyl Tetraisopalmitate, Trimethylolpropane Triisostearate, Pentaerythrityl Tetra-Di-T-Butyl Hydroxyhydrocinnamate, Trihydroxystearin, Schinus Terebinthifolius Seed Extract, Tocopherol, Sodium Hyaluronate, Propyl Gallate, [+/- Ci 77499 (Iron Oxides), Ci 77891 (Titanium Dioxide), Ci 45410 (Red 27), Ci 15850 (Red 6 - Red 7)].'] | M16: 38 | P16: 0 | Q16: 0 | R16: 0 | S16: 0 | T16: 0 | U16: ['Radiant Finish', 'Hyaluronic Acid', 'Liquid Formula', 'Plumping', 'Vitamin C', 'Hydrating'] | V16: Makeup | W16: Lip | X16: Lip Balm & Treatment | Y16: 5 | Z16: 38 | AA16: 38 | AC16: 0.0021800229
A17: P505364 | B17: Afterglow Sensual Shine Hydrating Lipstick | C17: 3976 | D17: NARS | E17: 688 | H17: .05 oz / 1.5 g | I17: Color | J17: ORGASM | L17: ['Tridecyl Trimellitate, Hydrogenated Polyisobutene, Phenylpropyldimethylsiloxysilicate, Synthetic Wax, Mica, Ricinus Communis (Castor) Seed Oil, Hydrogenated Vegetable Oil, Polyethylene, Diisostearyl Malate, Diglyceryl Sebacate/Isopalmitate, Dimethicone, Dicalcium Phosphate, Phytosteryl/Isostearyl/Cetyl/Stearyl/Behenyl Dimer Dilinoleate, Gardenia Taitensis Flower Extract, Moringa Oleifera Seed Extract, Polyhydroxystearic Acid, Isopropyl Myristate, Isostearic Acid, Ethylhexyl Palmitate, Lecithin, Polyglyceryl-3 Polyricinoleate, Triethoxycaprylylsilane, Polysilicone-11, Butyrospermum Parkii (Shea) Butter, Ethylene/Propylene Copolymer, Pentaerythrityl Tetra-Di-T-Butyl Hydroxyhydrocinnamate, Tocopherol, Water/Aqua/Eau, Collagen, Leuconostoc/Radish Root Ferment Filtrate, Hydrogenated Coco-Glycerides, Sodium Hyaluronate, Hydrogenated Castor Oil, Tocopheryl Acetate, Cocos Nucifera (Coconut) Oil, Simmondsia Chinensis (Jojoba) Seed Oil, Mangifera Indica (Mango) Seed Butter, Olea Europaea (Olive) Fruit Oil, Caprylyl Glycol, Glyceryl Caprylate, Glycerin, [+/-(May Contain/Peut Contenir): Iron Oxides (Ci 77491, Ci 77492, Ci 77499), Red 7 Lake (Ci 15850), Titanium Dioxide (Ci 77891), Yellow 5 Lake (Ci 19140)].'] | M17: 32 | P17: 0 | Q17: 1 | R17: 0 | S17: 1 | T17: 0 | U17: ['Stick Formula', 'High Shine Finish', 'Hydrating', 'Oil Free', 'Without Parabens'] | V17: Makeup | W17: Lip | X17: Lipstick | Y17: 9 | Z17: 32 | AA17: 32 | AC17: 0.0022873437
A18: P417107 | B18: The Moisturizing Soft Lotion | C18: 6201 | D18: La Mer | E18: 4580 | F18: 4.0704 | G18: 71 | H18: 1.7 oz/ 50 mL | I18: Size | J18: 1.7 oz/ 50 mL | L18: ['Algae (Seaweed) Extract, Petrolatum, Isocetyl Stearoyl Stearate, Butyrospermum Parkii (Shea Butter), Butylene Glycol, Cyclopentasiloxane, Dimethicone, Glyceryl Stearate, Cetyl Esters, Phenyl Trimethicone, Diethylhexyl Succinate, Cyclohexasiloxane, Cholesterol, Steareth-10, Glyceryl Stearate Se, Polysilicone-11, Sesamum Indicum (Sesame) Seed Oil, Medicago Sativa (Alfalfa) Seed Powder, Helianthus Annuus (Sunflower) Seedcake, Prunus Amygdalus Dulcis (Sweet Almond) Seed Meal, Eucalyptus Globulus (Eucalyptus) Leaf Oil, Sodium Gluconate, Copper Gluconate, Calcium Gluconate, Magnesium Gluconate, Zinc Gluconate, Tocopheryl Succinate, Niacin, Sesamum Indicum (Sesame) Seed Powder, Water\\Aqua\\Eau, Salicornia Herbacea Extract, Sigesbeckia Orientalis (St. Paul Wort) Extract, Citrus Aurantifolia (Lime) Peel Extract, Sea Salt\\Maris Sal\\Sel Marin, Chlorella Vulgaris Extract, Hydrolyzed Rice Extract, Micrococcus Lysate, Laminaria Digitata Extract, Plankton Extract, Caffeine, Glucose Oxidase, Trehalose, Sucrose, Acetyl Hexapeptide-8, Lactoperoxidase, Hydrolyzed Algin, Glyceryl Dilaurate, Alcaligenes Polysaccharides, Isohexadecane, Caprylic/Capric Triglyceride, Dipalmitoyl Hydroxyproline, Distearyldimonium Chloride, Glycerin, Tocopheryl Acetate, Steareth-21, Polyquaternium-51, Saccharide Isomerate, Tetrahexyldecyl Ascorbate, Sodium Pca, Urea, Glucose, Polysorbate 80, Sodium Hyaluronate, Cetyl Alcohol, Alcohol Denat., Acrylamide/Sodium Acryloyldimethyltaurate Copolymer, Fragrance (Parfum), Lecithin, BHT, Linalool, Citronellol, Hydroxycitronellal, Geraniol, Limonene, Benzyl Salicylate, Phenoxyethanol.'] | M18: 320 | P18: 0 | Q18: 0 | R18: 0 | S18: 0 | T18: 0 | U18: ['Best for Combination Skin', 'Good for: Pores', 'Without Sulfates SLS & SLES', 'Without Parabens', 'Without Phthalates'] | V18: Skincare | W18: Moisturizers | X18: Moisturizers | Y18: 0 | AC18: 0.0023807333
A19: P467973 | B19: Intensive Eye Renewal Cream with Firming Peptides | C19: 6314 | D19: Shani Darden Skin Care | E19: 12224 | F19: 4.2087 | G19: 254 | H19: 0.5 oz/ 15 mL | I19: Size | J19: 0.5 oz/ 15 mL | L19: ['Water (Aqua), Caprylic/Capric Triglyceride, Diheptyl Succinate, Capryloyl Glycerin/Sebacic Acid Copolymer, Butyrospermum Parkii (Shea Butter), Albizia Julibrissin Bark Extract, Darutoside, Cetearyl Alcohol, Pentylene Glycol, Glycerin, Niacinamide, Castanea Sativa (Chestnut) Seed Extract, Sorbitan Stearate, Glyceryl Stearate, PEG-100 Stearate, Hydroxyethyl Acrylate/Sodium Acryloyldimethyl Taurate Copolymer, Hydrolyzed Pea Protein, Lecithin, Olea Europaea (Olive) Fruit Oil, Phytosterols, Squalane, Ceramide NP, Propanediol, Physalis Angulata Extract, Tocopheryl (Vitamin E) Acetate, Cucumis Sativus (Cucumber) Fruit Extract, Tetrasodium Glutamate Diacetate, Phenoxyethanol, Ethylhexylglycerin, Chlorphenesin.'] | M19: 68 | P19: 0 | Q19: 0 | R19: 0 | S19: 0 | T19: 1 | V19: Skincare | W19: Eye Care | X19: Eye Creams & Treatments | Y19: 0 | AC19: 0.002448324
A20: P454967 | B20: Amalfi Lemon & Mint Reed Diffuser | C20: 7025 | D20: NEST New York | E20: 1829 | F20: 4.4444 | G20: 9 | H20: 5.9 oz/ 175 mL | I20: Size + Concentration + Formulation | J20: 5.9 oz/ 175 mL diffuser | M20: 58 | P20: 0 | Q20: 0 | R20: 0 | S20: 0 | T20: 0 | V20: Fragrance | W20: Candles & Home Scents | X20: Diffusers | Y20: 0 | AC20: 0.0025401527
A21: P504363 | B21: Lip Snatcher Hydrating Liquid Lipstick and Lip Gloss Duo | C21: 6326 | D21: ONE/SIZE by Patrick Starrr | E21: 18228 | F21: 4.297 | G21: 165 | H21: .24 oz / 7 mL | I21: Color | J21: Joelapuss | K21: pearlescent & matte medium pink | L21: ['CrÃ©me:', 'Isododecane, Octyldodecanol, Dicalcium Phosphate, Silica, Hydrogenated Styrene/Isoprene Copolymer, Synthetic Fluorphlogopite, Trimethylsiloxysilicate, Disteardimonium Hectorite, Ethyl Vanillin, Tocopheryl Acetate, Gossypium Herbaceum (Cotton) Seed Oil, Helianthus Annuus (Sunflower) Seed Oil, Pentaerythrityl Tetra-Di-T-Butyl Hydroxyhydrocinnamate, Ricinus Communis (Castor) Seed Oil, Hydrolyzed Sodium Hyaluronate, Sodium Hyaluronate, Hydrogenated Castor Oil, Lupinus Albus Seed Extract, Tocopherol. May Contain/Peut Contenir (Â±): Red 7 Lake (CI 15850), Titanium Dioxide (CI 77891), Red 28 Lake (CI 45410), Yellow 6 Lake (CI 15985), Iron Oxides (CI 77491, CI 77492), Blue 1 Lake (CI 42090).', 'Gloss:', 'Polybutene, Octyldodecanol, Hydrogenated Polyisobutene, Silica Dimethyl Silylate, Calcium Sodium Borosilicate, VP/Hexadecene Copolymer, Hydrogenated Styrene/Isoprene Copolymer, Caprylic/Capric Triglyceride, Ethyl Vanillin, Tocopheryl Acetate, Synthetic Fluorphlogopite, Pentaerythrityl Tetra-Di-T-Butyl Hydroxyhydrocinnamate, Dicalcium Phosphate, Tin Oxide, Helianthus Annuus (Sunflower) Seed Oil, Ricinus Communis (Castor) Seed Oil, Hydrolyzed Sodium Hyaluronate, Sodium Hyaluronate, Hydrogenated Castor Oil, Lupinus Albus Seed Extract, Jasminum Officinale (Jasmine) Flower Extract, Tocopherol. May Contain/Peut Contenir (Â±): Titanium Dioxide (CI 77891), Iron Oxides (CI 77491, CI 77492), Red 7 Lake (CI 15850), Yellow 5 (CI 19140), Blue 1 Lake (CI 42090).'] | M21: 28 | P21: 0 | Q21: 1 | R21: 0 | S21: 0 | T21: 1 | U21: ['Vegan', 'Liquid Formula', 'Hydrating', 'Long-wearing', 'Cruelty-Free'] | V21: Makeup | W21: Lip | X21: Lipstick | Y21: 7 | Z21: 28 | AA21: 28 | AC21: 0.0025421695
A22: P484044 | B22: The Body Duo Mini Body Scrub + Moisturizer Essentials | C22: 6352 | D22: Fenty Skin | E22: 10700 | F22: 4.2 | G22: 5 | L22: ['Buff Ryder Mini Exfoliating Body Scrub:', 'Sucrose, Glycine Soja (Soybean) Oil, Helianthus Annuus Hybrid Oil (Helianthus Annuus (Sunflower) Seed Oil), Sea Salt/Maris Sal/Sel Marin, Cocos Nucifera (Coconut) Oil, Butyrospermum Parkii (Shea) Butter, Polyglyceryl-3 Caprate, Silica, Helianthus Annuus (Sunflower) Seed Oil, Caprylic/Capric Triglyceride, Trihydroxystearin, Styrene/Butadiene Copolymer, Persea Gratissima (Avocado) Fruit Powder, Lactobacillus/Punica Granatum Fruit Ferment Extract, Papain, Bromelain, Quartz, Tocopherol, Citric Acid, Pumice, Caprylyl Glycol, Maltodextrin, Phenoxyethanol, Pentaerythrityl Tetra-Di-T-Butyl Hydroxyhydrocinnamate, Parfum/Fragrance, Hydroxycitronellal, Limonene.', 'Butta Drop Mini Whipped Oil Body Cream:', 'Aqua/Water/Eau, Cocos Nucifera (Coconut) Oil, Glycerin, Caprylic/Capric Triglyceride, Oryza Sativa (Rice) Bran Oil, Propanediol, Cetearyl Alcohol, Cetyl Ethylhexanoate, Dimethicone, Butyrospermum Parkii (Shea) Butter, Mangifera Indica (Mango) Seed Butter, Cetearyl Olivate, Diisostearyl Malate, Polyglyceryl-3 Methylglucose Distearate, Citrullus Lanatus (Watermelon) Seed Oil, Hibiscus Sabdariffa Seed Oil, Adansonia Digitata Seed Oil, Malpighia Punicifolia (Acerola) Fruit Extract, Adansonia Digitata Fruit Extract, Helianthus Annuus (Sunflower) Seed Oil, Simmondsia Chinensis (Jojoba) Seed Oil, Plumeria Acutifolia Flower Extract, Aloe Barbadensis Leaf Juice, Sodium Hyaluronate, Glycine Soja (Soybean) Oil, Tocopheryl Acetate, Tocopherol, Sorbitan Olivate, Polysorbate 60, Potassium Cetyl Phosphate, Acrylates/C10-30 Alkyl Acrylate Crosspolymer, Ethylhexylglycerin, Ethyl Hexanediol, Butylene Glycol, Caprylyl Glycol, Tromethamine, Phenoxyethanol, Parfum/Fragrance, Benzyl Salicylate, Hexyl Cinnamal, Limonene, Linalool.'] | M22: 32 | O22: 24 | P22: 1 | Q22: 0 | R22: 1 | S22: 0 | T22: 1 | U22: ['Vegan', 'Good for: Dullness/Uneven Texture', 'Hydrating', 'Clean at Sephora', 'Good for: Dryness'] | V22: Bath & Body | W22: Value & Gift Sets | Y22: 0 | AC22: 0.0025488118
A23: P502044 | B23: Mini Sparkling Cuvee Glass Jar Candle | C23: 6245 | D23: VOLUSPA | E23: 1158 | F23: 4.1667 | G23: 6 | H23: 5.5 oz / 156 g | I23: Size + Concentration + Formulation | J23: 5.5 oz / 156 g | M23: 20 | P23: 0 | Q23: 0 | R23: 0 | S23: 0 | T23: 0 | U23: ['Vegan', 'Without Phthalates', 'Without Parabens', 'Without Sulfates SLS & SLES', 'Cruelty-Free'] | V23: Fragrance | W23: Candles & Home Scents | X23: Candles | Y23: 0 | AC23: 0.0026192354
A24: P472340 | B24: Tea Tree Essential Oil | C24: 8020 | D24: SUNDAY II SUNDAY | E24: 2734 | F24: 4.25 | G24: 4 | H24: 1 oz/ 30 mL | I24: Size | J24: 1 oz/ 30 mL | L24: ['100% Pure Tea Tree Oil.'] | M24: 15 | P24: 0 | Q24: 0 | R24: 1 | S24: 0 | T24: 0 | U24: ['Vegan', 'All Hair Types', 'Good for: Frizz', 'Good for: Dryness', 'Without Parabens'] | V24: Hair | W24: Hair Styling & Treatments | X24: Hair Oil | Y24: 0 | AC24: 0.0026539865
A25: P434452 | B25: VIP Strong Hold Texturizing Hair Spray | C25: 6259 | D25: KÃ©rastase | E25: 5128 | F25: 3.8519 | G25: 27 | H25: 6.8 oz/ 193 g | I25: Size | J25: 6.8 oz/ 193 g | L25: ['Hydrofluorocarbon 152a, Alcohol Denat, Butane, Calcium Carbonate, Polyvinylcaprolactam, Disteardimonium Hectorite, Dimethicone, Fragrance, Dimethiconol, Benzyl Salicylate, Limonene, Benzyl Alcohol, Linalool, Citronellol, Geraniol, Hexyl Cinnamal, Hydroxycitronellal, Alpha-Isomethyl Ionone.'] | M25: 32 | P25: 0 | Q25: 0 | R25: 0 | S25: 1 | T25: 1 | U25: ['Good for: Volume', 'All Hair Types', 'Good for: Frizz'] | V25: Hair | W25: Hair Styling & Treatments | X25: Hair Spray | Y25: 0 | AC25: 0.0027013753
A26: P468829 | B26: Blond Absolu Strengthening Hair Oil for Very Damaged Blonde Hair | C26: 6259 | D26: KÃ©rastase | E26: 14239 | F26: 4.6159 | G26: 328 | H26: 3.4 oz/ 100 mL | I26: Size | J26: 3.4 oz/ 100 mL | L26: ['Cyclopentasiloxane, Dimethiconol, Parfum / Fragrance, Limonene, Helianthus Annuus Seed Oil / Sunflower Seed Oil, Linalool, Citronellol, Tocopherol, Leontopodium Alpinum Flower/Leaf Extract.'] | M26: 54 | P26: 0 | Q26: 0 | R26: 0 | S26: 0 | T26: 1 | U26: ['Good for: Damage', 'Floral Scent', 'All Hair Types', 'Good for: Dryness', 'Prevents Color Fading', 'Increases Shine'] | V26: Hair | W26: Hair Styling & Treatments | X26: Hair Oil | Y26: 1 | Z26: 26 | AA26: 26 | AC26: 0.0027729674
A27: P504785 | B27: Luxe Body Serum | C27: 5626 | D27: St. Tropez | E27: 1791 | F27: 4.8173 | G27: 892 | H27: 6.7 oz / 200 mL | I27: Size | J27: 6.7 oz / 200 mL | L27: ['Aqua (Water), Dihydroxyacetone, Butylene Glycol, Polysorbate 20, Trehalose, Phenoxyethanol, Hydroxyethylcellulose, Saccharide Isomerate, Panthenol, Sodium Metabisulfite, Parfum (Fragrance), Maltodextrin, Caramel, Citric Acid, Ethylhexylglycerin, Sodium Hyaluronate, Biosaccharide Gum-1, Linalool, Benzyl Salicylate, Niacinamide, Sodium Citrate, Coumarin, Limonene, Hexyl Cinnamal, Hydroxycitronellal, Geraniol, Alpha-Isomethyl Ionone, Sodium Hydroxide.'] | M27: 48 | P27: 0 | Q27: 1 | R27: 0 | S27: 0 | T27: 0 | U27: ['Vegan', 'Collagen', 'Hydrating', 'Niacinamide'] | V27: Bath & Body | W27: Body Moisturizers | X27: Body Lotions & Body Oils | Y27: 0 | AC27: 0.0027777238
A28: P479852 | B28: Melrose Place Moisturizing Body Cream | C28: 6144 | D28: OUAI | E28: 22152 | F28: 4.7096 | G28: 365 | H28: 7.5 oz/ 212 g | I28: Size | J28: 7.5 oz/ 212 g | L28: ['Aqua (Water, Eau), Caprylic/Capric Triglyceride, Phenyl Trimethicone, Cetyl Alcohol, Isododecane, Methyl Glucose Sesquistearate, Glycerin, Hydroxyethyl Acrylate/ Sodium Acryloyldimethyl Taurate Copolymer, Cocos Nucifera (Coconut) Oil, Sodium Stearoyl Glutamate, Glyceryl Stearate Citrate, Cetearyl Alcohol, Butyrospermum Parkii (Shea) Butter, Theobroma Grandiflorum Seed Butter, Lactobacillus Ferment, Squalane, Xanthan Gum, Citric Acid, Polysorbate 60, Ethylhexylglycerin, Glyceryl Caprylate, Tocopherol, Sodium Phytate, Sorbitan Isostearate, Benzophenone-4, Sodium Chloride, Alcohol, Phenoxyethanol, Parfum (Fragrance), Citronellol, Geraniol, Benzyl Salicylate, Linalool, Ci 14700 (Red 4), Ci 15985 (Yellow 6).'] | M28: 38 | P28: 0 | Q28: 0 | R28: 0 | S28: 0 | T28: 0 | U28: ['Cruelty-Free', 'Floral Scent', 'Hydrating', 'Good for: Dryness', 'Without Sulfates SLS & SLES'] | V28: Bath & Body | W28: Body Moisturizers | X28: Body Lotions & Body Oils | Y28: 0 | AC28: 0.00301315
A29: P503100 | B29: Soleil Neige Eye Color Quad | C29: 5869 | D29: TOM FORD | E29: 4436 | F29: 2.5 | G29: 4 | H29: 0.35 oz / 9.9 g | I29: Color | J29: Chalet Lust - rose golds and copper tones | L29: ['Mica, Cetearyl Ethylhexanoate, C12-20 Acid Peg-8 Ester, Hdi/Trimethylol Hexyllactone Crosspolymer, Squalane, Glycerin, Chondrus Crispus (Carrageenan), Ethylhexylglycerin, Dicalcium Phosphate, Silica, Aluminum Calcium Sodium Silicate, Synthetic Fluorphlogopite, Polysorbate 80, Tin Oxide, Caprylyl Glycol, 1,2-Hexanediol, [+/- Titanium Dioxide (Ci 77891), Iron Oxides (Ci 77491), Iron Oxides (Ci 77492), Iron Oxides (Ci 77499), Aluminum Powder (Ci 77000), Bismuth Oxychloride (Ci 77163), Blue 1 Lake (Ci 42090), Bronze Powder (Ci 77400), Carmine (Ci 75470), Chromium Hydroxide Green (Ci 77289), Chromium Oxide Greens (Ci 77288), Copper Powder (Ci 77400), Ferric Ammonium Ferrocyanide (Ci 77510), Ferric Ferrocyanide (Ci 77510), Manganese Violet (Ci 77742), Ultramarines (Ci 77007), Yellow 5 Lake (Ci 19140)].'] | M29: 90 | P29: 0 | Q29: 0 | R29: 0 | S29: 0 | T29: 0 | U29: ['Pressed Powder Formula', 'Shimmer Finish', 'Without Mineral Oil', 'Without Phthalates', 'Without Parabens', 'Without Triclosan'] | V29: Makeup | W29: Eye | X29: Eye Palettes | Y29: 1 | Z29: 90 | AA29: 90 | AC29: 0.0031015259
A30: P479342 | B30: Soft Pinch Blush Brush | C30: 6317 | D30: Rare Beauty by Selena Gomez | E30: 69220 | F30: 4.7143 | G30: 49 | M30: 23 | P30: 0 | Q30: 0 | R30: 0 | S30: 0 | T30: 1 | U30: ['Vegan', 'Cruelty-Free'] | V30: Makeup | W30: Brushes & Applicators | X30: Face Brushes | Y30: 0 | AC30: 0.0033103069
A31: P434500 | B31: Good Girl Rollerball | C31: 3155 | D31: Carolina Herrera | E31: 34288 | F31: 4.4665 | G31: 671 | H31: 0.30 oz/ 10 mL | I31: Size + Concentration + Formulation | J31: 0.30 oz/ 10 mL eau de parfum spray | L31: ['Alcohol Denat., Fragrance, Water, Linalool, Hydroxycitronellal, Benzyl Salicylate, Coumarin, Ethylhexyl Methoxycinnamate, Benzyl Benzoate, Ethylhexyl Saliclate, Butyl Methoxydibenzoylmethane, Limonen, Geraniol, Citronellol, Isoeugenol, Hexyl Cinnamal, Benzyl Alcohol, Citral, Ci 60730 (Ext. Violet 2) Alcohol Of Vegatal Origin 80%.'] | M31: 32 | P31: 0 | Q31: 0 | R31: 0 | S31: 0 | T31: 0 | V31: Fragrance | W31: Women | X31: Rollerballs & Travel Size | Y31: 0 | AC31: 0.003374984
A32: P428708 | B32: Patchouli Citrus Eau de Parfum | C32: 6238 | D32: The 7 Virtues | E32: 3882 | F32: 4.3093 | G32: 97 | H32: 1.7 oz/ 50 mL | I32: Size + Concentration + Formulation | J32: 1.7 oz/ 50 mL | L32: ['Organic Sugar Cane Alcohol Denat., Pogostemon Cablin, Water, Benzyl Alcohol, Benzyl Benzoate, Citral, Citronellol, Coumarin, Eugenol, Farnesol, Geraniol, Hydroxycitronellal, Limonene, Linalool, Lonones.'] | M32: 88 | P32: 0 | Q32: 0 | R32: 0 | S32: 0 | T32: 1 | U32: ['Vegan', 'Unisex/ Genderless Scent', 'Clean + Planet Positive', 'Without Phthalates', 'Hypoallergenic', 'Cruelty-Free'] | V32: Fragrance | W32: Women | X32: Perfume | Y32: 1 | Z32: 32 | AA32: 32 | AC32: 0.0033936965
A33: P500620 | B33: Mini Clay Play To-Go Cheek Palette | C33: 5648 | D33: tarte | E33: 25644 | F33: 4.303 | G33: 33 | L33: ['morning light:', 'Mica, Octyldodecyl Stearoyl Stearate, Synthetic Fluorphlogopite, Bis-Diglyceryl Polyacyladipate-2, Dimethicone, Pentaerythrityl Tetraisostearate, Phenoxyethanol, Silica, Ethylhexylglycerin, Tin Oxide, Kaolin, Tocopherol, Titanium Dioxide (CI 77891), Iron Oxides (CI 77491, CI 77492, CI 77499).', 'elements:', 'Mica, Octyldodecyl Stearoyl Stearate, Bis-Diglyceryl Polyacyladipate-2, Dimethicone, Pentaerythrityl Tetraisostearate, Phenoxyethanol, Silica, Ethylhexylglycerin, Tin Oxide, Kaolin, Tocopherol. (+/-): Titanium Dioxide (CI 77891), Iron Oxides (CI 77491, CI 77492, CI 77499), Red 7 Lake (CI 15850).', 'matte bronzer:', 'Mica, Dimethicone, Dimethicone/Vinyl Dimethicone Crosspolymer, Silica, Bis-Diglyceryl Polyacyladipate-2, Octyldodecyl Stearoyl Stearate, Pentaerythrityl Tetraisostearate, Phenoxyethanol, Ethylhexylglycerin, Kaolin, Tocopherol, Iron Oxides (CI 77491, CI 77492, CI 77499), Red 40 Lake (CI 16035), Titanium Dioxide (CI 77891).'] | M33: 25 | P33: 1 | Q33: 0 | R33: 0 | S33: 0 | T33: 0 | V33: Makeup | W33: Cheek | X33: Cheek Palettes | Y33: 0 | AC33: 0.0035148719
A34: P427314 | B34: Curl Control Mousse | C34: 6182 | D34: Moroccanoil | E34: 7535 | F34: 3.4146 | G34: 41 | H34: 5.1 oz/ 150 mL | I34: Size | J34: 5.1 oz/ 150 mL | L34: ['Water, Cocamidopropyl Hydroxysultaine, Polysorbate 20, Peg-40 Hydrogenated Castor Oil, Polyquaternium-72, Parfum/Fragrance, Argania Spinosa (Argan) Kernel Oil, Hydrolyzed Vegetable Protein PG-Propyl Silanetriol, Polyquaternium-11, Dipropylene Glycol, Phenoxyethanol, Tetrasodium EDTA, Citric Acid, Chlorphenesin, Polyquaternium-70, Caprylyl Glycol.'] | M34: 30 | P34: 0 | Q34: 0 | R34: 1 | S34: 0 | T34: 0 | V34: Hair | W34: Hair Styling & Treatments | X34: Hair Styling Products | Y34: 0 | AC34: 0.0036339355
A35: P471553 | B35: Legendary Conditioner | C35: 6162 | D35: IGK | E35: 1374 | F35: 4.3511 | G35: 262 | H35: 8 oz/ 236 mL | I35: Size | J35: 8 oz/ 236 mL | L35: ['Water (Aqua/Eau), Cetearyl Alcohol, Glycerin, Cetyl Esters, Butyrospermum Parkii (Shea) Butter, Behentrimonium Chloride, Fragrance (Parfum), Chondrus Crispus Extract, Eriophorum Spissum Flower/Stem Extract, Panthenol, Phenoxyethanol, Tilia Tomentosa Extract, Dimethicone, Dimethiconol, BHT, Disodium EDTA, Ethylhexylglycerin, Butyl Methoxydibenzoylmethane, Ethylhexyl Methoxycinnamate, Ethylhexyl Salicylate, Hydroxypropyltrimonium Hydrolyzed Corn Starch, Citric Acid, Sodium Hydroxide, Potassium Sorbate, Tocopherol, Sodium Benzoate, Sorbic Acid, Limonene.'] | M35: 32 | P35: 0 | Q35: 0 | R35: 0 | S35: 0 | T35: 0 | U35: ['Vegan', 'All Hair Types', 'Good for: Dryness', 'Without Parabens', 'Increases Shine'] | V35: Hair | W35: Shampoo & Conditioner | X35: Conditioner | Y35: 0 | AC35: 0.0036702977
A36: P385350 | B36: â€™REPLICAâ€™ Jazz Club | C36: 7038 | D36: Maison Margiela | E36: 62769 | F36: 4.5857 | G36: 980 | H36: 3.4 oz/ 100 mL | I36: Size + Concentration + Formulation | J36: 3.4 oz/ 100 mL | L36: ['Alcohol, Water, Fragrance, Ethylhexyl Methoxycinnamate, Coumarin, Limonene, Ethylhexyl Salicylate, Butyl Methoxydibenzoylmethane, Linalool, Citral, Geraniol, Ci 15985/Yellow 6, Cinnamal, Hydroxycitronellal, Eugenol Citronellol, Ci 19140/Yellow 5, Ci 17200/Red 33, Ci 42090/Blue 1, C162585/2.'] | M36: 160 | P36: 0 | Q36: 0 | R36: 0 | S36: 0 | T36: 0 | U36: ['Unisex/ Genderless Scent', 'Warm &Spicy Scent'] | V36: Fragrance | W36: Women | X36: Perfume | Y36: 2 | Z36: 85 | AA36: 35 | AC36: 0.0036823835
A37: P483696 | B37: Gentle Micellar Antioxidant Cleanser | C37: 6488 | D37: The Outset | E37: 3860 | F37: 4.6937 | G37: 111 | H37: 5 oz / 150 mL | I37: Size | J37: 5 oz / 150 mL | L37: ['Water (Aqua, Eau), Propanediol, Glycerin, Triheptanoin, Coco-Caprylate/Caprate, Sodium Polyacryloyldimethyl Taurate, Capryloyl Glycerin/Sebacic Acid Copolymer, Cassia Angustifolia Seed Polysaccharide, Helianthus Annuus (Sunflower) Seed Oil, Heterotheca Inuloides Flower Extract, Chenopodium Quinoa Seed Extract, Poncirus Trifoliata Fruit Extract, Hydrolyzed Brassica Napus Seedcake Extract, SR-Hydrozoan Polypeptide-1, Castor Oil/IPDI Copolymer, Diheptyl Succinate, Phenoxyethanol, Dilinoleic Acid/Butanediol Copolymer, Caprylyl Glycol, Hydrolyzed Jojoba Esters, Lysolecithin, Sclerotium Gum, Tetrahexyldecyl Ascorbate, Tocopheryl Acetate, Tetrasodium Glutamate Diacetate, Pullulan, Xanthan Gum, Jojoba Esters, Silica, Citric Acid, Sodium Benzoate, Sodium Formate, Sodium Glycolate, Sodium Hydroxide, Sodium PCA, Potassium Hydroxide, Potassium Sorbate.'] | M37: 32 | P37: 0 | Q37: 0 | R37: 0 | S37: 0 | T37: 1 | U37: ['Vegan', 'Clean + Planet Positive', 'Hydrating', 'Fragrance Free', 'Hypoallergenic', 'Cruelty-Free'] | V37: Skincare | W37: Cleansers | X37: Face Wash & Cleansers | Y37: 0 | AC37: 0.0036955222
A38: P504312 | B38: Donna Born In Roma Intense Eau de Parfum | C38: 1169 | D38: Valentino | E38: 13815 | F38: 4.6988 | G38: 581 | H38: 0.34 oz / 10 mL | I38: Size + Concentration + Formulation | J38: 0.34 oz / 10 mL eau de parfum spray | L38: ['Alcohol, Parfum/Fragrance, Aqua/Water/Eau, Benzyl Salicylate, Benzyl Alcohol, Ethylhexyl Salicylate, Butyl Methoxydibenzoylmethane, Hydroxycitronellal, Coumarin, Limonene, Linalool, Alpha-Isomethyl Ionone, Anise Alcohol, Isoeugenol, Methyl Anthranilate, Benzyl Benzoate, Citronellol, Geraniol, Benzyl Cinnamate, Tris (Tetramethylhydroxypiperidinol) Citrate, Citral, Cinnamal, Eugenol, Farnesol, CI 14700/Red 4, CI 17200/Red 33, CI 60730/Ext. Violet 2.'] | M38: 35 | P38: 0 | Q38: 1 | R38: 0 | S38: 0 | T38: 0 | U38: ['Layerable Scent', 'Floral Scent'] | V38: Fragrance | W38: Women | X38: Perfume | Y38: 3 | Z38: 156 | AA38: 85 | AC38: 0.0037187748
A39: P501243 | B39: GOOPGLOW Exfoliating Dark Spot Sleep Serum | C39: 6309 | D39: goop | E39: 2143 | F39: 4.0598 | G39: 251 | H39: 1 oz / 30 mL | I39: Size | J39: 1 oz / 30 mL | L39: ['Aqua/Water/Eau, Caprylic/Capric Triglyceride, Glycolic Acid, Squalane, Sodium Hydroxide, Behenyl Alcohol, Gluconolactone, Lactic Acid, Glycerin, Polyglyceryl-10 Dioleate, Pentylene Glycol, Propanediol, Magnesium Aluminum Silicate, Sodium Hyaluronate, Aloe Barbadensis Leaf Juice, Salicornia Herbacea Extract, Hydrogenated Lecithin, Hibiscus Sabdariffa Flower Extract, Piperonyl Glucoside, Polyglutamic Acid, Avena Sativa (Oat) Bran Extract, Tamarindus Indica Seed Polysaccharide, Simmondsia Chinensis (Jojoba) Seed Oil, Adansonia Digitata Seed Oil, Citrullus Lanatus (Watermelon) Seed Oil, Phospholipids, Adansonia Digitata Fruit Extract, Cyclodextrin, Xanthan Gum, Glyceryl Undecylenate, Glyceryl Caprylate, Tetrasodium Glutamate Diacetate, Caprylyl Glycol, Ethylhexylglycerin, Sclerotium Gum, 1,2-Hexanediol, Polyglyceryl-10 Dipalmitate, Sodium Benzoate, Potassium Sorbate, Citric Acid.'] | M39: 98 | P39: 0 | Q39: 0 | R39: 0 | S39: 0 | T39: 0 | U39: ['Good for: Dullness/Uneven Texture', 'Hyaluronic Acid', 'Clean at Sephora', 'AHA/Glycolic Acid', 'Best for Dry, Combo, Normal Skin', 'Good for: Dark spots'] | V39: Skincare | W39: Treatments | X39: Face Serums | Y39: 0 | AC39: 0.003890582
A40: P426000 | B40: Mini Texturizing Hair Spray | C40: 6144 | D40: OUAI | E40: 14727 | F40: 3.2632 | G40: 95 | H40: 1.4 oz | I40: Size | J40: 1.4 oz | L40: ['Hydrofluorocarbon 152A, Dimethyl Ether, Alcohol Denat., VP/VA Copolymer, Panthenol, Tocopheryl Acetate, Actinidia Chinensis (Kiwi) Fruit Extract, Aloe Barbadensis (Aloe Vera) Leaf Extract, Hedychium Coronarium (Ginger) Root Extract, Mangifera Indica (Mango) Fruit Extract, Passiflora Incarnata (Passion Flower) Extract, Helianthus Annuus (Sunflower) Seed Extract, Glycerin, Acetyl Triethyl Citrate, Fragrance, Zeolite, Butylene Glycol, Water, PEG/PPG-17/18 Dimethicone, Benzoic Acid, Sorbic Acid, Phenoxyethanol, Chlorphenesin, Benzyl Salicylate, Hexyl Cinnamal, Limonene, Butylphenyl Methylpropional, Linalool, Hydroxycitronellal.'] | M40: 14 | P40: 1 | Q40: 0 | R40: 0 | S40: 0 | T40: 0 | V40: Mini Size | W40: Hair | Y40: 0 | AC40: 0.0040554452
A41: P504797 | B41: Mini Color Care Conditioner | C41: 6182 | D41: Moroccanoil | E41: 163 | F41: 4.848 | G41: 171 | H41: 2.4 oz / 70 mL | I41: Size | J41: 2.4 oz / 70 mL | L41: ['Aqua/Water/Eau, Cetearyl Alcohol, PEG/PPG-20/20 Phenylisopropyl Caprylyl Dimethicone, Cetyl Alcohol, Stearamidopropyl Dimethylamine, Behentrimonium Chloride, Quaternium-91, Argania Spinosa (Argan) Kernel Oil, Helianthus Annuus (Sunflower) Seed Oil, Parfum/Fragrance, Pyrus Malus (Apple) Fruit Extract, Punica Granatum (Pomegranate) Fruit Extract, Prunus Armeniaca (Apricot) Kernel Oil, Glycerin, PPG-3 Benzyl Ether Myristate, Isopropyl Alcohol, Panthenol, Quaternium-95, Caprylic/Capric Triglyceride, Hydroxyacetophenone, Caprylyl Glycol, Chitosan, Guar Hydroxypropyltrimonium Chloride, Citric Acid, EDTA, PEG-12 Allyl Ether, PEG-12 Dimethicone, Amodimethicone/Morpholinomethyl Silsesquioxane Copolymer, Trideceth-5, Silica Dimethyl Silylate, Algin, Pentaerythrityl Tetra-Di-T-Butyl Hydroxyhydrocinnamate, Chlorphenesin, C12-13 Pareth-9, Propanediol, Sodium Benzoate, Potassium Sorbate, Phenoxyethanol, Sorbic Acid.'] | M41: 12 | P41: 0 | Q41: 1 | R41: 1 | S41: 0 | T41: 0 | U41: ['Sustainable Packaging', 'Good for: Color Care', 'Prevents Color Fading', 'Without Sulfates SLS & SLES', 'Increases Shine', 'Cruelty-Free'] | V41: Mini Size | W41: Hair | Y41: 0 | AC41: 0.0041700699
A42: P429981 | B42: Dylan Blue Pour Femme | C42: 2084 | D42: Versace | E42: 36867 | F42: 4.1516 | G42: 310 | H42: 1.7 oz/ 50 mL | I42: Size + Concentration + Formulation | J42: 1.7 oz/ 50 mL | L42: ['Alcohol Denat. (Sd Alcohol 39-C), Fragrance, Water, Benzyl Salicylate,', 'Limonene, Citronellol, Hydroxycitronellal, Alpha-Isomethyl Ionone, Ethylhexyl', 'Methoxycinnamate, Linalool, Benzyl Benzoate, Hexyl Cinnamal, Ethylhexyl Salicylate,', 'Butyl Methoxydibenzoylmethane, Geraniol, Citral, Benzyl Alcohol, Farnesol, Cinnamyl Alcohol.'] | M42: 98 | P42: 0 | Q42: 0 | R42: 0 | S42: 0 | T42: 0 | U42: ['allure 2020 Best of Beauty Award Winner', 'Floral Scent'] | V42: Fragrance | W42: Women | X42: Perfume | Y42: 3 | Z42: 74 | AA42: 32 | AC42: 0.0042647065
A43: P425840 | B43: Mini Ambient Lighting Powder | C43: 5879 | D43: Hourglass | E43: 65833 | F43: 4.086 | G43: 314 | H43: 0.049 oz/ 1.4 g | I43: Color | J43: Diffused Light | K43: soft, warm pale yellow powder | L43: ['Mica, Synthetic Fluorphlogopite, Boron Nitride, Hdi/Trimethylol Hexyllactone Crosspolymer, Polymethyl Methacrylate, Octyldodecanol, Benzoic Acid, C13-14 Isoparaffin, Dehydroacetic Acid, Diamond Powder, Dimethicone, Ethylhexylglycerin, Laureth-7, Magnesium Aluminum Silicate, Phenoxyethanol, Polyacrylamide, Polymethylsilsesquioxane, Potassium Sorbate, Silica, Sodium Dehydroacetate, Sorbic Acid, Sorbitan Sesquioleate, Trimethylsiloxysilicate. May Contain (+/-): Bismuth Oxychloride (Ci 77163), Iron Oxides (Ci 77491, Ci 77492, Ci 77499), Titanium Dioxide (Ci 77891).'] | M43: 28 | P43: 0 | Q43: 0 | R43: 0 | S43: 0 | T43: 1 | U43: ['Without Parabens', 'Radiant Finish', 'Vegan'] | V43: Mini Size | W43: Makeup | Y43: 3 | Z43: 28 | AA43: 28 | AC43: 0.0043360465
A44: P504204 | B44: True Textures Curl Enhancing Cream | C44: 6315 | D44: Mizani | E44: 1437 | F44: 4.5227 | G44: 352 | H44: 10.89 oz / 325 mL | I44: Size | J44: 10.89 oz / 325 mL | L44: ['Aqua/Water/Eau, Propylene Glycol, Dimethicone, Phenoxyethanol, Polyquaternium-11, Guar Hydroxypropyltrimonium Chloride, Cetearyl Alcohol, Parfum/Fragrance, Hydroxypropyl Guar, Caprylyl Glycol, Styrene/Acrylates Copolymer, Laureth-4, Dicetyl Phosphate, Laureth-23, Ceteth-10 Phosphate, Olea Europaea Oil/Olive Fruit Oil, Sclerocarya Birrea Seed Oil, Cocos Nucifera Oil/Coconut Oil, Benzophenone-4, Disodium EDTA, Sodium Citrate, Limonene, Coumarin, 2-Oleamido-1, 3-Octadecanediol, Linalool, Benzyl Alcohol, Hydroxycitronellal, Sodium Lauryl Sulfate, Citral, Geraniol, Disodium Laureth Sulfosuccinate, CI 19140/Yellow 5, CI 15985/Yellow 6.'] | M44: 25 | P44: 0 | Q44: 1 | R44: 0 | S44: 0 | T44: 0 | U44: ['Long-wearing', 'Curl-Enhancing', 'Good for: Frizz', 'Curly Hair', 'Good for: Dryness'] | V44: Hair | W44: Hair Styling & Treatments | X44: Hair Styling Products | Y44: 0 | AC44: 0.0043915625
A45: P417212 | B45: Peony & Blush Suede Body CrÃ¨me | C45: 6202 | D45: Jo Malone London | E45: 5073 | F45: 4.4706 | G45: 17 | H45: 5.9 oz/ 175 mL | I45: Size + Concentration + Formulation | J45: 5.9 oz/ 175 mL Body Cream | L45: ['Water, Glycerin, Cetearyl Alcohol, Simmondsia Chinensis (Jojoba) Seed Oil, Glyceryl Stearate, Stearic Acid, Fragrance, Triethanolamine, Isopropyl Palmitate, Theobroma Cacao (Cocoa) Seed Butter, Prunus Amygdalus Dulcis (Sweet Almond) Oil, Aloe Barbadensis Leaf Extract, Dimethicone, Caffeine, Caprylyl Glycol, Bisabolol, Hexylene Glycol, Disodium Edta, Benzyl Alcohol, Benzyl Salicylate, Geraniol, Hydroxycitronellal, Citronellol, Linalool, Alpha-Isomethyl Ionone, Eugenol, Cinnamyl Alcohol, Limonene, Phenoxyethanol <ILN40189>.'] | M45: 90 | P45: 0 | Q45: 0 | R45: 0 | S45: 0 | T45: 0 | V45: Bath & Body | W45: Body Moisturizers | X45: Body Lotions & Body Oils | Y45: 1 | Z45: 38 | AA45: 38 | AC45: 0.0047953301
A46: P482060 | B46: Mini RESIST Youth-Extending Daily Hydrating Fluid SPF 50 | C46: 6341 | D46: Paula's Choice | E46: 15303 | F46: 4.3966 | G46: 58 | H46: .5 oz / 15 mL | I46: Size | J46: .5 oz / 15 mL | L46: ['Avobenzone 2%, Octinoxate 7.5%, Octisalate 5%, Octocrylene 2%, Water (Aqua), Glycerin, Silica, Dimethicone, Tocopherol, Chamomilla Recutita (Matricaria) Flower Extract, Vitis Vinifera (Grape) Seed Extract, Camellia Sinensis (Green Tea) Leaf Extract, Camellia Oleifera (Green Tea) Leaf Extract, Peucedanum Graveolens (Dill) Extract, Sambucus Nigra (Black Elderberry) Fruit Extract, Avena Sativa (Oat) Bran Extract, Punica Granatum (Pomegranate) Extract, Lycium Barbarum (Goji) Fruit Extract, Hydrogenated Lecithin, Titanium Dioxide, Dimethicone/Vinyl Dimethicone Crosspolymer, Diethylhexyl Syringylidenemalonate, Hydroxyethyl Acrylate/Sodium Acryloyldimethyl Taurate Copolymer, Xanthan Gum, Sodium Carbomer, Benzyl Alcohol, Sodium Benzoate, Potassium Sorbate, Phenoxyethanol.'] | M46: 12 | P46: 0 | Q46: 0 | R46: 0 | S46: 0 | T46: 0 | U46: ['Good for: Anti-Aging', 'Matte Finish', 'Oil Free', 'Best for Oily, Combo, Normal Skin', 'SPF'] | V46: Mini Size | W46: Skincare | Y46: 0 | AC46: 0.0050349783
A47: P480178 | B47: Apple Brandy Eau de Parfum Travel Spray | C47: 6240 | D47: KILIAN Paris | E47: 10759 | F47: 4.4 | G47: 25 | H47: 0.24 oz/ 7.5 mL | I47: Size + Concentration + Formulation | J47: 0.24 oz/ 7.5 mL parfum spray | L47: ['Alcohol Denat., Water/Aqua/Eau, Fragrance (Parfum), Limonene, Linalool, Evernia Prunastri (Oakmoss) Extract, Citral, Geraniol, Citronellol, Tocopherol <Iln49607>.'] | M47: 50 | P47: 0 | Q47: 0 | R47: 0 | S47: 0 | T47: 1 | V47: Fragrance | W47: Women | X47: Rollerballs & Travel Size | Y47: 0 | AC47: 0.0050928074
A48: P393325 | B48: Beyond Perfecting Foundation + Concealer | C48: 1254 | D48: CLINIQUE | E48: 112957 | F48: 3.7543 | G48: 2572 | H48: 1 oz/ 30 mL | I48: Color | J48: CN 0.5 Shell | K48: fairest shade; with a cool neutral undertone | L48: ['Water\\Aqua\\Eau, Isostearyl Neopentanoate, Dimethicone, Isohexadecane, Trimethylsiloxysilicate, Butylene Glycol, Glycerin, Lauryl Peg-9 Polydimethylsiloxyethyl Dimethicone, Disteardimonium Hectorite, Trehalose, Peg-10 Dimethicone, Hdi/Trimethylol Hexyllactone Crosspolymer, Dimethicone/Peg-10/15 Crosspolymer, Triethoxycaprylylsilane, Sodium Hyaluronate, Hydrolyzed Soy Protein, Tocopheryl Acetate, Polymethyl Methacrylate, Propylene Carbonate, Lecithin, Laureth-7, Hydrogenated Lecithin, Dimethicone Silylate, Xanthan Gum, Dipropylene Glycol, Sodium Chloride, Magnesium Aluminum Silicate, Silica, Coconut Acid, Disodium Edta, Phenoxyethanol, [+/- Mica, Iron Oxides (Ci 77491), Iron Oxides (Ci 77492), Iron Oxides (Ci 77499), Titanium Dioxide (Ci 77891), Zinc Oxide (Ci 77947), Bismuth Oxychloride (Ci 77163).'] | M48: 37 | P48: 0 | Q48: 0 | R48: 0 | S48: 0 | T48: 0 | V48: Makeup | W48: Face | X48: Foundation | Y48: 34 | Z48: 37 | AA48: 36 | AC48: 0.0051867564
A49: P409630 | B49: SEA Pack Your Bags Undereye Patches | C49: 5648 | D49: tarte | E49: 56808 | F49: 4.1779 | G49: 298 | H49: 4 x 2 single use patches | I49: Size | J49: 4 x 2 single use patches | L49: ['Water, Glycerin, Butylene Glycol, Mannitol, Sodium Polyglutamate, Algin, Chondrus Crispus Powder, Laureth-21, Polyglyceryl-10 Laurate, Cocos Nucifera (Coconut) Oil, Carbomer, Sodium Lactate, Polysorbate 20, Hydroxypropyl Cyclodextrin, Algae Extract, Gardenia Taitensis Flower Extract, Palmaria Palmata Extract, Palmitoyl Pentapeptide-4, Tocopherol, Phenoxyethanol, Iodopropynyl Butylcarbamate.'] | M49: 22 | O49: 11 | P49: 0 | Q49: 0 | R49: 0 | S49: 1 | T49: 1 | U49: ['Clean at Sephora', 'Vegan'] | V49: Skincare | W49: Eye Care | X49: Eye Masks | Y49: 0 | AC49: 0.0051982051
A50: P474338 | B50: Specifique Divalent Hydrating Gel-Mask for Oily Hair | C50: 6259 | D50: KÃ©rastase | E50: 3130 | F50: 4.2647 | G50: 68 | L50: ['Aqua/Water/Eau, Hydroxypropyl Starch Phosphate, Quaternium-87, Stearyl Alcohol, Behentrimonium Chloride, Propylene Glycol, Isononyl Isononanoate, Cetyl Esters, Caprylyl Glycol, Capryloyl Glycine, Candelilla Cera/Candelilla Wax/Cire De Candelilla, Isopropyl Alcohol, Phenoxyethanol, Sodium Hydroxide, Linalool, Limonene, Geraniol, Citronellol, Alpha-Isomethyl Ionone, 2-Oleamido-1,3-Octadecanediol, CI 42090/Blue 1, CI 19140/Yellow 5, Parfum/Fragrance.'] | M50: 68 | P50: 0 | Q50: 0 | R50: 1 | S50: 0 | T50: 0 | U50: ['Hydrating', 'Fresh Scent', 'All Hair Types', 'Good for: Dryness', 'Increases Shine', 'Good for: Oily Scalp'] | V50: Hair | W50: Hair Styling & Treatments | X50: Hair Masks | Y50: 0 | AC50: 0.0054055786
A51: P454990 | B51: Mini babassu foundcealer skincare foundation SPF 20 | C51: 5648 | D51: tarte | E51: 9262 | F51: 3.52 | G51: 25 | H51: 0.33 oz/ 10 mL | I51: Color | J51: 13N fair neutral | K51: fair skin with neutral undertones | L51: ['Water, Phenyl Trimethicone, Butylene Glycol, Dimethicone, Butylene Glycol Dicaprylate/Dicaprate, Butyloctyl Salicylate, Cyclohexasiloxane, Cetyl PEG/PPG-10/1 Dimethicone, Bis-Diglyceryl Polyacyladipate-2, Aluminum Hydroxide, Methyl Methacrylate Crosspolymer, Orbignya Oleifera (Babassu) Seed Oil, Polypropylsilsesquioxane, Sodium Chloride, Stearic Acid, Polyglyceryl-4 Isostearate, Hexyl Laurate, Dimethicone/Vinyl Dimethicone Crosspolymer, Calcium Stearate, Disteardimonium Hectorite, Triethoxycaprylylsilane, Sodium Benzoate, Potassium Sorbate, Tocopherol, Polyhydroxystearic Acid, Helianthus Annuus (Sunflower) Seed Oil, Ethylhexyl Palmitate, Isopropyl Myristate, Isostearic Acid, Lecithin, Disodium EDTA, Cyclopentasiloxane, Polyglyceryl-3 Polyricinoleate, Kaolin, Cyclotetrasiloxane, Phenoxyethanol, Sodium Hyaluronate, Ethylhexylglycerin, Hydrolyzed Hyaluronic Acid, Titanium Dioxide, Iron Oxides.'] | M51: 16 | P51: 0 | Q51: 0 | R51: 0 | S51: 0 | T51: 0 | V51: Makeup | W51: Face | X51: Foundation | Y51: 3 | Z51: 16 | AA51: 16 | AC51: 0.0055850465
A52: P502055 | B52: Dolce Nourishing Shampoo | C52: 6159 | D52: Rossano Ferretti Parma | E52: 346 | F52: 5 | G52: 3 | H52: 1.7 oz / 50 mL | I52: Size | J52: 1.7 oz / 50 mL | L52: ['Aqua/Water/Eau, Laureth-5 Carboxylic Acid, Disodium Laureth Sulfosuccinate, Cocamidopropyl Betaine, Sodium Lauryl Sulfoacetate, Sodium Lauroyl Methyl Isethionate, Sodium Methyl Cocoyl Taurate, Sodium Hyaluronate, Aloe Barbadensis Leaf Juice, Hydrogenated Palm Glycerides Citrate, Vitis Vinifera (Grape) Leaf Extract, Panax Ginseng Root Extract, Paullinia Cupana Seed Extract, Serine, Pullulan, Tocopherol, Algin, Trehalose, Lauryl/Myristyl Polyricinoleate, Polyquaternium-7, Coco-Glucoside, Laureth-4, Caprylyl Glycol, Glyceryl Polyacrylate, Potassium Phosphate, Disodium Phosphate, Pentylene Glycol, Glyceryl Oleate, Glycol Distearate, Glycerol, Urea, Glycerin, Peg-120 Methyl Glucose Dioleate, Methoxy Peg/Ppg-7/3 Aminopropyl Dimethicone, Citric Acid, Sodium Benzoate, Potassium Sorbate, Gluconolactone, Calcium Gluconate, Phenoxyethanol, Limonene, Linalool, Parfum (Fragrance).'] | M52: 16 | P52: 0 | Q52: 0 | R52: 1 | S52: 0 | T52: 0 | U52: ['Vegan', 'Hyaluronic Acid', 'Good for: Frizz', 'Good for: Dryness', 'Without Sulfates SLS & SLES', 'Cruelty-Free'] | V52: Hair | W52: Shampoo & Conditioner | X52: Shampoo | Y52: 1 | Z52: 39 | AA52: 39 | AC52: 0.0058418416
A53: P502170 | B53: Hold Up Soft Set Creamy Eyebrow Wax | C53: 6246 | D53: LAWLESS | E53: 10006 | F53: 4.7289 | G53: 284 | H53: 0.24 oz / 7 mL | I53: Color | J53: Light/Medium | K53: flexible light/medium | L53: ['Water (Aqua), Euphorbia Cerifera (Candelilla) Wax [Euphorbia Cerifera Cera], Steareth-21, Glyceryl Stearate, Mica, Butylene Glycol, Acacia Senegal Gum [Acacia Senegal], Silica, Butyrospermum Parkii (Shea) Butter [Butyrospermum Parkii Butter], Cellulose, Dimer Dilinoleyl Dimer Dilinoleate, Simmondsia Chinensis (Jojoba) Seed Oil [Simmondsia Chinensis Seed Oil], Copernicia Cerifera (Carnauba) Wax [Copernicia Cerifera Wax], Argania Spinosa Kernel Oil, Cetyl Alcohol, Polyglyceryl-10 Myristate, Oryza Sativa (Rice) Starch [Oryza Sativa Starch], Phenoxyethanol, Caprylyl Glycol, Sodium Benzoate, Potassium Sorbate, Arginine, Chondrus Crispus Powder, Tocopherol, Simethicone, Titanium Dioxide (Ci 77891), Iron Oxides (Ci 77491, Ci 77492, Ci 77499).'] | M53: 21 | P53: 0 | Q53: 0 | R53: 0 | S53: 0 | T53: 1 | U53: ['Vegan', 'allure 2022 Best of Beauty Award Winner', 'Clean at Sephora', 'Long-wearing', 'Without Silicones', 'Cruelty-Free'] | V53: Makeup | W53: Eye | X53: Eyebrow | Y53: 1 | Z53: 21 | AA53: 21 | AC53: 0.0058823244
A54: P427385 | B54: Shimmer & Glow Liquid Eye Shadow | C54: 3865 | D54: stila | E54: 183848 | F54: 4.6466 | G54: 1197 | H54: 0.153 oz | I54: Color | J54: Grace | K54: shimmering rosey taupe | L54: ['Water, Mica (Ci 77019), Hydroxyethyl Acrylate/Sodium Acryloyldimethyl Taurate Copolymer, Squalane, Synthetic Fluorphlogopite, Calcium Sodium Borosilicate, Polysorbate 60, Caprylyl Glycol, Phenoxyethanol, Glycerin, Triethanolamine, Carbomer, Sorbitan Isostearate, Hexylene Glycol, Silica, Tin Oxide. (+/-) Titanium Dioxide (Ci 77891), Iron Oxides (Ci 77491, Ci 77499), Carmine (Ci 75470), Ferric Ferrocyanide (Ci 77510).'] | M54: 25 | P54: 0 | Q54: 0 | R54: 0 | S54: 0 | T54: 0 | U54: ['Liquid Formula', 'Medium Coverage', 'Shimmer Finish'] | V54: Makeup | W54: Eye | X54: Eyeshadow | Y54: 3 | Z54: 25 | AA54: 25 | AC54: 0.0059889943
A55: P429434 | B55: You Glow Girl Iridescent Jelly | C55: 6235 | D55: INC.redible | E55: 27977 | F55: 3.8776 | G55: 147 | H55: 0.32 oz/ 9.35 g | I55: Color | J55: Show Glow | K55: gold | L55: ['Water, Butylene Glycol, Glycerin, Calcium Sodium Borosilicate, Phenoxyethanol, PEG-240/HDI Copolymer Bis-Decyltetradeceth-20 Ether, Mica, Silica, Sodium Hyaluronate, Tin Oxide. May Contain (+/-): Titanium Dioxide (Ci 77891), Iron Oxides (Ci 77491).'] | M55: 12 | P55: 0 | Q55: 0 | R55: 0 | S55: 0 | T55: 0 | V55: Makeup | W55: Face | X55: Highlighter | Y55: 0 | AC55: 0.0060313987
A56: P383054 | B56: Do Not Age with Dr. Brandt Transforming Pearl Serum | C56: 4372 | D56: Dr. Brandt Skincare | E56: 3259 | F56: 4.1852 | G56: 54 | H56: 1.35 oz/ 40 mL | I56: Size | J56: 1.35 oz/ 40 mL | L56: ['Water (Aqua), Caprylic /Capric Triglyceride, Propanediol, Glycerin, Pentylene Glycol, Alcohol Denat., Prunus Armeniaca (Apricot) Kernel Oil, Phenoxyethanol, Hydroxyethylpiperazine Ethane Sulfonic Acid, Sodium Hydroxide, Xanthan Gum, Sodium Hyaluronate, Hydroxyethylcellulose, Carrageenan, Algin, Decarboxy Carnosine Hcl, Synthetic Fluorphlogopite, Butylene Glycol, Spilanthes Acmella Flower Extract, Titanium Dioxide (Ci 77891), Alaria Esculenta Extract, Geranylgeranylisopropanol, Silica, Mica, Sodium Acetate, Bht, Sodium Lauryl Sulfate, Cellulose, Citrus Aurantium Dulcis (Orange) Peel Oil, Citrus Aurantium Dulcis (Orange) Fruit Extract, Cananga Odorata Flower Oil, Vanillin, Lavandula Hybrida Oil, Litsea Cubeba Fruit Oil, Vanilla Planifolia Fruit Extract, Jasminum Sambac (Jasmine) Flower Extract, Tin Oxide, Limonene.'] | M56: 152 | P56: 0 | Q56: 0 | R56: 0 | S56: 0 | T56: 0 | V56: Skincare | W56: Treatments | X56: Face Serums | Y56: 0 | AC56: 0.0061479141
A57: P504319 | B57: Golden Nectar Perfume Set | C57: 7025 | D57: NEST New York | E57: 2443 | F57: 4.1667 | G57: 6 | L57: ['Alcohol Denat., Fragrance (Parfum), Water (Aqua), Alpha-Isomethyl Ionone, Cinnamyl Alcohol, Citral, Citronellol, Coumarin, Farnesol, Geraniol, Limonene, Linalool.'] | M57: 86 | P57: 1 | Q57: 1 | R57: 0 | S57: 1 | T57: 0 | V57: Fragrance | W57: Value & Gift Sets | X57: Perfume Gift Sets | Y57: 0 | AC57: 0.0061540496
A58: P461217 | B58: Illuminator Liquid Highlight | C58: 6331 | D58: Iconic London | E58: 46623 | F58: 4.4943 | G58: 87 | H58: 0.45 oz/ 13.5 mL | I58: Color | J58: Blush | K58: peachy antique-rose based shimmer that adds a warm rosy glow | L58: ['Hydrogenated Didecene Isododecane Hydrogenated Polyisobutene Mica Hydrogenated Polycyclopentadiene Hydrogenated Styrene/Isoprene Copolymer Triethoxycaprylylsilane 1,2-Hexanediol Caprylyl Glycol May Contain: CI 77491 (Iron Oxides) CI 77891 (Titanium Dioxide).'] | M58: 40 | P58: 0 | Q58: 0 | R58: 0 | S58: 0 | T58: 0 | U58: ['Liquid Formula', 'High Shine Finish', 'Alcohol Free', 'Oil Free', 'Vegan'] | V58: Makeup | W58: Face | X58: Highlighter | Y58: 2 | Z58: 40 | AA58: 40 | AC58: 0.0061723452
A59: P501520 | B59: Noir Extreme Parfum | C59: 5869 | D59: TOM FORD | E59: 1838 | F59: 4.6117 | G59: 273 | H59: 3.4 oz / 100 mL | I59: Size + Concentration + Formulation | J59: 3.4 oz / 100 mL parfum spray | L59: ['Alcohol Denat., Fragrance (Parfum), Water\\Aqua\\Eau, Benzyl Salicylate, Hydroxycitronellal, Alpha-Isomethyl Ionone, Coumarin, Limonene, Linalool, Eugenol, Farnesol, Cinnamal, Geraniol, Citronellol, Benzyl Benzoate, Amyl Cinnamal, Cinnamyl Alcohol, Citral, Pentaerythrityl Tetra-Di-T-Butyl Hydroxyhydrocinnamate, Phenoxyethanol <ILN50363>'] | M59: 235 | P59: 0 | Q59: 0 | R59: 0 | S59: 0 | T59: 0 | U59: ['Unisex/ Genderless Scent', 'Layerable Scent', 'Warm &Spicy Scent'] | V59: Fragrance | W59: Men | X59: Cologne | Y59: 1 | Z59: 180 | AA59: 180 | AC59: 0.0061965464
A60: P500426 | B60: Solar Radiance Hydrating Cream Highlighter Refill | C60: 6367 | D60: ROSE INC | E60: 902 | F60: 4 | G60: 2 | H60: 0.2 oz / 6 mL | I60: Color | J60: Glancing | K60: rosy bronze | L60: ['Caprylic/Capric Triglyceride, C13-15 Alkane, Silica, Octyldodecanol, Ricinus Communis (Castor) Seed Oil, Euphorbia Cerifera (Candelilla) Wax, Copernicia Cerifera (Carnauba) Wax, Glyceryl Hydrogenated Rosinate, Squalane, Eryngium Maritimum Callus Culture Filtrate, Ascorbyl Palmitate, Tocopherol, Rosa Damascena Flower Oil, Rosa Damascena Flower Water, Pentaerythrityl Tetra-di-t-butyl Hydroxyhydrocinnamate, Boron Nitride, Pentylene Glycol, Caprylyl Glycol, Tin Oxide, [+/-: Mica, Titanium Dioxide (CI 77891), Iron Oxides (CI 77491, CI 77499), Manganese Violet (CI 77742), Ultramarines (CI 77007)].'] | M60: 18 | P60: 0 | Q60: 0 | R60: 0 | S60: 0 | T60: 1 | U60: ['Vegan', 'Radiant Finish', 'Refill Available', 'Cream Formula', 'Clean + Planet Positive', 'Hydrating'] | V60: Makeup | W60: Face | X60: Highlighter | Y60: 4 | Z60: 18 | AA60: 18 | AC60: 0.0062557095
A61: P475590 | B61: MINI GINZING VITAMIN C EYE CREAM TO BRIGHTEN AND DEPUFF | C61: 3733 | D61: Origins | E61: 18284 | F61: 3.45 | G61: 40 | H61: .34 oz/ 10 mL | I61: Color | J61: Original | L61: ['Water/Aqua/Eau, Butylene Glycol, PEG-100 Stearate, Dimethicone, Silica, Cetyl Ricinoleate, Olea Europaea (Olive) Fruit Oil, Glycerin, Panax Ginseng (Ginseng) Root Extract, Coffea Arabica (Coffee) Seed Oil, Caffeine, Citrus Aurantium Dulcis (Orange) Peel Extract, Aminopropyl Ascorbyl Phosphate, Caprylic/Capric Triglyceride, Hypnea Musciformis (Algae) Extract, Gelidiella Acerosa Extract, Sigesbeckia Orientalis (St. Paul Wort) Extract, Ascophyllum Nodosum Extract, Chrysanthellum Indicum Extract, Asparagopsis Armata Extract, Cucumis Sativus (Cucumber) Fruit Extract, Pyrus Malus (Apple) Fruit Extract, Scutellaria Baicalensis Root Extract, Molasses Extract/Saccharum Officinarum/Extrait De MÃ©lasse, Butyrospermum Parkii (Shea) Butter, Simmondsia Chinensis (Jojoba) Seed Oil, Sodium Hyaluronate, Niacinamide, Linoleic Acid, Phytosphingosine, Tocopheryl Acetate, Methyl Trimethicone, Trehalose, Tribehenin, Inulin, Sorbitol, Ethylhexylglycerin, Caprylyl Glycol, Tocopherol, Myristyl Alcohol, Hydrogenated Lecithin, Jojoba Wax PEG-120 Esters, Carbomer, Behenyl Alcohol, Sodium Hydroxide, BHT, Hydroxyacetophenone, Sodium Metabisulfite, Sodium Sulfite, Disodium EDTA, Phenoxyethanol, Chlorphenesin, Sorbic Acid, Potassium Sorbate, [+/- Mica, Titanium Dioxide (CI 77891), Iron Oxides (CI 77491), Iron Oxides (CI 77492), Bismuth Oxychloride (CI 77163)].'] | M61: 29 | P61: 0 | Q61: 0 | R61: 1 | S61: 0 | T61: 0 | U61: ['Vegan', 'Good for: Dullness/Uneven Texture', 'Vitamin C', 'Good for: Dark Circles', 'Good for: Dryness', 'Niacinamide'] | V61: Skincare | W61: Eye Care | X61: Eye Creams & Treatments | Y61: 0 | AC61: 0.0062957312
A62: P470507 | B62: The Cream with TFC8 Face Moisturizer | C62: 6356 | D62: Augustinus Bader | E62: 11428 | F62: 4.3605 | G62: 430 | H62: 1 oz/ 30 mL | I62: Size | J62: 1 oz/ 30 mL | L62: ['Aqua (Water), Caprylic/Capric Triglyceride, Pentylene Glycol, Propylene Glycol, Hydrogenated Phosphatidylcholine, Glycerin, Sorbitol, Tocopheryl Acetate, Butyrospermum Parkii (Shea) Butter, Xanthan Gum, Butylene Glycol, Panthenol, Sodium Carbomer, Aloe Barbadensis Leaf Juice, Alcohol, Hydrolyzed Rice Protein, Squalane, Helianthus Annuus (Sunflower) Seed Oil, Phenoxyethanol, Sodium Hydroxide, Carbomer, Lecithin, Cholesterol, Hydrogenated Lecithin, Ascorbyl Palmitate, Ceramide NP, Glycine Soja (Soybean) Protein, Superoxide Dismutase, Citric Acid, Dextran, Palmitoyl Tripeptide-8, Alanyl Glutamine, Arginine, Ceramide NG, Glycine, Lysine, Oleic Acid, Palmitic Acid, Phenylalanine, Proline, Scenedesmus Rubescens Extract, Ascorbic Acid, Retinyl Palmitate, Sodium Benzoate, Potassium Sorbate, Ethylhexylglycerin, Sodium Dextran Sulfate, Brassica Alba Oil, Disodium EDTA, Oligopeptide-177, Sodium Ascorbate, Tocopherol.'] | M62: 180 | P62: 0 | Q62: 0 | R62: 0 | S62: 0 | T62: 0 | U62: ['Vitamin C', 'Good for: Anti-Aging', 'Good for: Loss of firmness', 'Good for: Dullness/Uneven Texture', 'Good for: Dark spots', 'Best for Oily, Combo, Normal Skin'] | V62: Skincare | W62: Moisturizers | X62: Moisturizers | Y62: 2 | Z62: 290 | AA62: 92 | AC62: 0.006331698
A63: P477798 | B63: Nail Prep Set | C63: 3902 | D63: SEPHORA COLLECTION | E63: 4153 | F63: 4.3333 | G63: 6 | M63: 20 | O63: 10 | P63: 0 | Q63: 0 | R63: 0 | S63: 0 | T63: 1 | V63: Makeup | W63: Nail | Y63: 0 | AC63: 0.0066393181
A64: P501474 | B64: The Youth Vault: 13-Piece Vegan Skincare + Apparel Set | C64: 6169 | D64: Youth To The People | E64: 8989 | F64: 4.875 | G64: 8 | L64: ['Superfood Antioxidant Cleanser:', 'Water/Aqua/Eau, Cocamidopropyl Hydroxysultaine, Sodium Cocoyl Glutamate, Sorbeth-230 Tetraoleate, Polysorbate 20, Sodium Chloride, Aloe Barbadensis Leaf (Aloe Vera) Juice Powder, Brassica Oleracea Acephala (Kale) Leaf Extract, Spinacia Oleracea (Spinach) Leaf Extract, Camellia Sinensis (Green Tea) Leaf Extract, Medicago Sativa (Alfalfa) Extract, Chamomilla Recutita (Matricaria) Flower Extract, Tetrahexyldecyl Ascorbate (Vitamin C), Glycerin, Panthenol (Vitamin B5), Tocopheryl Acetate (Vitamin E), Decyl Glucoside, Sorbitan Laurate, Tetrasodium Glutamate Diacetate, Gluconolactone, Ethylhexylglycerin, Maltodextrin, Citric Acid, Phenoxyethanol, Potassium Sorbate, Sodium Benzoate, Gardenia Jasminoides (Jasmine) Fruit Extract, Fragrance/Parfum, Sodium Hydroxide, Sodium Glycolate, Sodium Formate, Hexyl Cinnamal, Linalool, Limonene, Chlorophyllin-Copper Complex (CI 75810).', 'Triple Peptide + Cactus Oasis Serum:', 'Water/Aqua/Eau, Butylene Glycol, Glycerin, Pentylene Glycol, Opuntia Ficus-Indica Stem (Prickly Pear Cactus) Extract, Palmitoyl Tripeptide-1, Palmitoyl Tetrapeptide-7, Palmitoyl Tripeptide-28, Sodium Hyaluronate, Hydrolyzed Sodium Hyaluronate, Sodium Hyaluronate Crosspolymer, Sodium Acetylated Hyaluronate, Synthetic Sapphire, Citrullus Lanatus (Watermelon) Fruit Extract, Lens Esculenta (Lentil) Fruit Extract, Pyrus Malus (Apple) Fruit Extract, Nephelium Lappaceum Peel (Rambutan) Extract, Sodium Pca, Glutathione, Malachite Extract, Citric Acid, Hydroxypropyl Methylcellulose, Tetrasodium Glutamate Diacetate, Polyglutamic Acid, 1,2-Hexandiol, Caprylyl Glycol, Sodium Lactate, Carbomer, Propanediol, Polysorbate 20, Hydroxyethylcellulose, Xanthan Gum, Phenoxyethanol, Ethylhexylglycerin, Sodium Benzoate, Potassium Sorbate, Disodium Phosphate, Polysorbate 60, Benzyl Alcohol, Sodium Hydroxide, Glyceryl Caprylate, Sodium Formate, Sodium Glycolate, Sodium Phosphate, Benzoic Acid.', 'Superfood Air-Whip Moisture Cream:', 'Water/Aqua/Eau, Helianthus Annuus (Sunflower) Seed Oil, Glyceryl Stearate, Cetyl Alcohol, Glycerin, Lecithin, Butylene Glycol, Panthenol (Vitamin B5), Sodium Hyaluronate Crosspolymer, Tocopheryl Acetate (Vitamin E), Phenoxyethanol, Ascorbic Acid (Vitamin C), Hydroxyethylcellulose, Brassica Oleracea Capitata (Kale) Leaf Extract, Camellia Sinensis (Green Tea) Leaf Extract, Chamomilla Recutita (Matricaria) Flower Extract, Medicago Sativa (Alfalfa) Leaf Extract, Spinacia Oleracea (Spinach) Leaf Extract, Hyaluronic Acid, Potassium Sorbate, Pentylene Glycol, Aloe Barbadensis (Aloe Vera) Leaf Extract, Ethylhexylglycerin, Tocopherol, Sodium Acetate, Isopropyl Alcohol, Propylene Glycol, Cellulose, Sodium Hydroxymethylglycinate, Sodium Benzoate, Benzyl Benzoate, Natural Fragrance/Parfum, Citronellol, Hexyl Cinnamal, Limonene, Linalool, Chlorophyll (CI 75810).', 'Polypeptide-121 Future Cream:', 'Water/Aqua/Eau, Dicaprylyl Carbonate, Hydrolyzed Hyaluronic Acid, Trimethylolpropane Tricaprylate/Tricaprate, Tridecyl Trimellitate, Propanediol, Sh-Polypeptide-121, Polyglyceryl-3 Methylglucose Distearate, Panthenol, Niacinamide, Proline, Tocopheryl Acetate, Aloe Barbadensis Leaf Juice, Hydrolyzed Cannabis Sativa (Hemp) Seed Extract, Hydrolyzed Rice Protein, Hydrolyzed Pea Protein, Salvia Hispanica (Chia) Seed Extract, Acetyl Tetrapeptide-11, Acetyl Tetrapeptide-9, Acetyl Tetrapeptide-2, Hibiscus Sabdariffa Fruit Extract, Ammonium Acryloyldimethyltaurate/Beheneth-25 Methacrylate Crosspolymer, Hydrolyzed Linseed Seed, Castor Oil/IPDI Copolymer, Ceramide AP, Ceramide NP, Cetearyl Alcohol, Cetearyl Glucoside, Glycerin, Hydrolyzed Sodium Hyaluronate, Coco-Caprylate/Caprate, Dilinoleic Acid/Propanediol/Pdi Crosspolymer, Benzyl Alcohol, Zingiber Officinale (Ginger) Root Extract, Bisabolol, Caprylyl Glycol, Carbomer, Dimethyl Isosorbide, Dipropylene Glycol, Erythritol, Ethylhexylglycerin, Glucose, 1,2-Hexanediol, Trisodium Ethylenediamine Disuccinate, Glyceryl Monostearate, Phytospingosine, Polyacrylate Crosspolymer-6, Polysorbate 20, Caprylhydroxamic Acid, Potassium Sorbate, Glycine, Hydroxyacetophenone, Sodium Benzoate, T-Buty Alcohol, Citric Acid, Sodium Citrate, Sodium Lactate, Triheptanoin, Xanthan Gum.', 'Superberry Hydrate + Glow Dream Mask:', 'Water/Aqua/Eau, Glycerin, Helianthus Annuus (Sunflower) Seed Oil, Isopropyl Myristate, Glyceryl Stearate, Betaine, Cetyl Alcohol, Stearic Acid, Tetrahexyldecyl Ascorbate (Vitamin C), Opuntia Tuna (Prickly Pear) Flower/Stem Extract, Euterpe Oleracea (AcaÃ¬) Fruit Extract, Lycium Barbarum (Goji) Fruit Extract, Aristotelia Chilensis (Maqui) Fruit Extract, Moringa Oleifera Leaf Extract, Glyceryl Stearate Citrate, Tocopheryl Acetate (Vitamin E), Glyceryl Laurate, Squalane, Carbomer, Hyaluronic Acid, Allantoin, Panthenol (Vitamin B5), Ethylhexylglycerin, Xanthan Gum, Phenoxyethanol, Riboflavin (Vitamin B2), Triethyl Citrate, Citrus Aurantium Dulcis Peel Oil, Gamma-Undecalactone, Gamma-Decalactone, Tocopherol, Limonene.', 'Retinal + Niacinamide Youth Serum:', 'Water/Aqua/Eau, Butylene Glycol, Triethylhexanoin, Niacinamide, Squalane, Cyclodextrin, Glycerin, Hydrogenated Lecithin, Polyglyceryl-10 Myristate, Grifola Frondosa Fruiting Body Extract, Rubus Chamaemorus (Cloudberry) Seed Oil, Arginine, Retinal, Withania Somnifera (Ashwagandha) Root Extract, Helianthus Annuus (Sunflower) Seed Oil, Hordeum Vulgare Extract, Ganoderma Lucidum (Reishi Mushroom) Stem Extract, Sodium Hyaluronate Crosspolymer, Cucumis Sativus (Cucumber) Seed Oil, Lonicera Japonica (Honeysuckle) Flower Extract, Ceramide NP, Ceramide AP, Phytosphingosine, Cholesterol, Letinus Edodes Mycelium Extract, Lonicera Caprifolium (Honeysuckle) Flower Extract, Butyrospermum Parkii (Shea) Oil, Ceramide EOP, Sodium Lauroyl Lactylate, Acrylates/C10-30 Alkyl Acrylate Crosspolymer, Capryloyl Glycerin/Sebacic Acid Copolymer, Xanthan Gum, Tocopherol, Carbomer, Hydrolyzed Glycosaminoglycans, Sodium Hyaluronate, Hyaluronic Acid, Pentylene Glycol, Hydrolyzed Sodium Hyaluronate, Diheptyl Succinate, Phenoxyethanol, Ethylhexylglycerin, Phytosterols, Propanediol, Benzyl Glycol, Raspberry Ketone.', 'Adaptogen Deep Moisture Cream:', 'Aqua/Water/Eau, Helianthus Annuus (Sunflower) Seed Oil, Ethylhexyl Palmitate, Propanediol, Glyceryl Stearate, Stearic Acid, Glycerin, Aloe Barbadensis Leaf Juice, Glyceryl Laurate, Squalane, Pentapeptide-59, Withania Somnifera (Ashwagandha) Leaf Extract, Ganoderma Lucidum (Reishi Mushroom) Extract, Ocimum Tenuiflorum (Holy Basil) Extract, Simmondsia Chinensis (Jojoba) Seed Oil, Prunus Amygdalus (Sweet Almond) Dulcis Oil, Butyrospermum Parkii (Shea) Butter, Borago Officinalis Seed Oil, Hydrogenated Lecithin, Rhodiola Rosea Extract, Phenethyl Alcohol, Xanthan Gum, Carbomer, Ethylhexylglycerin, Panthenol, Tocopherol, Maltodextrin, Phenoxyethanol, Potassium Sorbate, Allantoin, Caramel.', 'Mandelic Acid + Superfood Unity Exfoliant:', 'Water/Aqua/Eau (Aqua), Helianthus Annuus (Sunflower) Seed Oil, Stearic Acid, Glycerin, Glyceryl Stearate, Cetyl Alcohol, Ascorbic Acid (Vitamin C), Lecithin, Panthenol (Vitamin B5), Sodium Hyaluronate Crosspolymer, Tocopheryl Acetate (Vitamin E), Phenoxyethanol, Hydroxyethylcellulose, Potassium Sorbate, Aloe Barbadensis (Aloe) Leaf Extract*, Brassica Oleracea Capitata (Kale) Leaf Extract*, Camellia Sinensis (Green Tea) Leaf Extract*, Chamomilla Recutita (Matricaria) Flower Extract*, Medicago Sativa (Alfalfa) Leaf Extract*, Spinacia Oleracea (Spinach) Leaf Extract*, Natural Fragrance, Pentylene Glycol, Ethylhexylglycerin, Magnesium Chloride, Palmitoyl Dipeptide-5 Diaminobutyroyl Hydroxythreonine, Palmitoyl Tripeptide-5, Tetradecyl Aminobutyroylvalylaminobutyric Urea Trifluoroacetate, Benzyl Benzoate, Citronellol, Hexyl Cinnamal, Limonene, Linalool.', 'Superclay Purify + Clear Power Mask:', 'Aqua/Water/Eau, Kaolin, Stearyl Alcohol,Propanediol,Glycerin, Glyceryl Stearate, Niacinamide, Oryza Sativa (Rice) Starch, Bentonite (Volcanic Clay), Cetyl Alcohol, Magnesium Aluminum Silicate, Montmorillonite (French Green Clay), Illite, Calcite, Salicylic Acid, Salix Purpurea (Red Willow) Bark Extract, Saccharomyces/Xylinum/Black Tea Ferment, Allantoin, Carthamus Tinctorius (Safflower) Seed Oil, Phycocyanin (Blue Green Algae), Aloe Barbadensis Leaf Juice, Glyceryl Acrylate/Acrylic Acid Copolymer, Cetearyl Olivate, Sorbitan Olivate, Triticum Aestivum (Wheatgrass) Leaf Extract, Lactic Acid, Sorbitan Stearate, Caprylhydroxamic Acid, Charcoal Powder, Sodium Citrate, 1,2-Hexanediol, Phenoxyethanol, Quartz, Silica, Sodium Benzoate, Potassium Sorbate, Maltodextrin, Gardenia Florida Fruit Extract', 'Dream Eye Cream:', 'Water/Aqua/Eau, Dicaprylyl Carbonate, Butyrospermum Parkii (Shea) Butter, Cetearyl Alcohol, Glycerin, Squalane, Glyceryl Stearate, Avena Sativa (Oat) Bran Extract, Citrus Aurantium Dulcis (Orange) Peel Extract, Moringa Oleifera Seed Oil, Opuntia Ficus-Indica (Prickly Pear) Seed Oil*, Lycium Barbarum (Goji) Callus Culture Extract, Gardenia Jasminoides (Gardenia) Fruit Extract, Sodium Stearoyl Glutamate, Carbomer, Cetearyl Glucoside, Isomalt, Sodium Benzoate, Tetrahexyldecyl Ascorbate (Vitamin C), Tocopheryl Acetate, Tetrasodium Glutamate Diacetate, Betaine, Ceramide NP, Phospholipids, Sodium Hyaluronate, Maltodextrin, Sodium Hydroxide, Phenoxyethanol, Glucose, Lecithin, Tocopherol, Sodium Glycolate, Sodium Formate, Ethylhexylglycerin, Citric Acid.', 'Yerba Mate Resurfacing Energy Facial:', 'Water/Aqua/Eau, Bambusa Arundinacea (Bamboo) Stem Extract, Diatomaceous Earth, Carthamus Tinctorius (Safflower) Seed Oil, Propanediol, Aloe Barbadensis (Aloe Vera) Leaf Juice, Cetyl Alcohol, Glyceryl Stearate Se, Glycerin, Lactic Acid, Sodium Acrylate/Sodium Acryloyldimethyl Taurate Copolymer, Niacinamide, C15-19 Alkane, Ilex Paraguariensis (Yerba Mate) Leaf Extract, Ilex Guayusa (Guayusa) Leaf Extract, Potassium Sorbate, Polyglyceryl-6 Laurate, Tocopherol, Ethylhexylglycerin, Bromelain (Pineapple), Sodium Phytate, Papain (Papaya), Polyglycerin-6, Zingiber Officinale (Ginger) Root Oil, Passiflora Edulis (Passion Fruit) Extract, Xanthan Gum, Curcuma Longa (Turmeric) Root Powder, Hylocereus Undatus (Dragon Fruit) Fruit Extract, Sorbitan Oleate, Helianthus Annus (Sunflower) Seed Oil, Sorbitan Isostearate, Phenoxyethanol, Sodium Benzoate.'] | M64: 340 | N64: 420 | O64: 320 | P64: 1 | Q64: 0 | R64: 1 | S64: 0 | T64: 1 | U64: ['Clean at Sephora', 'Hydrating', 'Good for: Anti-Aging', 'Retinol', 'AHA/Glycolic Acid', 'Good for: Acne/Blemishes'] | V64: Skincare | W64: Value & Gift Sets | Y64: 0 | AC64: 0.0066851366
A65: P483677 | B65: Mini Himalayan Salt & Rosewater Candle | C65: 7025 | D65: NEST New York | E65: 2154 | F65: 5 | G65: 2 | H65: 2 oz / 70 g | I65: Size + Concentration + Formulation | J65: 2 oz / 70 g candle | M65: 18 | P65: 0 | Q65: 0 | R65: 1 | S65: 0 | T65: 0 | U65: ['Vegan', 'Without Phthalates', 'Without Parabens', 'Without Sulfates SLS & SLES', 'Cruelty-Free'] | V65: Fragrance | W65: Candles & Home Scents | X65: Candles | Y65: 0 | AC65: 0.0068168011
A66: P470049 | B66: Clearcalm Clarifying Clay Cleanser | C66: 5857 | D66: REN Clean Skincare | E66: 4303 | F66: 4.6 | G66: 40 | H66: 5.1 oz/ 150 mL | I66: Size | J66: 5.1 oz/ 150 mL | L66: ['Aqua (Water), Kaolin, Cetearyl Alcohol, Caprylic/Capric Triglyceride, Sesamum Indicum (Sesame) Seed Oil, Cetearyl Glucoside, Glycerin, Benzyl Alcohol, Helianthus Annuus (Sunflower) Seed Oil, Salix Nigra (Willow) Bark Extract, Zinc Gluconate, Bisabolol, Oryzanol, Salvia Officinalis (Sage) Oil, Lavandula Angustifolia (Lavender) Oil, Linalool, Calendula Officinalis Flower Extract, Leptospermum Scoparium Oil, Tocopherol, Dehydroacetic Acid, Anthemis Nobilis (Chamomile) Flower Oil, Citral, Xanthan Gum, Lactic Acid, Citronellol, Farnesol, Limonene, Crataegus Oxyacantha Stem Extract, Glucose.'] | M66: 38 | P66: 0 | Q66: 0 | R66: 0 | S66: 0 | T66: 0 | U66: ['Good for: Acne/Blemishes', 'Fragrance Free', 'Gluten Free', 'Cruelty-Free', 'Clean at Sephora'] | V66: Skincare | W66: Cleansers | X66: Face Wash & Cleansers | Y66: 0 | AC66: 0.0069781229
A67: P502989 | B67: Total Coverage Body Makeup Sponge | C67: 3902 | D67: SEPHORA COLLECTION | E67: 1080 | F67: 4 | G67: 4 | M67: 14 | P67: 0 | Q67: 1 | R67: 0 | S67: 0 | T67: 1 | U67: ['Recyclable Packaging', 'Pressed Powder Formula', 'Cream Formula', 'Liquid Formula'] | V67: Makeup | W67: Brushes & Applicators | X67: Sponges & Applicators | Y67: 0 | AC67: 0.0070355904
A68: P431192 | B68: Curl Corps Curl Enhancing Hair Gel | C68: 6004 | D68: amika | E68: 14341 | F68: 4.2192 | G68: 73 | H68: 6.7 oz/ 200 mL | I68: Size | J68: 6.7 oz/ 200 mL | L68: ['Water/Eau/Aqua, Glycerin, PEG-6 Caprylic/Capric Glycerides, Hippophae Rhamnoides (Sea Buckthorn/Argousier) Extract, Avena Sativa (Oat/Avoine) Peptide, Glycine Soja (Soybean/Soja) Protein, Hydrolyzed Wheat Protein, PEG-40 Hydrogenated Castor Oil, Guar Hydroxypropyltrimonium Chloride, Propylene Glycol, Caprylyl Glycol, Hydroxyethylcellulose, Butylene Glycol, 1,2-Hexanediol, Polysorbate 60, Glyoxal, Phenoxyethanol, Sodium Benzoate, Potassium Sorbate, Fragrance/Parfum, Citric Acid, Sodium Phosphate, Disodium Phosphate, Benzoic Acid, Benzyl Alcohol, Butylphenyl Methylpropional, Hydroxycitronellal, Hydroxyisohexyl 3-Cyclohexene Carboxaldehyde, Limonene.'] | M68: 28 | P68: 0 | Q68: 0 | R68: 1 | S68: 0 | T68: 0 | U68: ['Vegan', 'Clean at Sephora', 'Coily Hair', 'Good for: Frizz', 'Curly Hair', 'Good for: Dryness'] | V68: Hair | W68: Hair Styling & Treatments | X68: Hair Styling Products | Y68: 0 | AC68: 0.0073443129
A69: P417213 | B69: Nectarine Blossom & Honey Body CrÃ¨me | C69: 6202 | D69: Jo Malone London | E69: 4100 | F69: 4.5 | G69: 14 | H69: 5.9 oz/ 175 mL | I69: Size | J69: 5.9 oz/ 175 mL | L69: ['Water, Glycerin, Cetearyl Alcohol, Simmondsia Chinensis (Jojoba) Seed Oil, Fragrance, Glyceryl Stearate, Stearic Acid, Triethanolamine, Theobroma Cacao (Cocoa) Seed Butter, Prunus Amygdalus Dulcis (Sweet Almond) Oil, Isopropyl Palmitate, Dimethicone, Aloe Barbadensis Leaf Extract, Bisabolol, Caffeine, Cocamidopropyl Pg-Dimonium Chloride Phosphate, Glyceryl Laurate, Hexylene Glycol, Caprylyl Glycol, Disodium Edta, Citral, Limonene, Hydroxyisohexyl 3-Cyclohexene Carboxaldehyde, Citronellol, Linalool, Geraniol, Phenoxyethanol <ILN39546>.'] | M69: 90 | P69: 0 | Q69: 0 | R69: 0 | S69: 0 | T69: 0 | V69: Bath & Body | W69: Body Moisturizers | X69: Body Lotions & Body Oils | Y69: 0 | AC69: 0.0073452671
A70: P501767 | B70: Flor de la Virgen Eau de Parfum Travel Spray | C70: 7101 | D70: Boy Smells | E70: 1458 | F70: 4.4242 | G70: 66 | H70: .34 oz / 10 mL eau de parfum spray | I70: Size + Concentration + Formulation | J70: .34 oz / 10 mL eau de parfum spray | L70: ['Alcohol Denat., Parfum (Fragrance), Aqua (Water/Eau), Alpha-isomethyl Ionone, Benzyl Salicylate, Butylphenyl Methylpropional, Citral, Citronellol, Farnesol, Geraniol, Limonene, Linalool.'] | M70: 30 | P70: 0 | Q70: 0 | R70: 0 | S70: 0 | T70: 0 | U70: ['Vegan', 'Unisex/ Genderless Scent', 'Floral Scent', 'Without Phthalates', 'Without Parabens', 'Cruelty-Free'] | V70: Fragrance | W70: Women | X70: Rollerballs & Travel Size | Y70: 0 | AC70: 0.0074106861
A71: P446612 | B71: Instant Magic Facial Dry Sheet Mask | C71: 6236 | D71: Charlotte Tilbury | E71: 11527 | F71: 3.4906 | G71: 53 | H71: 1 mask | I71: Size | J71: 1 mask | L71: ['Stearic Acid, Butyrosperum Parkii (Shea) Butter, Glycerin, Olea Europeaea (Olive) Fruit Oil, Mangifera Indica (Mango) Seed Butter, Persea Gratissima (Avocado) Oil, Peg-20 Methyl Glucose Sesquistearate, Cetyl Ricinoleate, Hydrogenated Vegetable Oil, Cetyl Alcohol, Tocopheryl Acetate, Sorbitan Oleate, Sorbitan Stearate, Glyceryl Stearate, Glycine Soja (Soybean) Oil, Acacia Senegal Gum, Ethylhexylglycerin, Caprylyl Glycol, Cetearyl Olivate, Niacinamide, Benzyl Alcohol, Sorbitan Olivate, Butylene Glycol, Arginine, Leontopodium Alpinum Callus Culture Extract, Pentaerythrityl Tetra-Di-t-Butyl Hydroxyhydrocinnamate, Calcium Titanium Borosilicate, Disodium Edta, Magnolia Officinalis Bark Extract, Helianthus Annuus (Sunflower Seed Oil), Xanthan Gum, Dicaprylyl Ether, Rosmarinus Officinalis (Rosemary) Leaf Extract, Carbomer Algae (Dictyopteris Membranacca) Extract, Polysorbate 20, Sodium Lactate, Magnolia Gradiflora Bark Extract, Luaryl Alcohol, Crocus Sativus Flower Extract, Citric Acid, Tocopherol, Palmitoyl Tripeptide-1, Palmitoyl Tetrapeptide-7, Tin Oxide (Ci 77861), Titanium Dioxide (Ci 77891), Mica (Ci 77019), Carmine (Ci 75470).'] | M71: 25 | P71: 0 | Q71: 0 | R71: 0 | S71: 1 | T71: 0 | V71: Skincare | W71: Masks | X71: Sheet Masks | Y71: 0 | AC71: 0.0074297889
A72: P136025 | B72: Burberry London | C72: 1179 | D72: BURBERRY | E72: 8056 | F72: 4.6875 | G72: 272 | H72: 3.3 oz/ 100 mL | I72: Size + Concentration + Formulation | J72: 3.3 oz/ 100 mL | L72: ['Alcohol Denat., Fragrance, Water, Benzyl Salicylate, Ethylhexyl Methoxycinnamate, Limonene, Butylphenyl Methylpropional, Linalool, Hexyl Cinnamal, Benzophenone-3, Ethylhexyl Salicylate, Butyl Methoxydibenzoylmethane, Citronellol, Alpha-Isomethyl Ionone, Geraniol, Eugenol, Isoeugenol, Benzyl Benzoate, Citral, Benzyl Alcohol, Bht, Ext. Violet 2 (Ci 60730), Red 33 (Ci 17200), Yellow 5 (Ci 19140).'] | M72: 112 | P72: 0 | Q72: 0 | R72: 0 | S72: 0 | T72: 0 | V72: Fragrance | W72: Women | X72: Perfume | Y72: 1 | Z72: 90 | AA72: 90 | AC72: 0.0074331822
A73: P434402 | B73: Nutritive Heat Protecting Leave-In Treatment For Dry Hair | C73: 6259 | D73: KÃ©rastase | E73: 40523 | F73: 4.6966 | G73: 323 | H73: 5.1 oz/ 150 mL | I73: Size | J73: 5.1 oz/ 150 mL | L73: ['Water, C13-16 Isoparaffin, Propylene Glycol, Dimethicone, Triethanolamine, Phenoxyethanol, Peg/Ppg-17/18 Dimethicone, Carbomer, Potato Starch Modified, Behentrimonium Chloride, Hydroxypropyl Guar, Caprylyl Glycol, Polyquaternium-4, Amodimethicone, Poly(Linseed Oil), Linalool, Butylphenyl Methylpropional, Benzophenone-4, Hexyl Cinnamal, Benzyl Salicylate, Benzyl Alcohol, Citronellol, Alpha-Isomethyl Ionone, Trideceth-6, 2-Oleamido-1,3-Octadecanediol, Xylose, Hydroxycitronellal, Coumarin, Limonene, Iris Florentina / Iris Florentina Root Extract, Cetrimonium Chloride, Royal Jelly / Royal Jelly Extract, Fragrance.'] | M73: 45 | P73: 0 | Q73: 0 | R73: 0 | S73: 0 | T73: 1 | U73: ['Hydrating', 'Heat Protection', 'All Hair Types', 'Good for: Frizz', 'Good for: Dryness', 'Increases Shine'] | V73: Hair | W73: Hair Styling & Treatments | X73: Hair Primers | Y73: 0 | AC73: 0.0074424048
A74: P67988453 | B74: Gloss Bomb Universal Lip Luminizer | C74: 6200 | D74: Fenty Beauty by Rihanna | E74: 968317 | F74: 4.6357 | G74: 12136 | H74: 0.30 oz/ 9 mL | I74: Color | J74: Fenty Glow | K74: shimmering rose nude | L74: ['Polybutene, Octyldodecanol, Bis-Diglyceryl Polyacyladipate-2, Tricaprylin, Cera Microcristallina/Microcrystalline Wax/Cire Microcristalline, Polyethylene, Silica Dimethyl Silylate, Vp/Eicosene Copolymer, Vp/Hexadecene Copolymer, Butyrospermum Parkii (Shea) Butter, Mica, Sorbitan Oleate, Silica, Octyldodecyl Neopentanoate, Ethylhexyl Palmitate, Caprylyl Glycol, Butyrospermum Parkii (Shea) Butter Unsaponifiables, Aroma/Flavor, Parfum/Fragrance, Tribehenin, Pentaerythrityl Tetra-Di-T-Butyl Hydroxyhydrocinnamate, Sorbitan Isostearate, Tocopherol, Tocopheryl Acetate, Synthetic Fluorphlogopite, Tetrahexyldecyl Ascorbate, Lactic Acid, Calcium Sodium Borosilicate, Calcium Aluminum Borosilicate, Polyethylene Terephthalate, Palmitoyl Tripeptide-1, Acrylates Copolymer, Tin Oxide, Titanium Dioxide (CI 77891), Iron Oxides (CI 77491, CI 77499), Benzyl Benzoate, Limonene.'] | M74: 21 | P74: 0 | Q74: 0 | R74: 0 | S74: 0 | T74: 0 | U74: ['Vegan', 'Community Favorite', 'Shimmer Finish'] | V74: Makeup | W74: Lip | X74: Lip Gloss | Y74: 6 | Z74: 21 | AA74: 20 | AC74: 0.007521662
A75: P428255 | B75: Capture Youth Serum Collection | C75: 1073 | D75: Dior | E75: 47079 | F75: 4.2434 | G75: 152 | H75: 1 oz/ 30 mL | I75: Type | J75: Glow Booster Age-Delay Illuminating Serum | L75: ['Aqua (Water), Dipropylene Glycol, Glycerin, Glycolic Acid, 3-O-Ethyl Ascorbic Acid, Ppg-26-Buteth-26, Tromethamine, Phenoxyethanol, Parfum (Fragrance), Peg-40 Hydrogenated Castor Oil, Sodium Citrate, Tetrasodium Edta, Terminalia Ferdinandiana Fruit Extract, Xanthan Gum, Adenosine, Sodium Tocopheryl Phosphate, Sodium Metabisulfite, Ci 15985 (Yellow 6), Iris Florentina Root Extract, Bht, Tocopherol.'] | M75: 110 | P75: 0 | Q75: 0 | R75: 0 | S75: 0 | T75: 0 | U75: ['Good for: Dullness/Uneven Texture', 'Good for: Dark spots', 'Vitamin C', 'AHA/Glycolic Acid', 'Without Sulfates SLS & SLES', 'Without Parabens'] | V75: Skincare | W75: Treatments | X75: Face Serums | Y75: 2 | Z75: 110 | AA75: 110 | AC75: 0.007958474
A76: P431164 | B76: No.02 Le Long Fond Perfume Oil | C76: 6250 | D76: Maison Louis Marie | E76: 3431 | F76: 4.45 | G76: 20 | H76: 0.50 oz/ 15mL | I76: Size + Concentration + Formulation | J76: 0.50 oz/ 15mL Oil | L76: ['Fragrance/Parfum, Carthamus Tinctorius (Safflower) Seed Oil, Helianthus Annuus (Sunflower) Seed Oil, Rosmarinus Officinalis (Rosemary) Leaf Extract,', 'Citronellol, Eugenol, Geraniol, Limonene, Linalool'] | M76: 65 | P76: 0 | Q76: 0 | R76: 0 | S76: 0 | T76: 0 | U76: ['Clean + Planet Positive', 'Without Parabens', 'Without Phthalates', 'Woody & Earthy Scent', 'Vegan'] | V76: Bath & Body | W76: Body Moisturizers | X76: Body Lotions & Body Oils | Y76: 1 | Z76: 16 | AA76: 16 | AC76: 0.0080863491
A77: P67617 | B77: Amazonian Clay BB Tinted Moisturizer Broad Spectrum SPF 20 Sunscreen | C77: 5648 | D77: tarte | E77: 78502 | F77: 4.2289 | G77: 2586 | H77: 1.7 oz | I77: Color | J77: Ivory | K77: for ivory/fair complexions with beige undertones | L77: ['Water, Cyclopentasiloxane, Octyldodecyl Neopentanoate, Glycerin, Peg/Ppg-18/18 Dimethicone, Dimethicone, Aluminum Hydroxide, Stearic Acid, Triethoxycaprylylsilane, Saccharum Officinarum (Sugarcane) Extract, Pyrus Malus (Apple) Fruit Extract, Citrus Limon (Lemon) Fruit Extract , Citrus Aurantium Dulcis (Orange) Fruit Extract, Camellia Sinensis Leaf Extract, Panax Ginseng Root Extract, Ginkgo Biloba Leaf Extract, Chamomilla Recutita (Matricaria) Flower Extract, Kaolin, Phytantriol, Magnesium Ascorbyl Phosphate, Retinyl Palmitate, Tocopheryl Acetate, Tocopherol, Tetrahexyldecyl Ascorbate, Butylene Glycol, Methicone, Octyldodecanol, Boron Nitride, Palmitic Acid, Dextrin Palmitate, Sodium Hyaluronate, Sodium Chloride, Sodium Dehydroacetate, Hexylene Glycol, Caprylyl Glycol, Phenoxyethanol, Mica, Iron Oxides.'] | M77: 39 | P77: 0 | Q77: 0 | R77: 0 | S77: 0 | T77: 0 | V77: Makeup | W77: Face | X77: Tinted Moisturizer | Y77: 5 | Z77: 39 | AA77: 39 | AC77: 0.0081181578
A78: P404168 | B78: POWER Advanced Wrinkle Fighter Moisturizer | C78: 6018 | D78: Algenist | E78: 5169 | F78: 4.1818 | G78: 77 | H78: 2 oz/ 60 mL | I78: Size | J78: 2 oz/ 60 mL | L78: ['Water, Glycerin, C12-15 Alkyl Benzoate, Caprylic/Capric Triglyceride, Palmitic Acid, Stearic Acid, Chlorella Protothecoides, Algae Exopolysaccharides, Citrullus Vulgaris (Watermelon) Fruit Extract, Hydrolyzed Myrtus Communis Leaf Extract, Lens Esculenta (Lentil) Fruit Extract, Pyrus Malus (Apple) Fruit Extract, Collagen, Sodium PCA, Ribose, Sodium Lactate, Leuconostoc/Radish Root Ferment Filtrate, Butyrospermum Parkii (Shea) Butter, Dimethicone, Tetradecyl Aminobutyroylvalylaminobutyric Urea Trifluoroacetate, Glyceryl Stearate, Glyceryl Stearate SE, Cetearyl Alcohol, Sodium Hydroxide, Disodium EDTA, Xanthan Gum, Magnesium Chloride, Potassium Sorbate, Sodium Benzoate, Citric Acid, Ethylhexylglycerin, Chlorphenesin, Caprylyl Glycol, Phenoxyethanol, Fragrance.'] | M78: 85 | P78: 0 | Q78: 0 | R78: 0 | S78: 0 | T78: 1 | V78: Skincare | W78: Moisturizers | X78: Moisturizers | Y78: 0 | AC78: 0.0083596387
A79: P504824 | B79: Color Care Conditioner | C79: 6182 | D79: Moroccanoil | E79: 221 | F79: 4.848 | G79: 171 | H79: 8.5 oz / 250 mL | I79: Size | J79: 8.5 oz / 250 mL | L79: ['Aqua/Water/Eau, Cetearyl Alcohol, PEG/PPG-20/20 Phenylisopropyl Caprylyl Dimethicone, Cetyl Alcohol, Stearamidopropyl Dimethylamine, Behentrimonium Chloride, Quaternium-91, Argania Spinosa (Argan) Kernel Oil, Helianthus Annuus (Sunflower) Seed Oil, Parfum/Fragrance, Pyrus Malus (Apple) Fruit Extract, Punica Granatum (Pomegranate) Fruit Extract, Prunus Armeniaca (Apricot) Kernel Oil, Glycerin, PPG-3 Benzyl Ether Myristate, Isopropyl Alcohol, Panthenol, Quaternium-95, Caprylic/Capric Triglyceride, Hydroxyacetophenone, Caprylyl Glycol, Chitosan, Guar Hydroxypropyltrimonium Chloride, Citric Acid, EDTA, PEG-12 Allyl Ether, PEG-12 Dimethicone, Amodimethicone/Morpholinomethyl Silsesquioxane Copolymer, Trideceth-5, Silica Dimethyl Silylate, Algin, Pentaerythrityl Tetra-Di-T-Butyl Hydroxyhydrocinnamate, Chlorphenesin, C12-13 Pareth-9, Propanediol, Sodium Benzoate, Potassium Sorbate, Phenoxyethanol, Sorbic Acid.'] | M79: 26 | P79: 0 | Q79: 1 | R79: 0 | S79: 0 | T79: 0 | U79: ['Sustainable Packaging', 'Good for: Color Care', 'Prevents Color Fading', 'Without Sulfates SLS & SLES', 'Increases Shine', 'Cruelty-Free'] | V79: Hair | W79: Shampoo & Conditioner | X79: Conditioner | Y79: 1 | Z79: 12 | AA79: 12 | AC79: 0.0085506128
A80: P429566 | B80: French Cade & Lavender Decorative Tin Candle | C80: 6245 | D80: VOLUSPA | E80: 3348 | F80: 4 | G80: 20 | H80: 12 oz/ 340 g | I80: Size + Concentration + Formulation | J80: 12 oz/ 340 g 3-wick Candle | L80: ['Coconut Oil, Petrolatum, Paraffin Wax, Benzyl Benzoate, 2-t-butylcyclohexyl oxybutanol, Tetramethylacetyloctahydronaphthalenes, Linalool, 2,6-dimethyl-7-octen-2-ol, Musk Ketone, Butylphenyl Methylpropional, Linalyl Acetate, Ethyl Trimethylcyclopentene Butenol, Hexyl Cinnamal, Ethyl Linalool, Limonene, Acetylcedrene.'] | M80: 26 | P80: 0 | Q80: 0 | R80: 1 | S80: 0 | T80: 0 | U80: ['Woody & Earthy Scent'] | V80: Fragrance | W80: Candles & Home Scents | X80: Candles | Y80: 1 | Z80: 12 | AA80: 12 | AC80: 0.0087204775
A81: P503601 | B81: Discovery Sampler Set | C81: 6745 | D81: KAYALI | E81: 45869 | F81: 3.6066 | G81: 61 | L81: ['Vanilla | 28:', 'SD Alcohol 40-B/Alcohol Denat., Fragrance/Parfum, Water / Aqua / Eau, Butyl Methoxydibenzoylmethane, Alcohol, Tris(Tetramethylhydroxypiperidinol) Citrate, Ci 19140 (Yellow 5), Ci 60730 (Violet 2), Ci 14700 (Red 4), Citronellol, Coumarin, Limonene, Benzyl Salicylate, Butylphenyl Methylpropional.', 'Eden Juicy Apple | 01:', 'SD Alcohol 40-B/Alcohol Denat., Fragrance/Parfum, Water/Aqua/Eau, Linalool, Ethylhexyl Methoxycinnamate, Ethylhexyl Salicylate, Butyl Methoxydibenzoylmethane, Bht, Citral, Citronellol, Geraniol, Hydroxycitronellal, Limonene, Benzyl Salicylate.', 'Sweet Diamond Pink Pepper | 25:', 'Alcohol Denat./Sd Alcohol 40-B, Fragrance/Parfum, Water/Aqua/Eau, Avobenzone/Butyl Methoxydibenzoylmethane, Alcohol, Tris (Tetramethylhydroxypiperidinol) Citrate, Citral, Citronellol, Eugenol, Geraniol, Isoeugenol, Limonene, Linalool, Benzyl Salicylate, Ext. Violet 2/Ci 60730, Red 4/Ci 14700, Yellow 5/Ci 19140.', 'Utopia Vanilla Cocoa | 21:', 'SD Alcohol 40-B/Alcohol Denat., Fragrance/Parfum, Water/Aqua/Eau, Ethylhexyl Methoxycinnamate, Ethylhexyl Salicylate, Avobenzone/Butyl Methoxydibenzoylmethane, BHT, Citral, Geraniol, Limonene, Linalool, Benzyl Alcohol, Benzyl Salicylate.', 'Lovefest Burning Cherry | 48:', 'Sd Alcohol 40-B/Alcohol Denat., Fragrance/Parfum, Water/Aqua/Eau, Citral, Citronellol, Coumarin, Eugenol, Geraniol, Hydroxycitronellal, Isoeugenol, Limonene, Linalool, Anise Alcohol, Benzyl Alcohol, Benzyl Benzoate, Benzyl Cinnamate, Benzyl Salicylate. 70%', 'Invite Only Amber | 23:', 'Alcohol Denat./Sd Alcohol 40-B, Fragrance/Parfum, Water/Aqua/Eau, Avobenzone/Butyl Methoxydibenzoylmethane, Alcohol, Tris (Tetramethylhydroxypiperidinol) Citrate, Alpha-Isomethyl Ionone, Benzyl Benzoate, Cinnamal, Cinnamyl Alcohol, Coumarin, Linalool, Red 4/Ci 14700, Blue 1/Ci 42090, Ext. Violet 2/Ci 60730.', 'DÃ©jÃ vu White Flower | 57:', 'Sd Alcohol 40-B/Alcohol Denat., Fragrance/Parfum, Water/Aqua/Eau, Avobenzone/Butyl Methoxydibenzoylmethane, Alcohol, Tris(Tetramethylhydroxypiperidinol) Citrate, Yellow 5 / Ci 19140, Ext. Violet 2 / Ci 60730, Red 4 / Ci 14700, Citral, Citronellol, Eugenol, Farnesol, Geraniol, Hydroxycitronellal, Isoeugenol, Limonene, Linalool, Benzyl Alcohol, Benzyl Benzoate. 70% Alcohol', 'Musk | 12:', 'Sd Alcohol 40-B/Alcohol Denat., Fragrance/Parfum, Water / Aqua / Eau, Ethylhexyl Methoxycinnamate, Ethylhexyl Salicylate, Butyl Methoxydibenzoylmethane, Alcohol, Tris(Tetramethylhydroxypiperidinol)Citrate, Ci 60730 (Violet 2), Bht, Ci 19140 (Yellow 5), Ci 14700 (Red 4), Alpha-Isomethyl Ionone, Coumarin, Butylphenyl Methylpropional.'] | M81: 25 | P81: 0 | Q81: 0 | R81: 0 | S81: 0 | T81: 0 | U81: ['Unisex/ Genderless Scent', 'Layerable Scent', 'Warm &Spicy Scent', 'Woody & Earthy Scent', 'Floral Scent', 'Cruelty-Free'] | V81: Fragrance | W81: Value & Gift Sets | X81: Perfume Gift Sets | Y81: 0 | AC81: 0.0087686735
A82: P217513 | B82: Black Tea Instant Perfecting Mask | C82: 4348 | D82: fresh | E82: 65834 | F82: 4.2919 | G82: 908 | H82: 3.3 oz/ 100 mL | I82: Size | J82: 3.3 oz/ 100 mL | L82: ['Water, Glycerin, Rice Ferment Filtrate (Sake), Caprylic/Capric', 'Triglyceride, Pentylene Glycol, Sodium Polyacrylate, Betaine, Saccharomyces Ferment', 'Filtrate, Camellia Sinensis Leaf Extract, Avena Sativa (Oat) Kernel Extract, Vitis Vinif-', 'era (Grape) Seed Oil, Litchi Chinensis Seed Extract, Rubus Fruticosus (Blackberry) Leaf', 'Extract, Rosa Damascena Flower Oil, Sodium Hyaluronate, Adenosine, Tocopheryl Ac-', 'etate, Tocopherol, Ethylhexyl Palmitate, Poloxamer 407, Butylene Glycol, Parfum', '(Fragrance), Hydrogenated Lecithin, Menthoxypropanediol, Maltodextrin, Silica, CI', '77891 (Titanium Dioxide), Trihydroxystearin, Hydroxyethylcellulose, Disodium', 'EDTA, Sodium Citrate, Caprylyl Glycol, Citric Acid, Caramel, Hexylene Glycol,', 'Potassium Sorbate, BHT, Biotin, Phenoxyethanol, Linalool.'] | M82: 96 | P82: 0 | Q82: 0 | R82: 0 | S82: 0 | T82: 0 | V82: Skincare | W82: Masks | X82: Face Masks | Y82: 1 | Z82: 40 | AA82: 40 | AC82: 0.0089722321
A83: P434455 | B83: Laque Couture Medium Hold Hair Spray | C83: 6259 | D83: KÃ©rastase | E83: 2997 | F83: 4.1 | G83: 10 | H83: 8.8 oz/ 249 g | I83: Size | J83: 8.8 oz/ 249 g | L83: ['Alcohol Denat, Hydrofluorocarbon 152a, Butane, Va/Crotonates/Vinyl Neodecanoate Copolymer, Water, Aminomethyl Propanol, Benzyl Salicylate, Peg/Ppg-4/12 Dimethicone, Limonene, Benzyl Alcohol, Linalool, Citronellol, Geraniol, Hexyl Cinnamal, Hydroxycitronellal, Alpha-Isomethyl Ionone, Fragrance.'] | M83: 32 | P83: 0 | Q83: 0 | R83: 0 | S83: 0 | T83: 1 | U83: ['Good for: Color Care', 'Heat Protection', 'All Hair Types', 'Good for: Frizz', 'UV Protection'] | V83: Hair | W83: Hair Styling & Treatments | X83: Hair Spray | Y83: 0 | AC83: 0.0091550646
A84: P461633 | B84: Color Fanatic Heat Protectant Leave-In Conditioner | C84: 6330 | D84: Pureology | E84: 48940 | F84: 4.5761 | G84: 1937 | H84: 6.7 oz / 200 mL | I84: Size | J84: 6.7 oz / 200 mL | L84: ['Aqua/Water/Eau, Cocos Nucifera Oil/Coconut Oil, Amodimethicone, Polyquaternium-37, Ppg-5-Ceteth-10 Phosphate, Phenoxyethanol, Propylene Glycol Dicaprylate/Dicaprate, Acetamide Mea, Sodium Hydroxide, Parfum/Fragrance, Lactamide Mea, Dimethicone, Butylene Glycol, Ppg-1 Trideceth-6, Trideceth-6, Behentrimonium Chloride, Xylose, Ethylhexylglycerin, Helianthus Annuus Seed Extract/Sunflower Seed Extract, Linalool, Dimethiconol, Benzophenone-4, Isopropyl Alcohol, Cetrimonium Chloride, Tocopherol, Camelina Sativa Seed Oil, Ascorbyl Glucoside, Olea Europaea Fruit Oil/Olive Fruit Oil, Benzyl Alcohol, Geraniol, Citronellol, Benzyl Salicylate, Hydrolyzed Vegetable Protein Pg-Propyl Silanetriol, Isoeugenol, Bht, Sodium Chloride, Melanin, Potassium Sorbate, Pentylene Glycol, Citric Acid.'] | M84: 34 | P84: 0 | Q84: 1 | R84: 0 | S84: 0 | T84: 0 | U84: ['Good for: Damage', 'Vegan', 'Heat Protection', 'Good for: Dryness', 'Increases Shine', 'Cruelty-Free'] | V84: Hair | W84: Hair Styling & Treatments | X84: Leave-In Conditioner | Y84: 2 | Z84: 51 | AA84: 11 | AC84: 0.0092558161
A85: P429278 | B85: Effortless Kit - No Trim No Measure Natural Lash Kit | C85: 7064 | D85: Velour Lashes | E85: 48693 | F85: 3.9385 | G85: 423 | I85: Type | J85: Would I Lie? | K85: naturally flared & crisscrossed | L85: ['False Lashes:', 'Cruelty Free, Synthetic Silk Material on an invisible band.', 'Lash Adhesive:'] | M85: 29 | N85: 39 | P85: 0 | Q85: 0 | R85: 0 | S85: 0 | T85: 1 | U85: ['Natural Finish', 'Volumizing', 'Lengthening', 'Hypoallergenic', 'allure 2020 Best of Beauty Award Winner', 'Cruelty-Free'] | V85: Makeup | W85: Eye | X85: False Eyelashes | Y85: 0 | AC85: 0.0093819525
A86: P475998 | B86: Mini Hydration Shampoo | C86: 6366 | D86: PATTERN by Tracee Ellis Ross | E86: 2238 | F86: 3.7778 | G86: 9 | H86: 3 oz/ 88.7 mL | I86: Size | J86: 3 oz/ 88.7 mL | L86: ['Aqua (Water, Eau), Sodium C14-16 Olefin Sulfonate, Cocamidopropyl Betaine, Propanediol, Glycol Distearate, Argania Spinosa Kernel Oil, Cocos Nucifera (Coconut) Oil, Mel (Honey, Miel), Melaleuca Alternifolia (Tea Tree) Leaf Oil, Olea Europaea (Olive) Fruit Oil, Biotin, Persea Gratissima (Avocado) Oil, Ricinus Communis (Castor) Seed Oil, Simmondsia Chinensis (Jojoba) Seed Oil, Butyrospermum Parkii (Shea) Butter, Aloe Barbadensis Leaf Juice, Prunus Amygdalus Dulcis (Sweet Almond) Oil, Glycine Soja (Soybean) Oil, Glycine Soja (Soybean) Sterols, Glycolipids, Glycerin, Phospholipids, Amodimethicone, Guar Hydroxypropyltrimonium Chloride, Hydroxyethylcellulose, Lauryl Lactyl Lactate, Hydroxyacetophenone, PEG-150 Distearate, Parfum (Fragrance), Hydrolyzed Vegetable Protein PG-Propyl Silanetriol, Celluose, Phenoxyethanol, Citric Acid, PEG-150 Stearate, Disodium EDTA, PEG-1M, Stearic Acid, Sodium Hydroxide, Sodium Acetate, Potassium Sorbate, Sodium Benzoate, Linalool.'] | M86: 9 | P86: 0 | Q86: 0 | R86: 1 | S86: 0 | T86: 0 | U86: ['Good for: Color Care', 'Curl-Enhancing', 'Good for: Dryness', 'Curly Hair', 'Without Parabens', 'Without Sulfates SLS & SLES'] | V86: Hair | W86: Shampoo & Conditioner | X86: Shampoo | Y86: 0 | AC86: 0.0098043688
A87: P470063 | B87: Donna Born in Roma Yellow Dream Eau de Parfum | C87: 1169 | D87: Valentino | E87: 15990 | F87: 4.6551 | G87: 316 | H87: 3.4 oz/ 100 mL | I87: Size + Concentration + Formulation | J87: 3.4 oz/ 100 mL Eau de Parfum Spray | L87: ['Alcohol, Parfum/Fragrance, Aqua/Water/Eau, Hydroxycitronellal, Ethylhexyl Salicylate, Butyl Methoxydibenzoylmethane, Limonene, Linalool, Citronellol, Geraniol, Benzyl Alcohol, Coumarin, Cinnamyl Alcohol, Methyl Anthranilate, Citral, Tris (Tetramethylhydroxypiperidinol) Citrate, Isoeugenol, Eugenol, Benzyl Benzoate, CI 14700/Red 4, CI 19140/Yellow 5, CI 60730/Ext. Violet 2.'] | M87: 156 | P87: 0 | Q87: 0 | R87: 0 | S87: 0 | T87: 0 | V87: Fragrance | W87: Women | X87: Perfume | Y87: 2 | Z87: 130 | AA87: 35 | AC87: 0.0098754812
A88: P183301 | B88: Black Orchid Eau de Parfum | C88: 5869 | D88: TOM FORD | E88: 54405 | F88: 4.2191 | G88: 1912 | H88: 1.7oz/ 50mL | I88: Size + Concentration + Formulation | J88: 1.7oz/ 50mL | L88: ['Alcohol Denat., Water, Fragrance, Benzyl Salicylate, Linalool, Hydroxycitronellal, Benzyl Benzoate, Geraniol, Limonene, Coumarin, Cinnamyl Alcohol, Citronellol, Eugenol, Isoeugenol, Benzyl Alcohol, Citral, Farnesol, Cinnamal, Methyl 2-Octynoate, Benzyl Cinnamate <ILN34117>.'] | M88: 150 | P88: 0 | Q88: 0 | R88: 0 | S88: 0 | T88: 0 | V88: Fragrance | W88: Women | X88: Perfume | Y88: 3 | Z88: 215 | AA88: 50 | AC88: 0.01012277
A89: P422239 | B89: BodyWaver 1.75â€ Professional Ceramic Styling Iron for Waves and Volume (White & Rose Gold) | C89: 5780 | D89: T3 | E89: 10547 | F89: 3.3846 | G89: 65 | M89: 169.99 | P89: 0 | Q89: 0 | R89: 0 | S89: 0 | T89: 0 | U89: ['Good for: Volume', 'Good for: Frizz', 'All Hair Types', 'Increases Shine'] | V89: Hair | W89: Tools | X89: Curling Irons | Y89: 0 | AC89: 0.010441389
A90: P470065 | B90: Superclay Purify + Clear Power Mask with Niacinamide | C90: 6169 | D90: Youth To The People | E90: 62672 | F90: 4.4595 | G90: 346 | H90: 2.0 oz/ 60 mL | I90: Size | J90: 2.0 oz/ 60 mL | L90: ['Aqua/Water/Eau, Kaolin, Stearyl Alcohol,Propanediol,Glycerin, Glyceryl Stearate, Niacinamide, Oryza Sativa (Rice) Starch, Bentonite (Volcanic Clay), Cetyl Alcohol, Magnesium Aluminum Silicate, Montmorillonite (French Green Clay), Illite, Calcite, Salicylic Acid, Salix Purpurea (Red Willow) Bark Extract, Saccharomyces/Xylinum/Black Tea Ferment, Allantoin, Carthamus Tinctorius (Safflower) Seed Oil, Phycocyanin (Blue Green Algae), Aloe Barbadensis Leaf Juice, Glyceryl Acrylate/Acrylic Acid Copolymer, Cetearyl Olivate, Sorbitan Olivate, Triticum Aestivum (Wheatgrass) Leaf Extract, Lactic Acid, Sorbitan Stearate, Caprylhydroxamic Acid, Charcoal Powder, Sodium Citrate, 1,2-Hexanediol, Phenoxyethanol, Quartz, Silica, Sodium Benzoate, Potassium Sorbate, Maltodextrin, Gardenia Florida Fruit Extract'] | M90: 38 | P90: 0 | Q90: 0 | R90: 0 | S90: 0 | T90: 0 | U90: ['Vegan', 'Best for Oily Skin', 'Good for: Pores', 'Clean + Planet Positive', 'Fragrance Free', 'Niacinamide'] | V90: Skincare | W90: Masks | X90: Face Masks | Y90: 0 | AC90: 0.010582295
A91: P502042 | B91: Sparkling Cuvee Glass Home Diffuser | C91: 6245 | D91: VOLUSPA | E91: 754 | F91: 4.2 | G91: 5 | H91: 3.4 oz / 100 mL | I91: Size + Concentration + Formulation | J91: 3.4 oz / 100 mL | M91: 32 | P91: 0 | Q91: 0 | R91: 1 | S91: 0 | T91: 0 | U91: ['Vegan', 'Without Phthalates', 'Without Parabens', 'Without Sulfates SLS & SLES', 'Cruelty-Free'] | V91: Fragrance | W91: Candles & Home Scents | X91: Diffusers | Y91: 0 | AC91: 0.010757377
A92: P456989 | B92: Super Glow Body Hyaluronic Self-Tan Serum | C92: 6225 | D92: TAN-LUXE | E92: 6917 | F92: 3.6809 | G92: 47 | H92: 5.07 oz/ 150 mL | I92: Size | J92: 5.07 oz/ 150 mL | L92: ['Aqua (Water), Glycerin, Dihydroxyacetone, Hydrolyzed Soybean Fiber, Hyaluronic Acid, Beta Vulgaris (Beet) Root Extract, Brassica Oleracea Acephala (Kale) Leaf Extract, Sodium Hyaluronate, Rubus Idaeus (Raspberry) Seed Oil, Cocos Nucifera (Coconut) Oil, Persea Gratissima (Avocado) Oil, Salvia Hispanica (Sage) Seed Oil, Vaccinium Myrtillus (Myrtle) Fruit Extract, Theobroma Cacoa (Cocoa) Seed Extract, Aloe Barbadensis (Aloe Vera) Leaf Juice, Caffeine, Palmitoyl Carnitine, Tocopheryl Acetate, Ascorbic Acid, Retinyl Acetate, Erythrulose, Cyclopentasiloxane, Polyacrylamide, C13-14 Isoparaffin, Glyceryl Acrylate/Acrylic Acid Copolymer, Dimethicone Crosspolymer, Dimethicone, PVM/MA Copolymer, Laureth-7, Laureth-23, Laureth-4, Butylene Glycol, Ethylhexylglycerin Parfum (Fragrance), Limonene, Geraniol, Hexyl Cinnamal, Benzyl Salicylate, Sodium Metabisulfite, Citric Acid, Tetrasodium EDTA, Phenoxyethanol, Sclerotium Gum, Lecithin, Xanthan Gum, Triethylene Glycol, Potassium Sorbate, CI 17200 (D&C Red No.33).'] | M92: 49 | P92: 0 | Q92: 0 | R92: 0 | S92: 0 | T92: 0 | U92: ['Vegan', 'Good for: Dullness/Uneven Texture', 'Hyaluronic Acid', 'Plumping', 'Hydrating', 'Cruelty-Free'] | V92: Skincare | W92: Self Tanners | X92: For Body | Y92: 0 | AC92: 0.010765318
A93: P469864 | B93: SEA Breezy Cream Blush | C93: 5648 | D93: tarte | E93: 20783 | F93: 4.3636 | G93: 55 | H93: 0.17 oz/ 5 g | I93: Color | J93: Peach Sunset | K93: peachy pink | L93: ['Triethylhexanoin, Synthetic Fluorphlogopite, Isodecyl Neopentanoate, Hydrogenated Polyisobutene, Isononyl Isononanoate, Polyethylene, Silica, Dimethicone, Synthetic Beeswax, Methicone, Alumina, Sodium Hyaluronate, Cocos Nucifera (Coconut) Oil, Sargassum Pacificum Thallus Extract, Gardenia Taitensis Flower Extract, Tocopherol, Titanium Dioxide (Ci 77891), Red 7 Lake (Ci 15850), Iron Oxides (Ci 77491, Ci 77492, Ci 77499).'] | M93: 27 | O93: 13 | P93: 0 | Q93: 0 | R93: 0 | S93: 1 | T93: 1 | U93: ['Vegan', 'Natural Finish', 'Cream Formula', 'Hydrating', 'Clean at Sephora', 'Long-wearing'] | V93: Makeup | W93: Cheek | X93: Blush | Y93: 3 | Z93: 27 | AA93: 7 | AC93: 0.0108007
A94: P390708 | B94: Legend Body Spray | C94: 5606 | D94: Montblanc | E94: 1653 | F94: 4.871 | G94: 31 | H94: 6.6 oz/ 200 mL | I94: Size | J94: 6.6 oz/ 200 mL | L94: ['Hydrofluorocarbon 152a, Alcohol Denat. (SD Alcohol 39-C), Parfum (Fragrance), Triethyl Citrate, Propanediol, Ethylhexyl Methoxycinnamate, Ethylhexyl Salicylate, Butyl Methoxydibenzoylmethane, Bht, Citronellol, Limonene, Linalool, Coumarin, Citral.'] | M94: 25 | P94: 0 | Q94: 0 | R94: 0 | S94: 0 | T94: 0 | V94: Bath & Body | W94: Body Care | X94: Deodorant & Antiperspirant | Y94: 0 | AC94: 0.010932534
A95: P255506 | B95: Flowerbomb | C95: 5979 | D95: Viktor&Rolf | E95: 232390 | F95: 4.585 | G95: 5039 | H95: 3.4 oz/ 100 mL | I95: Size + Concentration + Formulation | J95: 3.4 oz/ 100 mL | L95: ['Alcohol, Parfum/Fragrance, Aqua/Water, Benzyl Salicylate, Linalool, Butyl Methoxydibenzoylmethane, Ethylhexyl Methoxycinnamate, Limonene, Pentaerythrityl Tetra-Di-T-Butyl Hydroxyhydrocinnamate, Coumarin, Benzyl Alcohol, Benzyl Benzoate, Citral, Ci 19140/Yellow 5, Ci 60730/Ext. Violet 2, Ci 17200/Red 33.'] | M95: 180 | P95: 0 | Q95: 0 | R95: 0 | S95: 0 | T95: 0 | U95: ['allure 2020 Best of Beauty Award Winner', 'Floral Scent'] | V95: Fragrance | W95: Women | X95: Perfume | Y95: 5 | Z95: 224 | AA95: 35 | AC95: 0.010981775
A96: P454606 | B96: Stay Naked The Fix Powder Foundation | C96: 3806 | D96: Urban Decay | E96: 12462 | F96: 4.1551 | G96: 445 | H96: 0.21 oz/ 6 g | I96: Color | J96: 90WO | K96: ultra deep warm with a peachy undertone | L96: ['Talc, Magnesium Stearate, Polymethyl Methacrylate, Synthetic Fluorphlogopite, Isononyl Isononanoate, Nylon-12, Hydrogenated Polydecene, Vinyl Dimethicone/Methicone Silsesquioxane Crosspolymer, Diphenyl Dimethicone/Vinyl Diphenyl Dimethicone/Silsesquioxane Crosspolymer, Dimethicone, Aluminum Hydroxide, Ethylhexylglycerin, Perfluorooctyl Triethoxysilane / Perfluorohexylethyl Triethoxysilane, Lauroyl Lysine, Methicone, Hydrogenated Palm Oil, Palmitoyl Proline, Glycerin, Hydrogen Dimethicone, Aqua / Water / Eau, Sodium Palmitoyl Sarcosinate, Magnesium Palmitoyl Glutamate, Palmitic Acid, Phenoxyethanol, Moringa Oleifera Seed Extract, Disodium Phosphate, Citric Acid, Tocopherol. [+/- (May contain/Peut contenir): CI 77891 / Titanium Dioxide, CI 77491, CI 77492, CI 77499 / Iron Oxides, Mica].'] | M96: 40 | P96: 0 | Q96: 0 | R96: 0 | S96: 1 | T96: 0 | V96: Makeup | W96: Face | X96: Foundation | Y96: 2 | Z96: 40 | AA96: 40 | AC96: 0.011032244
A97: P453823 | B97: Vital-E Antioxidant Recovery Eye Cream | C97: 3728 | D97: Peter Thomas Roth | E97: 15022 | F97: 4.3255 | G97: 599 | H97: 0.5 oz/ 15 mL | I97: Size | J97: 0.5 oz/ 15 mL | L97: ['Water/Aqua/Eau, Glycerin, Dimethicone, Methyl Trimethicone, Butylene Glycol, Caprylyl Methicone, Ceresin, Dimethicone/PEG-10/15 Crosspolymer, Microcrystalline Wax, Lauryl PEG-9 Polydimethylsiloxyethyl Dimethicone, Astrocaryum Tucuma Seed Butter, Caffeine, Paraffin, Dimethylmethoxy Chromanol, Tocopherol, Bacillus, Yeast Beta-Glucan, Palmitoyl Tripeptide-5, Silybum Marianum Seed Extract, Acetyl Heptapeptide-4, Ceramide NP, Sodium Hyaluronate, Hedychium Coronarium Root Extract, Sodium PCA, Eclipta Prostrata Extract, Dunaliella Salina Extract, Panthenol, Melia Azadirachta Leaf Extract, Undaria Pinnatifida Extract, Inulin, Moringa Oleifera Seed Oil, Phenoxyethanol, Potassium Sorbate, Mannitol, Cellulose, Dipropylene Glycol, Sodium Benzoate, Sodium Citrate, Hydroxypropyl Methylcellulose, Citric Acid, Ethylhexylglycerin, Pantolactone, Caprylyl Glycol, Maltodextrin, Mica.'] | M97: 55 | P97: 0 | Q97: 0 | R97: 1 | S97: 0 | T97: 0 | V97: Skincare | W97: Eye Care | X97: Eye Creams & Treatments | Y97: 0 | AC97: 0.011059264
A98: P407040 | B98: Acne Solutions Acne + Line Correcting Serum | C98: 1254 | D98: CLINIQUE | E98: 9778 | F98: 4.1304 | G98: 115 | H98: 1 oz/ 30 mL | I98: Size | J98: 1 oz/ 30 mL | L98: ['Water, Dimethicone, Butylene Glycol, Vinyl Dimethicone/Methicone Silsesquioxane Crosspolymer, Methyl Trimethicone, Polysorbate 20, Bis-Peg-18 Methyl Ether Dimethyl Silane, Lauryl Peg-9 Polydimethylsiloxyethyl Dimethicone, Glycerin, Methyl Gluceth-20, Polysilicone-11, Oenothera Biennis (Evening Primrose) Flower Extract, Glycine Soja (Soybean) Seed Extract, Sigesbeckia Orientalis (St. Paul Wort) Extract, Salvia Sclarea (Clary) Extract, Plankton Extract, Laminaria Saccharina Extract, Acetyl Hexapeptide-8, Acetyl Glucosamine, Caffeine, Glycine Soja (Soybean) Protein, Aminopropyl Ascorbyl Phosphate, Cholesterol, Caprylyl Glycol, Micrococcus Lysate, Palmitoyl Hexapeptide-12, Lecithin, Whey Protein/Lactis Protein/Proteine Du Petit-Lait, Sodium Hyaluronate, Tocopheryl Acetate, Peg-8, Sodium Hydroxide, Ammonium Acryloyldimethyltaurate/Vp Copolymer, Xanthan Gum, Carbomer, Glyceryl Polymethacrylate, Sodium Benzoate, Sodium Citrate, Disodium Edta, Phenoxyethanol <ILN42038>.'] | M98: 52 | P98: 0 | Q98: 0 | R98: 0 | S98: 0 | T98: 0 | V98: Skincare | W98: Treatments | X98: Face Serums | Y98: 0 | AC98: 0.011129122
A99: P375853 | B99: Facial Treatment Clear Lotion Toner | C99: 6084 | D99: SK-II | E99: 24003 | F99: 4.0959 | G99: 1001 | H99: 5.4 oz | I99: Size | J99: 5.4 oz | L99: ['Water, Galactomyces Ferment Filtrate (Pitera), Butylene Glycol, Polysorbate 20, Glycerin, Sodium Hyaluronate, PEG-150, Cellulose Gum, Disodium EDTA, Citric Acid, Salicylic Acid, Lactic Acid, Malic Acid, Sodium Citrate, Sodium Benzoate, Methylparaben.'] | M99: 80 | P99: 0 | Q99: 0 | R99: 0 | S99: 0 | T99: 0 | U99: ['Good for: Dullness/Uneven Texture', 'Good for: Loss of firmness', 'Good for: Anti-Aging', 'Best for Dry, Combo, Normal Skin', 'Good for: Dark spots', 'Niacinamide'] | V99: Skincare | W99: Cleansers | X99: Toners | Y99: 0 | AC99: 0.011144605
A100: P421291 | B100: Artist Color Refillable Makeup Palette | C100: 4028 | D100: MAKE UP FOR EVER | E100: 57439 | F100: 4.73 | G100: 263 | I100: Type | J100: Large | M100: 4 | P100: 0 | Q100: 0 | R100: 0 | S100: 0 | T100: 1 | V100: Makeup | W100: Makeup Palettes | Y100: 4 | Z100: 4 | AA100: 4 | AC100: 0.011148246
...

Sheet Beauty_500_Raw
A1: product_id | B1: product_name | C1: brand_id | D1: brand_name | E1: loves_count | F1: rating | G1: reviews | H1: size | I1: variation_type | J1: variation_value | K1: variation_desc | L1: ingredients | M1: price_usd | N1: value_price_usd | O1: sale_price_usd | P1: limited_edition | Q1: new | R1: online_only | S1: out_of_stock | T1: sephora_exclusive | U1: highlights | V1: primary_category | W1: secondary_category | X1: tertiary_category | Y1: child_count | Z1: child_max_price | AA1: child_min_price | AC1: Rating_category
A2: P453279 | B2: Mini Intenso Smoothing Mask for Thick Hair | C2: 6159 | D2: Rossano Ferretti Parma | E2: 557 | F2: 3 | G2: 2 | H2: 1.7 oz/ 50 mL | I2: Size | J2: 1.7 oz/ 50 mL | M2: 18 | P2: 0 | Q2: 0 | R2: 1 | S2: 0 | T2: 0 | U2: ['Vegan', 'Hydrating', 'Clean at Sephora', 'Good for: Frizz', 'Good for: Dryness', 'Cruelty-Free'] | V2: Hair | W2: Hair Styling & Treatments | X2: Hair Masks | Y2: 0 | AC2: =IF(F2="","Not Rated", IF(F2>4,"High Rated","Low Rated")) -> Low Rated
A3: P501449 | B3: PEPTIDE PREP Clarifying Detox Shampoo | C3: 6472 | D3: K18 Biomimetic Hairscience | E3: 24418 | F3: 4.7944 | G3: 603 | H3: 8.5 oz / 250 mL | I3: Size | J3: 8.5 oz / 250 mL | L3: ['Water (Aqua) (Eau), Sodium C14-16 Olefin Sulfonate, Cocamidopropyl Hydroxysultaine, Salicylic Acid, Charcoal Powder, sh-Oligopeptide-78, Panthenol,', 'Glycerin, Sodium Phytate, Guar Hydroxypropyltrimonium Chloride, Caprylyl Glycol, Caprylhydroxamic Acid, Citric Acid, Potassium Hydroxide, Sodium Hydroxide, Fragrance (Parfum), Benzyl Salicylate, Limonene.'] | M3: 38 | P3: 0 | Q3: 0 | R3: 0 | S3: 0 | T3: 1 | U3: ['Vegan', 'Good for: Color Care', 'Clean at Sephora', 'All Hair Types', 'Salicylic Acid', 'Good for: Oily Scalp'] | V3: Hair | W3: Shampoo & Conditioner | X3: Shampoo | Y3: 1 | Z3: 14 | AA3: 14 | AC3: =IF(F3="","Not Rated", IF(F3>4,"High Rated","Low Rated")) -> High Rated
A4: P501526 | B4: Even Better All-Over Primer + Color Corrector | C4: 1254 | D4: CLINIQUE | E4: 2159 | F4: 3.8 | G4: 5 | H4: 0.2 oz / 6 mL | I4: Color | J4: Peach | K4: very fair to moderately fair complexions | L4: ['Water/Aqua/Eau, Methyl Trimethicone, Trimethylsiloxysilicate, Dimethicone, Butylene Glycol, Phenyl Trimethicone, Neopentyl Glycol Diheptanoate, Niacinamide, Hydroxyethyl Urea, Lauryl PEG-9 Polydimethylsiloxyethyl Dimethicone, Glycerin, Sodium Polyaspartate, Ascorbyl Glucoside, Phytosphingosine, Palmitoyl Hexapeptide-12, Sodium Hyaluronate, Resveratrol, Acetyl Hexapeptide-8, Caffeine, Magnesium Ascorbyl Phosphate, Tetrahexyldecyl Ascorbate, Polygonum Cuspidatum Root Extract, Tocopheryl Acetate, PEG-10 Dimethicone, Triethyl Citrate, Sigesbeckia Orientalis (St. Paul Wort) Extract, Micrococcus Lysate, Isopropyl Isostearate, PPG-15 Stearyl Ether, Salicylic Acid, Trihydroxystearin, Caprylyl Glycol, Sorbitol, Trehalose, Silica, Dimethicone/PEG-10/15 Crosspolymer, Xanthan Gum, Magnesium Aluminum Silicate, Lecithin, Triethoxycaprylylsilane, Zinc Stearate, Laureth-7, PEG-8, Ammonium Acryloyldimethyltaurate/VP Copolymer, Glyceryl Polymethacrylate, Alumina, Propylene Glycol Caprylate, Polysilicone-11, Disteardimonium Hectorite, Citric Acid, Hexylene Glycol, Dipropylene Glycol, Vinyl Dimethicone/Methicone Silsesquioxane Crosspolymer, Sodium Chloride, Sodium Hydroxide, BHT, Disodium EDTA, Sodium Citrate, Potassium Sorbate, Phenoxyethanol, [+/- Mica, Titanium Dioxide (CI 77891), Iron Oxides (CI 77491), Iron Oxides (CI 77492), Iron Oxides (CI 77499), Bismuth Oxychloride (CI 77163), Ultramarines (CI 77007), Chromium Oxide Greens (CI 77288)].'] | M4: 29 | P4: 0 | Q4: 0 | R4: 1 | S4: 0 | T4: 0 | U4: ['Natural Finish', 'Hyaluronic Acid', 'Vitamin C', 'Good for: Dark Circles', 'Long-wearing', 'Niacinamide'] | V4: Makeup | W4: Face | X4: Face Primer | Y4: 1 | Z4: 29 | AA4: 29 | AC4: =IF(F4="","Not Rated", IF(F4>4,"High Rated","Low Rated")) -> Low Rated
A5: P422093 | B5: Bloom Eau de Parfum For Her | C5: 1063 | D5: Gucci | E5: 69220 | F5: 4.1913 | G5: 1317 | H5: 1.6 oz/ 50 mL | I5: Size + Concentration + Formulation | J5: 1.6 oz/ 50 mL Eau de Parfum Spray | L5: ['Alcohol Denat., Fragrance, Water, Ethylhexyl Methoxycinnamate, Diethylamino Hydroxybenzoyl Hexyl Benzoate, Bht, Linalool, Benzyl Alcohol, Cinnamal, Hydroxycitronellal, Citronellol, Geraniol, Eugenol, Isoeugenol, Farnesol, Benzyl Benzoate, Hexyl Cinnamal, Citral.'] | M5: 123 | P5: 0 | Q5: 0 | R5: 0 | S5: 0 | T5: 0 | U5: ['Floral Scent', 'Layerable Scent'] | V5: Fragrance | W5: Women | X5: Perfume | Y5: 3 | Z5: 155 | AA5: 38 | AC5: =IF(F5="","Not Rated", IF(F5>4,"High Rated","Low Rated")) -> High Rated
A6: P9549 | B6: ALLURE Eau de Parfum | C6: 1065 | D6: CHANEL | E6: 7564 | F6: 4.3077 | G6: 26 | H6: 1.7 oz | I6: Size | J6: 1.7 oz | L6: ['Alcohol, Fragrance, Water, Linalool, Benzyl Salicylate, Limonene, Hexyl Cinnamal, Hydroxycitronellal, Citronellol, Geraniol, Alpha-Isomethyl Ionone, Coumarin, Citral, Benzyl Benzoate, Farnesol, Benzyl Alcohol, Amyl Cinnamal, Isoeugenol, Eugenol, Ethylhexyl Methoxycinnamate, Butyl Methoxydibenzoylmethane, Ethylhexyl Salicylate, Ci 14700 (Red 4), Ci 42090 (Blue 1), Ci 15985 (Yellow 6), Ci 19140 (Yellow 5), Il18-1.'] | M6: 122 | P6: 0 | Q6: 0 | R6: 0 | S6: 0 | T6: 0 | V6: Fragrance | W6: Women | X6: Perfume | Y6: 0 | AC6: =IF(F6="","Not Rated", IF(F6>4,"High Rated","Low Rated")) -> High Rated
A7: P408230 | B7: V-Facial Instant Depuffing Face Mask | C7: 2082 | D7: Clarins | E7: 26393 | F7: 4.7547 | G7: 159 | H7: 2.5 oz/ 74 mL | I7: Size | J7: 2.5 oz/ 74 mL | L7: ['Water, Glycerin, Kaolin, Alcohol, Cetearyl Ethylhexanoate, Cetearyl Alcohol, Betaine, Cetyl Alcohol, Polymethyl Methacrylate, Butylene Glycol, Caffeine, Glyceryl Stearate, Ci 77891/Titanium Dioxide, Gellan Gum, Dimethicone, Phenoxyisopropanol, Escin, Ethylhexylglycerin, Sodium Cetearyl Sulfate, Sodium Lauryl Sulfate, Sodium Acrylates Copolymer, Hydrogenated Polyisobutene, Disodium Edta, Zingiber Zerumbet Extract, Parfum/Fragrance, Phospholipids, Polyglyceryl-10 Stearate, Helianthus Annuus (Sunflower) Seed Oil, Tromethamine, Alumina, Ethylene Brassylate, Xylitol, Alchemilla Vulgaris Extract, Callicarpa Japonica Fruit Extract.'] | M7: 67 | P7: 0 | Q7: 0 | R7: 0 | S7: 0 | T7: 0 | U7: ['Good for: Dullness/Uneven Texture', 'Good for: Loss of firmness', 'Without Phthalates', 'Without Parabens', 'Best for Dry, Combo, Normal Skin'] | V7: Skincare | W7: Masks | X7: Face Masks | Y7: 0 | AC7: =IF(F7="","Not Rated", IF(F7>4,"High Rated","Low Rated")) -> High Rated
A8: P500716 | B8: 10 Day Results Kit | C8: 6018 | D8: Algenist | E8: 3206 | F8: 4.8023 | G8: 258 | L8: ['GENIUS Liquid Collagen:', 'Collagen (Vegan), Water (Aqua, Eau), Propanediol, Isononyl Isononanoate, Butylene Glycol, Glycerin, Betaine, Pentylene Glycol, Dextrin Palmitate, Collagen Amino Acids (Vegan), Parachlorella Beijerinckii Exopolysaccharides, Chlorella Protothecoides Oil, Helichrysum Stoechas Flower Extract, Cylindrotheca Fusiformis Extract, Niacinamide, Tocopherol, Palmitoyl Tripeptide-1, Palmitoyl Tetrapeptide-7, Adenosine, Helianthus Annuus (Sunflower) Seed Oil, Leuconostoc/Radish Root Ferment Filtrate, Caprylic/Capric Triglyceride, Palmitic Acid, Disodium EDTA, Carbomer, Sodium Lactate, Amodimethicone, Homosalate, Polysorbate 20, Butyl Methoxydibenzoylmethane, 1,2-Hexanediol, Caprylyl Glycol, Octocrylene, Sodium Hydroxide, Phenoxyethanol, Fragrance (Parfum), Limonene, Beta-Carotene (CI 40800).', 'Triple Algae Eye Renewal Balm with Multi-Peptide Complex:', 'Aqua (Water/Eau), Stearic Acid, Isopropyl Isostearate, Dimethicone, Glycerin, Pentylene', 'Glycol, Glyceryl Stearate SE, Cetearyl Alcohol, Butyrospermum Parkii (Shea) Butter, C12-15 Alkyl Benzoate, Limnanthes Alba (Meadowfoam) Seed Oil, Parachlorella Beijerinckii Exopolysaccharides, Corallina Officinalis Extract, Dunaliella Salina Extract, Undaria Pinnatifida Extract, Dipeptide-2, Palmitoyl Tetrapeptide-7, Palmitoyl Hexapeptide-12, Palmitoyl Tripeptide-5, Sodium Hyaluronate, Caffeine, Coffea Arabica (Coffee) Seed Oil, Tribehenin, Ceramide NG, PEG-10 Phytosterol, Tetrahexyldecyl Ascorbate, Aloe Barbadensis Leaf Juice, Tocopheryl Acetate, Bambusa Vulgaris Leaf/Stem Extract, Pisum Sativum (Pea)', 'Extract, Glucosamine HCl, Leuconostoc/Radish Root Ferment Filtrate, Camellia Sinensis Leaf Extract, Cucumis Sativus (Cucumber) Fruit Extract, Dimethicone Crosspolymer, Panthenol, Pantolactone, Caprylyl/Capryl Glucoside, Pfaffia Paniculata Root Extract, Ptychopetalum Olacoides Bark/Stem Extract, Lilium Candidum Flower Extract, Rubus Idaeus (Raspberry) Leaf Extract, Aloe Barbadensis Leaf Juice Powder, Vinyl Dimethicone/Methicone Silsesquioxane Crosspolymer, Phospholipids, Ceteareth-20, Acrylates/C10-30 Alkyl Acrylate Crosspolymer, Disodium EDTA, Aminomethyl Propanol, Caprylyl Glycol, Lactic Acid, Ethylhexylglycerin, Hexylene Glycol, Hesperidin Methyl Chalcone, Steareth-20, Citric Acid, Sodium Citrate, Chlorhexidine Digluconate, Phenoxyethanol, Potassium Sorbate, Benzyl Alcohol, Sodium Benzoate.', 'GENIUS Ultimate Anti-Aging Cream:', 'Water (Aqua, Eau), Caprylic/Capric Triglyceride, Hydrogenated Polyisobutene, Glycerin, Chlorella Protothecoides Oil, Dimethicone, Butylene Glycol, Glyceryl Stearate, PEG-100 Stearate, Butyrospermum Parkii (Shea) Butter, Pentylene Glycol, Potassium Cetyl Phosphate, Parachlorella Beijerinckii Exopolysaccharides, Collagen (Vegan), Ceramide NP, Cynara Scolymus (Artichoke) Leaf Extract, Retinyl Palmitate, Astragalus Membranaceus Root Extract, Atractylodes Macrocephala Root Extract, Iris Florentina Root Extract, Bupleurum Falcatum Root Extract, Copper Lysinate/Prolinate, Methylglucoside Phosphate, Stearalkonium Bentonite, Acrylates/C10-30 Alkyl Acrylate Crosspolymer, Silica, Caprylyl Glycol, Sodium Hydroxide, Disodium EDTA, Ethylhexylglycerin, Cetyl Alcohol, Propylene Carbonate, Quartz, Phenoxyethanol, Leuconostoc/Radish Root Ferment Filtrate, Chlorphenesin, Fragrance (Parfum), Coumarin.'] | M8: 88 | N8: 142 | P8: 0 | Q8: 0 | R8: 0 | S8: 0 | T8: 1 | U8: ['Vegan', 'Good for: Loss of firmness', 'Good for: Dark Circles', 'Collagen', 'Hydrating', 'Good for: Anti-Aging'] | V8: Skincare | W8: Value & Gift Sets | Y8: 0 | AC8: =IF(F8="","Not Rated", IF(F8>4,"High Rated","Low Rated")) -> High Rated
A9: P502274 | B9: Paper- Personal | C9: 7095 | D9: Commodity | E9: 664 | F9: 3.5455 | G9: 11 | H9: 3.4 oz / 100 mL | I9: Size + Concentration + Formulation | J9: 3.4 oz / 100 mL perfume spray | L9: ['SD Alcohol 40-B (Alcohol Denat.), Parfum/Fragrance, Aqua/Water/Eau.'] | M9: 135 | P9: 0 | Q9: 0 | R9: 0 | S9: 0 | T9: 1 | U9: ['Vegan', 'Unisex/ Genderless Scent', 'Clean at Sephora', 'Cruelty-Free'] | V9: Fragrance | W9: Women | X9: Perfume | Y9: 1 | Z9: 25 | AA9: 25 | AC9: =IF(F9="","Not Rated", IF(F9>4,"High Rated","Low Rated")) -> Low Rated
A10: P462706 | B10: Epic Curl Vegan Lash Primer | C10: 5905 | D10: KVD Beauty | E10: 2352 | F10: 2.9355 | G10: 31 | L10: ['Aqua/Water/Eau, Hydrogenated Olive Oil Stearyl Esters, Bambusa Arundinacea Stem Extract, Cera, Carnauba/Copernicia, Cerifera (Carnauba) Wax/Cire De Carnauba, Oryza Sativa Cera/Oryza Sativa (Rice) Bran Wax, Glyceryl Stearate, Helianthus Annuus Seed Cera/Helianthus Annuus (Sunflower) Seed Wax, Bis-Diglyceryl Polyacyladipate-2, Acacia Senegal Gum, Stearic Acid, Propanediol, Palmitic Acid, Aminomethyl Propanol, Hydrolyzed Jojoba Esters, Phenoxyethanol, Sodium Dehydroacetate, Galactoarabinan, Jojoba Esters, Xanthan Gum, Ethylhexylglycerin, Talc, Kaolin, Tocopherol, Ultramarines (Ci 77007), Iron Oxides (Ci 77499), Ferric Ammonium Ferrocianide (Ci 77510).'] | M10: 24 | P10: 0 | Q10: 0 | R10: 0 | S10: 0 | T10: 0 | U10: ['Vegan', 'Liquid Formula', 'Curling'] | V10: Makeup | W10: Eye | X10: Mascara | Y10: 0 | AC10: =IF(F10="","Not Rated", IF(F10>4,"High Rated","Low Rated")) -> Low Rated
A11: P376726 | B11: Maracuja Oil | C11: 5648 | D11: tarte | E11: 79986 | F11: 4.396 | G11: 2419 | H11: 1.7 oz/ 50 mL | I11: Size | J11: 1.7 oz/ 50 mL | L11: ['Passiflora Edulis Seed Oil, Citrus Paradisi (Grapefruit) Peel Oil, Limonene, Tocopherol, Oryza Sativa (Rice) Bran Extract, Helianthus Annuus (Sunflower) Extract, Rosmarinus Officinalis (Rosemary) Leaf Extract, Citral, Linalool.'] | M11: 48 | P11: 0 | Q11: 0 | R11: 0 | S11: 0 | T11: 0 | V11: Skincare | W11: Moisturizers | X11: Face Oils | Y11: 1 | Z11: 16 | AA11: 16 | AC11: =IF(F11="","Not Rated", IF(F11>4,"High Rated","Low Rated")) -> High Rated
A12: P504146 | B12: Sunday Scalp Reset Foam Pre Shampoo | C12: 5995 | D12: Bumble and bumble | E12: 292 | F12: 4.766 | G12: 47 | H12: 3.5 oz / 150 mL | I12: Size | J12: 3.5 oz / 150 mL | L12: ['Butane, Water/Aqua/Eau, Alcohol Denat., Isobutane, Glycerin, Butylene Glycol, Dimethicone, Fragrance (Parfum), Caprylic/Capric Triglyceride, PPG-8-Ceteth-20, Salicylic Acid, Caffeine, Epilobium Angustifolium Flower/Leaf/Stem Extract, Sodium Lauroamphoacetate, Panthenol, Tocopheryl Acetate, Punica Granatum (Pomegranate) Extract, Honey Extract/Mel/Extrait De Miel, Leuconostoc/Radish Root Ferment Filtrate, Wheat Amino Acids, Aloe Barbadensis Leaf Juice, Gellidiella Acerosa Extract, Hypnea Musciformis (Algae) Extract, Sargassum Filipendula (Algae) Extract, Citrus Tangerina (Tangerine), Zingiber Officinale (Ginger) Root Extract, Rice Amino Acids, Glyceryl Polyacrylate, Hydroxyethylcellulose, Biotin, Cellulose, Cocamide Mipa, Sodium Lauroyl Methyl Isethionate, Citric Acid, Linalool, Benzyl Salicylate, Citronellol, Limonene, Alpha-Isomethyl Ionone, Phenoxyethanol, Sodium Benzoate.'] | M12: 34 | P12: 0 | Q12: 0 | R12: 0 | S12: 0 | T12: 1 | U12: ['Good for: Color Care', 'Salicylic Acid', 'Without Sulfates SLS & SLES', 'Good for: Oily Scalp', 'Cruelty-Free'] | V12: Hair | W12: Hair Styling & Treatments | X12: Scalp Treatments | Y12: 0 | AC12: =IF(F12="","Not Rated", IF(F12>4,"High Rated","Low Rated")) -> High Rated
A13: P462356 | B13: Mini Honey Infused Hair Perfume | C13: 6328 | D13: Gisou | E13: 70086 | F13: 4.0824 | G13: 425 | H13: 1.7 oz/ 50 mL | I13: Size | J13: 1.7 oz/ 50 mL | L13: ['Alcohol Denat., Parfum (Fragrance), Aqua (Water, Eau), Mel (Honey, Miel)*, Argania Spinosa Kernel Oil, Sodium Benzotriazolyl Butylphenol Sulfonate, Tris(Tetramethylhydroxypiperidinol) Citrate, Citral**, Coumarin**, Linalool**, Hexyl Cinnamal**, Limonene**, CI 19140 (Yellow 5), CI 14700 (Red 4).'] | M13: 44 | P13: 0 | Q13: 0 | R13: 0 | S13: 0 | T13: 0 | U13: ['Layerable Scent', 'Fresh Scent', 'Clean at Sephora', 'All Hair Types', 'Good for: Frizz'] | V13: Hair | W13: Hair Styling & Treatments | X13: Hair Styling Products | Y13: 0 | AC13: =IF(F13="","Not Rated", IF(F13>4,"High Rated","Low Rated")) -> High Rated
A14: P462386 | B14: Drying Cream | C14: 8017 | D14: Mario Badescu | E14: 1635 | F14: 3.75 | G14: 4 | H14: 0.5 oz/ 14 g | I14: Size | J14: 0.5 oz/ 14 g | L14: ['Aqua (Water, Eau), Zinc Oxide, Cetyl Alcohol, Aloe Barbadensis Leaf Juice, Cera Alba (Beeswax, Cire dÂ´abeille), Polysorbate 80, Glycerin, Ethylhexyl Palmitate, Propylene Glycol, Sulfur, Oleth-10, Paraffinum Liquidum (Mineral Oil, Huile MinÃ©rale), Ichthammol, Hydrolyzed Yeast Protein, Triticum Vulgare (Wheat) Starch, Arctium Lappa Root Extract, Cysteine, Niacinamide, Panthenol, Nasturtium Officinale Flower/Leaf Extract, Citrus Limon (Lemon) Fruit Extract, Allantoin, Biotin, Arginine, Leucine, Lysine, Tyrosine, Valine, Glutamic Acid, Cellulose Gum, Polysorbate 20, Maltodextrin, Zinc Chloride, Glyceryl Acrylate/Acrylic Acid Copolymer, Pyridoxine HCl, Parfum (Fragrance), Sodium Chloride, Methylparaben, Propylparaben, Potassium Sorbate, Citric Acid, Sodium Benzoate, Chlorphenesin, Disodium EDTA, Phenoxyethanol, Benzyl Benzoate, Alpha-Isomethyl Ionone, Limonene, Linalool, CI 77891 (Titanium Dioxide).'] | M14: 17 | P14: 0 | Q14: 0 | R14: 1 | S14: 0 | T14: 0 | V14: Skincare | W14: Treatments | X14: Blemish & Acne Treatments | Y14: 0 | AC14: =IF(F14="","Not Rated", IF(F14>4,"High Rated","Low Rated")) -> Low Rated
A15: P437657 | B15: Scalp Care Dry Scalp Treatment | C15: 5936 | D15: Living Proof | E15: 33713 | F15: 4.301 | G15: 309 | H15: 3.4 oz/ 100 mL | I15: Size | J15: 3.4 oz/ 100 mL | L15: ['Water/Eau/Aqua, Glycerin, Niacinamide, Sodium Hyaluronate, Trehalose, Urea, Serine, Algin, Pentylene Glycol, Pullulan, Lecithin, Glyceryl Polyacrylate, C13-15 Alkane, Caprylyl Glycol, Disodium Phosphate, Potassium Phosphate, Hydroxyethyl Acrylate/Sodium Acryloyldimethyl Taurate Copolymer, Hydroxyacetophenone, Caesalpinia Spinosa Gum, Sclerotium Gum, Xanthan Gum, Isohexadecane, Ethylhexylglycerin, Polysorbate 60, Fragrance/Parfum.'] | M15: 37 | P15: 0 | Q15: 0 | R15: 0 | S15: 0 | T15: 0 | U15: ['Vegan', 'All Hair Types', 'Without Parabens', 'Without Silicones', 'Without Sulfates SLS & SLES', 'Good for: Flaky/Dry Scalp'] | V15: Hair | W15: Hair Styling & Treatments | X15: Scalp Treatments | Y15: 0 | AC15: =IF(F15="","Not Rated", IF(F15>4,"High Rated","Low Rated")) -> High Rated
A16: P457245 | B16: Rose Perfecto Tinted Liquid Balm | C16: 1133 | D16: Givenchy | E16: 62416 | F16: 4.3079 | G16: 367 | H16: .2 oz/ 6mL | I16: Color | J16: 001 Pink Irresistible | K16: transparent pink, custom to your PH | L16: ['C10-30 Cholesterol/Lanosterol Esters, Isononyl Isononanoate, Polyglyceryl-2 Triisostearate, Hydrogenated Polyisobutene, Pentaerythrityl Tetraisostearate, Copernicia Cerifera (Carnauba) Wax, Ethylene/Propylene/Styrene Copolymer, Glyceryl Behenate/Eicosadioate, Ethylhexyl Palmitate, Butyrospermum Parkii (Shea) Butter, Butyrospermum Parkii (Shea) Butter Unsaponifiables, Menthoxypropanediol, Parfum (Fragrance), Butylene/Ethylene/Styrene Copolymer, Diisostearyl Malate, Ascorbyl Tetraisopalmitate, Trimethylolpropane Triisostearate, Pentaerythrityl Tetra-Di-T-Butyl Hydroxyhydrocinnamate, Trihydroxystearin, Schinus Terebinthifolius Seed Extract, Tocopherol, Sodium Hyaluronate, Propyl Gallate, [+/- Ci 77499 (Iron Oxides), Ci 77891 (Titanium Dioxide), Ci 45410 (Red 27), Ci 15850 (Red 6 - Red 7)].'] | M16: 38 | P16: 0 | Q16: 0 | R16: 0 | S16: 0 | T16: 0 | U16: ['Radiant Finish', 'Hyaluronic Acid', 'Liquid Formula', 'Plumping', 'Vitamin C', 'Hydrating'] | V16: Makeup | W16: Lip | X16: Lip Balm & Treatment | Y16: 5 | Z16: 38 | AA16: 38 | AC16: =IF(F16="","Not Rated", IF(F16>4,"High Rated","Low Rated")) -> High Rated
A17: P505364 | B17: Afterglow Sensual Shine Hydrating Lipstick | C17: 3976 | D17: NARS | E17: 688 | H17: .05 oz / 1.5 g | I17: Color | J17: ORGASM | L17: ['Tridecyl Trimellitate, Hydrogenated Polyisobutene, Phenylpropyldimethylsiloxysilicate, Synthetic Wax, Mica, Ricinus Communis (Castor) Seed Oil, Hydrogenated Vegetable Oil, Polyethylene, Diisostearyl Malate, Diglyceryl Sebacate/Isopalmitate, Dimethicone, Dicalcium Phosphate, Phytosteryl/Isostearyl/Cetyl/Stearyl/Behenyl Dimer Dilinoleate, Gardenia Taitensis Flower Extract, Moringa Oleifera Seed Extract, Polyhydroxystearic Acid, Isopropyl Myristate, Isostearic Acid, Ethylhexyl Palmitate, Lecithin, Polyglyceryl-3 Polyricinoleate, Triethoxycaprylylsilane, Polysilicone-11, Butyrospermum Parkii (Shea) Butter, Ethylene/Propylene Copolymer, Pentaerythrityl Tetra-Di-T-Butyl Hydroxyhydrocinnamate, Tocopherol, Water/Aqua/Eau, Collagen, Leuconostoc/Radish Root Ferment Filtrate, Hydrogenated Coco-Glycerides, Sodium Hyaluronate, Hydrogenated Castor Oil, Tocopheryl Acetate, Cocos Nucifera (Coconut) Oil, Simmondsia Chinensis (Jojoba) Seed Oil, Mangifera Indica (Mango) Seed Butter, Olea Europaea (Olive) Fruit Oil, Caprylyl Glycol, Glyceryl Caprylate, Glycerin, [+/-(May Contain/Peut Contenir): Iron Oxides (Ci 77491, Ci 77492, Ci 77499), Red 7 Lake (Ci 15850), Titanium Dioxide (Ci 77891), Yellow 5 Lake (Ci 19140)].'] | M17: 32 | P17: 0 | Q17: 1 | R17: 0 | S17: 1 | T17: 0 | U17: ['Stick Formula', 'High Shine Finish', 'Hydrating', 'Oil Free', 'Without Parabens'] | V17: Makeup | W17: Lip | X17: Lipstick | Y17: 9 | Z17: 32 | AA17: 32 | AC17: =IF(F17="","Not Rated", IF(F17>4,"High Rated","Low Rated")) -> Not Rated
A18: P417107 | B18: The Moisturizing Soft Lotion | C18: 6201 | D18: La Mer | E18: 4580 | F18: 4.0704 | G18: 71 | H18: 1.7 oz/ 50 mL | I18: Size | J18: 1.7 oz/ 50 mL | L18: ['Algae (Seaweed) Extract, Petrolatum, Isocetyl Stearoyl Stearate, Butyrospermum Parkii (Shea Butter), Butylene Glycol, Cyclopentasiloxane, Dimethicone, Glyceryl Stearate, Cetyl Esters, Phenyl Trimethicone, Diethylhexyl Succinate, Cyclohexasiloxane, Cholesterol, Steareth-10, Glyceryl Stearate Se, Polysilicone-11, Sesamum Indicum (Sesame) Seed Oil, Medicago Sativa (Alfalfa) Seed Powder, Helianthus Annuus (Sunflower) Seedcake, Prunus Amygdalus Dulcis (Sweet Almond) Seed Meal, Eucalyptus Globulus (Eucalyptus) Leaf Oil, Sodium Gluconate, Copper Gluconate, Calcium Gluconate, Magnesium Gluconate, Zinc Gluconate, Tocopheryl Succinate, Niacin, Sesamum Indicum (Sesame) Seed Powder, Water\\Aqua\\Eau, Salicornia Herbacea Extract, Sigesbeckia Orientalis (St. Paul Wort) Extract, Citrus Aurantifolia (Lime) Peel Extract, Sea Salt\\Maris Sal\\Sel Marin, Chlorella Vulgaris Extract, Hydrolyzed Rice Extract, Micrococcus Lysate, Laminaria Digitata Extract, Plankton Extract, Caffeine, Glucose Oxidase, Trehalose, Sucrose, Acetyl Hexapeptide-8, Lactoperoxidase, Hydrolyzed Algin, Glyceryl Dilaurate, Alcaligenes Polysaccharides, Isohexadecane, Caprylic/Capric Triglyceride, Dipalmitoyl Hydroxyproline, Distearyldimonium Chloride, Glycerin, Tocopheryl Acetate, Steareth-21, Polyquaternium-51, Saccharide Isomerate, Tetrahexyldecyl Ascorbate, Sodium Pca, Urea, Glucose, Polysorbate 80, Sodium Hyaluronate, Cetyl Alcohol, Alcohol Denat., Acrylamide/Sodium Acryloyldimethyltaurate Copolymer, Fragrance (Parfum), Lecithin, BHT, Linalool, Citronellol, Hydroxycitronellal, Geraniol, Limonene, Benzyl Salicylate, Phenoxyethanol.'] | M18: 320 | P18: 0 | Q18: 0 | R18: 0 | S18: 0 | T18: 0 | U18: ['Best for Combination Skin', 'Good for: Pores', 'Without Sulfates SLS & SLES', 'Without Parabens', 'Without Phthalates'] | V18: Skincare | W18: Moisturizers | X18: Moisturizers | Y18: 0 | AC18: =IF(F18="","Not Rated", IF(F18>4,"High Rated","Low Rated")) -> High Rated
A19: P467973 | B19: Intensive Eye Renewal Cream with Firming Peptides | C19: 6314 | D19: Shani Darden Skin Care | E19: 12224 | F19: 4.2087 | G19: 254 | H19: 0.5 oz/ 15 mL | I19: Size | J19: 0.5 oz/ 15 mL | L19: ['Water (Aqua), Caprylic/Capric Triglyceride, Diheptyl Succinate, Capryloyl Glycerin/Sebacic Acid Copolymer, Butyrospermum Parkii (Shea Butter), Albizia Julibrissin Bark Extract, Darutoside, Cetearyl Alcohol, Pentylene Glycol, Glycerin, Niacinamide, Castanea Sativa (Chestnut) Seed Extract, Sorbitan Stearate, Glyceryl Stearate, PEG-100 Stearate, Hydroxyethyl Acrylate/Sodium Acryloyldimethyl Taurate Copolymer, Hydrolyzed Pea Protein, Lecithin, Olea Europaea (Olive) Fruit Oil, Phytosterols, Squalane, Ceramide NP, Propanediol, Physalis Angulata Extract, Tocopheryl (Vitamin E) Acetate, Cucumis Sativus (Cucumber) Fruit Extract, Tetrasodium Glutamate Diacetate, Phenoxyethanol, Ethylhexylglycerin, Chlorphenesin.'] | M19: 68 | P19: 0 | Q19: 0 | R19: 0 | S19: 0 | T19: 1 | V19: Skincare | W19: Eye Care | X19: Eye Creams & Treatments | Y19: 0 | AC19: =IF(F19="","Not Rated", IF(F19>4,"High Rated","Low Rated")) -> High Rated
A20: P454967 | B20: Amalfi Lemon & Mint Reed Diffuser | C20: 7025 | D20: NEST New York | E20: 1829 | F20: 4.4444 | G20: 9 | H20: 5.9 oz/ 175 mL | I20: Size + Concentration + Formulation | J20: 5.9 oz/ 175 mL diffuser | M20: 58 | P20: 0 | Q20: 0 | R20: 0 | S20: 0 | T20: 0 | V20: Fragrance | W20: Candles & Home Scents | X20: Diffusers | Y20: 0 | AC20: =IF(F20="","Not Rated", IF(F20>4,"High Rated","Low Rated")) -> High Rated
A21: P504363 | B21: Lip Snatcher Hydrating Liquid Lipstick and Lip Gloss Duo | C21: 6326 | D21: ONE/SIZE by Patrick Starrr | E21: 18228 | F21: 4.297 | G21: 165 | H21: .24 oz / 7 mL | I21: Color | J21: Joelapuss | K21: pearlescent & matte medium pink | L21: ['CrÃ©me:', 'Isododecane, Octyldodecanol, Dicalcium Phosphate, Silica, Hydrogenated Styrene/Isoprene Copolymer, Synthetic Fluorphlogopite, Trimethylsiloxysilicate, Disteardimonium Hectorite, Ethyl Vanillin, Tocopheryl Acetate, Gossypium Herbaceum (Cotton) Seed Oil, Helianthus Annuus (Sunflower) Seed Oil, Pentaerythrityl Tetra-Di-T-Butyl Hydroxyhydrocinnamate, Ricinus Communis (Castor) Seed Oil, Hydrolyzed Sodium Hyaluronate, Sodium Hyaluronate, Hydrogenated Castor Oil, Lupinus Albus Seed Extract, Tocopherol. May Contain/Peut Contenir (Â±): Red 7 Lake (CI 15850), Titanium Dioxide (CI 77891), Red 28 Lake (CI 45410), Yellow 6 Lake (CI 15985), Iron Oxides (CI 77491, CI 77492), Blue 1 Lake (CI 42090).', 'Gloss:', 'Polybutene, Octyldodecanol, Hydrogenated Polyisobutene, Silica Dimethyl Silylate, Calcium Sodium Borosilicate, VP/Hexadecene Copolymer, Hydrogenated Styrene/Isoprene Copolymer, Caprylic/Capric Triglyceride, Ethyl Vanillin, Tocopheryl Acetate, Synthetic Fluorphlogopite, Pentaerythrityl Tetra-Di-T-Butyl Hydroxyhydrocinnamate, Dicalcium Phosphate, Tin Oxide, Helianthus Annuus (Sunflower) Seed Oil, Ricinus Communis (Castor) Seed Oil, Hydrolyzed Sodium Hyaluronate, Sodium Hyaluronate, Hydrogenated Castor Oil, Lupinus Albus Seed Extract, Jasminum Officinale (Jasmine) Flower Extract, Tocopherol. May Contain/Peut Contenir (Â±): Titanium Dioxide (CI 77891), Iron Oxides (CI 77491, CI 77492), Red 7 Lake (CI 15850), Yellow 5 (CI 19140), Blue 1 Lake (CI 42090).'] | M21: 28 | P21: 0 | Q21: 1 | R21: 0 | S21: 0 | T21: 1 | U21: ['Vegan', 'Liquid Formula', 'Hydrating', 'Long-wearing', 'Cruelty-Free'] | V21: Makeup | W21: Lip | X21: Lipstick | Y21: 7 | Z21: 28 | AA21: 28 | AC21: =IF(F21="","Not Rated", IF(F21>4,"High Rated","Low Rated")) -> High Rated
A22: P484044 | B22: The Body Duo Mini Body Scrub + Moisturizer Essentials | C22: 6352 | D22: Fenty Skin | E22: 10700 | F22: 4.2 | G22: 5 | L22: ['Buff Ryder Mini Exfoliating Body Scrub:', 'Sucrose, Glycine Soja (Soybean) Oil, Helianthus Annuus Hybrid Oil (Helianthus Annuus (Sunflower) Seed Oil), Sea Salt/Maris Sal/Sel Marin, Cocos Nucifera (Coconut) Oil, Butyrospermum Parkii (Shea) Butter, Polyglyceryl-3 Caprate, Silica, Helianthus Annuus (Sunflower) Seed Oil, Caprylic/Capric Triglyceride, Trihydroxystearin, Styrene/Butadiene Copolymer, Persea Gratissima (Avocado) Fruit Powder, Lactobacillus/Punica Granatum Fruit Ferment Extract, Papain, Bromelain, Quartz, Tocopherol, Citric Acid, Pumice, Caprylyl Glycol, Maltodextrin, Phenoxyethanol, Pentaerythrityl Tetra-Di-T-Butyl Hydroxyhydrocinnamate, Parfum/Fragrance, Hydroxycitronellal, Limonene.', 'Butta Drop Mini Whipped Oil Body Cream:', 'Aqua/Water/Eau, Cocos Nucifera (Coconut) Oil, Glycerin, Caprylic/Capric Triglyceride, Oryza Sativa (Rice) Bran Oil, Propanediol, Cetearyl Alcohol, Cetyl Ethylhexanoate, Dimethicone, Butyrospermum Parkii (Shea) Butter, Mangifera Indica (Mango) Seed Butter, Cetearyl Olivate, Diisostearyl Malate, Polyglyceryl-3 Methylglucose Distearate, Citrullus Lanatus (Watermelon) Seed Oil, Hibiscus Sabdariffa Seed Oil, Adansonia Digitata Seed Oil, Malpighia Punicifolia (Acerola) Fruit Extract, Adansonia Digitata Fruit Extract, Helianthus Annuus (Sunflower) Seed Oil, Simmondsia Chinensis (Jojoba) Seed Oil, Plumeria Acutifolia Flower Extract, Aloe Barbadensis Leaf Juice, Sodium Hyaluronate, Glycine Soja (Soybean) Oil, Tocopheryl Acetate, Tocopherol, Sorbitan Olivate, Polysorbate 60, Potassium Cetyl Phosphate, Acrylates/C10-30 Alkyl Acrylate Crosspolymer, Ethylhexylglycerin, Ethyl Hexanediol, Butylene Glycol, Caprylyl Glycol, Tromethamine, Phenoxyethanol, Parfum/Fragrance, Benzyl Salicylate, Hexyl Cinnamal, Limonene, Linalool.'] | M22: 32 | O22: 24 | P22: 1 | Q22: 0 | R22: 1 | S22: 0 | T22: 1 | U22: ['Vegan', 'Good for: Dullness/Uneven Texture', 'Hydrating', 'Clean at Sephora', 'Good for: Dryness'] | V22: Bath & Body | W22: Value & Gift Sets | Y22: 0 | AC22: =IF(F22="","Not Rated", IF(F22>4,"High Rated","Low Rated")) -> High Rated
A23: P502044 | B23: Mini Sparkling Cuvee Glass Jar Candle | C23: 6245 | D23: VOLUSPA | E23: 1158 | F23: 4.1667 | G23: 6 | H23: 5.5 oz / 156 g | I23: Size + Concentration + Formulation | J23: 5.5 oz / 156 g | M23: 20 | P23: 0 | Q23: 0 | R23: 0 | S23: 0 | T23: 0 | U23: ['Vegan', 'Without Phthalates', 'Without Parabens', 'Without Sulfates SLS & SLES', 'Cruelty-Free'] | V23: Fragrance | W23: Candles & Home Scents | X23: Candles | Y23: 0 | AC23: =IF(F23="","Not Rated", IF(F23>4,"High Rated","Low Rated")) -> High Rated
A24: P472340 | B24: Tea Tree Essential Oil | C24: 8020 | D24: SUNDAY II SUNDAY | E24: 2734 | F24: 4.25 | G24: 4 | H24: 1 oz/ 30 mL | I24: Size | J24: 1 oz/ 30 mL | L24: ['100% Pure Tea Tree Oil.'] | M24: 15 | P24: 0 | Q24: 0 | R24: 1 | S24: 0 | T24: 0 | U24: ['Vegan', 'All Hair Types', 'Good for: Frizz', 'Good for: Dryness', 'Without Parabens'] | V24: Hair | W24: Hair Styling & Treatments | X24: Hair Oil | Y24: 0 | AC24: =IF(F24="","Not Rated", IF(F24>4,"High Rated","Low Rated")) -> High Rated
A25: P434452 | B25: VIP Strong Hold Texturizing Hair Spray | C25: 6259 | D25: KÃ©rastase | E25: 5128 | F25: 3.8519 | G25: 27 | H25: 6.8 oz/ 193 g | I25: Size | J25: 6.8 oz/ 193 g | L25: ['Hydrofluorocarbon 152a, Alcohol Denat, Butane, Calcium Carbonate, Polyvinylcaprolactam, Disteardimonium Hectorite, Dimethicone, Fragrance, Dimethiconol, Benzyl Salicylate, Limonene, Benzyl Alcohol, Linalool, Citronellol, Geraniol, Hexyl Cinnamal, Hydroxycitronellal, Alpha-Isomethyl Ionone.'] | M25: 32 | P25: 0 | Q25: 0 | R25: 0 | S25: 1 | T25: 1 | U25: ['Good for: Volume', 'All Hair Types', 'Good for: Frizz'] | V25: Hair | W25: Hair Styling & Treatments | X25: Hair Spray | Y25: 0 | AC25: =IF(F25="","Not Rated", IF(F25>4,"High Rated","Low Rated")) -> Low Rated
A26: P468829 | B26: Blond Absolu Strengthening Hair Oil for Very Damaged Blonde Hair | C26: 6259 | D26: KÃ©rastase | E26: 14239 | F26: 4.6159 | G26: 328 | H26: 3.4 oz/ 100 mL | I26: Size | J26: 3.4 oz/ 100 mL | L26: ['Cyclopentasiloxane, Dimethiconol, Parfum / Fragrance, Limonene, Helianthus Annuus Seed Oil / Sunflower Seed Oil, Linalool, Citronellol, Tocopherol, Leontopodium Alpinum Flower/Leaf Extract.'] | M26: 54 | P26: 0 | Q26: 0 | R26: 0 | S26: 0 | T26: 1 | U26: ['Good for: Damage', 'Floral Scent', 'All Hair Types', 'Good for: Dryness', 'Prevents Color Fading', 'Increases Shine'] | V26: Hair | W26: Hair Styling & Treatments | X26: Hair Oil | Y26: 1 | Z26: 26 | AA26: 26 | AC26: =IF(F26="","Not Rated", IF(F26>4,"High Rated","Low Rated")) -> High Rated
A27: P504785 | B27: Luxe Body Serum | C27: 5626 | D27: St. Tropez | E27: 1791 | F27: 4.8173 | G27: 892 | H27: 6.7 oz / 200 mL | I27: Size | J27: 6.7 oz / 200 mL | L27: ['Aqua (Water), Dihydroxyacetone, Butylene Glycol, Polysorbate 20, Trehalose, Phenoxyethanol, Hydroxyethylcellulose, Saccharide Isomerate, Panthenol, Sodium Metabisulfite, Parfum (Fragrance), Maltodextrin, Caramel, Citric Acid, Ethylhexylglycerin, Sodium Hyaluronate, Biosaccharide Gum-1, Linalool, Benzyl Salicylate, Niacinamide, Sodium Citrate, Coumarin, Limonene, Hexyl Cinnamal, Hydroxycitronellal, Geraniol, Alpha-Isomethyl Ionone, Sodium Hydroxide.'] | M27: 48 | P27: 0 | Q27: 1 | R27: 0 | S27: 0 | T27: 0 | U27: ['Vegan', 'Collagen', 'Hydrating', 'Niacinamide'] | V27: Bath & Body | W27: Body Moisturizers | X27: Body Lotions & Body Oils | Y27: 0 | AC27: =IF(F27="","Not Rated", IF(F27>4,"High Rated","Low Rated")) -> High Rated
A28: P479852 | B28: Melrose Place Moisturizing Body Cream | C28: 6144 | D28: OUAI | E28: 22152 | F28: 4.7096 | G28: 365 | H28: 7.5 oz/ 212 g | I28: Size | J28: 7.5 oz/ 212 g | L28: ['Aqua (Water, Eau), Caprylic/Capric Triglyceride, Phenyl Trimethicone, Cetyl Alcohol, Isododecane, Methyl Glucose Sesquistearate, Glycerin, Hydroxyethyl Acrylate/ Sodium Acryloyldimethyl Taurate Copolymer, Cocos Nucifera (Coconut) Oil, Sodium Stearoyl Glutamate, Glyceryl Stearate Citrate, Cetearyl Alcohol, Butyrospermum Parkii (Shea) Butter, Theobroma Grandiflorum Seed Butter, Lactobacillus Ferment, Squalane, Xanthan Gum, Citric Acid, Polysorbate 60, Ethylhexylglycerin, Glyceryl Caprylate, Tocopherol, Sodium Phytate, Sorbitan Isostearate, Benzophenone-4, Sodium Chloride, Alcohol, Phenoxyethanol, Parfum (Fragrance), Citronellol, Geraniol, Benzyl Salicylate, Linalool, Ci 14700 (Red 4), Ci 15985 (Yellow 6).'] | M28: 38 | P28: 0 | Q28: 0 | R28: 0 | S28: 0 | T28: 0 | U28: ['Cruelty-Free', 'Floral Scent', 'Hydrating', 'Good for: Dryness', 'Without Sulfates SLS & SLES'] | V28: Bath & Body | W28: Body Moisturizers | X28: Body Lotions & Body Oils | Y28: 0 | AC28: =IF(F28="","Not Rated", IF(F28>4,"High Rated","Low Rated")) -> High Rated
A29: P503100 | B29: Soleil Neige Eye Color Quad | C29: 5869 | D29: TOM FORD | E29: 4436 | F29: 2.5 | G29: 4 | H29: 0.35 oz / 9.9 g | I29: Color | J29: Chalet Lust - rose golds and copper tones | L29: ['Mica, Cetearyl Ethylhexanoate, C12-20 Acid Peg-8 Ester, Hdi/Trimethylol Hexyllactone Crosspolymer, Squalane, Glycerin, Chondrus Crispus (Carrageenan), Ethylhexylglycerin, Dicalcium Phosphate, Silica, Aluminum Calcium Sodium Silicate, Synthetic Fluorphlogopite, Polysorbate 80, Tin Oxide, Caprylyl Glycol, 1,2-Hexanediol, [+/- Titanium Dioxide (Ci 77891), Iron Oxides (Ci 77491), Iron Oxides (Ci 77492), Iron Oxides (Ci 77499), Aluminum Powder (Ci 77000), Bismuth Oxychloride (Ci 77163), Blue 1 Lake (Ci 42090), Bronze Powder (Ci 77400), Carmine (Ci 75470), Chromium Hydroxide Green (Ci 77289), Chromium Oxide Greens (Ci 77288), Copper Powder (Ci 77400), Ferric Ammonium Ferrocyanide (Ci 77510), Ferric Ferrocyanide (Ci 77510), Manganese Violet (Ci 77742), Ultramarines (Ci 77007), Yellow 5 Lake (Ci 19140)].'] | M29: 90 | P29: 0 | Q29: 0 | R29: 0 | S29: 0 | T29: 0 | U29: ['Pressed Powder Formula', 'Shimmer Finish', 'Without Mineral Oil', 'Without Phthalates', 'Without Parabens', 'Without Triclosan'] | V29: Makeup | W29: Eye | X29: Eye Palettes | Y29: 1 | Z29: 90 | AA29: 90 | AC29: =IF(F29="","Not Rated", IF(F29>4,"High Rated","Low Rated")) -> Low Rated
A30: P479342 | B30: Soft Pinch Blush Brush | C30: 6317 | D30: Rare Beauty by Selena Gomez | E30: 69220 | F30: 4.7143 | G30: 49 | M30: 23 | P30: 0 | Q30: 0 | R30: 0 | S30: 0 | T30: 1 | U30: ['Vegan', 'Cruelty-Free'] | V30: Makeup | W30: Brushes & Applicators | X30: Face Brushes | Y30: 0 | AC30: =IF(F30="","Not Rated", IF(F30>4,"High Rated","Low Rated")) -> High Rated
A31: P434500 | B31: Good Girl Rollerball | C31: 3155 | D31: Carolina Herrera | E31: 34288 | F31: 4.4665 | G31: 671 | H31: 0.30 oz/ 10 mL | I31: Size + Concentration + Formulation | J31: 0.30 oz/ 10 mL eau de parfum spray | L31: ['Alcohol Denat., Fragrance, Water, Linalool, Hydroxycitronellal, Benzyl Salicylate, Coumarin, Ethylhexyl Methoxycinnamate, Benzyl Benzoate, Ethylhexyl Saliclate, Butyl Methoxydibenzoylmethane, Limonen, Geraniol, Citronellol, Isoeugenol, Hexyl Cinnamal, Benzyl Alcohol, Citral, Ci 60730 (Ext. Violet 2) Alcohol Of Vegatal Origin 80%.'] | M31: 32 | P31: 0 | Q31: 0 | R31: 0 | S31: 0 | T31: 0 | V31: Fragrance | W31: Women | X31: Rollerballs & Travel Size | Y31: 0 | AC31: =IF(F31="","Not Rated", IF(F31>4,"High Rated","Low Rated")) -> High Rated
A32: P428708 | B32: Patchouli Citrus Eau de Parfum | C32: 6238 | D32: The 7 Virtues | E32: 3882 | F32: 4.3093 | G32: 97 | H32: 1.7 oz/ 50 mL | I32: Size + Concentration + Formulation | J32: 1.7 oz/ 50 mL | L32: ['Organic Sugar Cane Alcohol Denat., Pogostemon Cablin, Water, Benzyl Alcohol, Benzyl Benzoate, Citral, Citronellol, Coumarin, Eugenol, Farnesol, Geraniol, Hydroxycitronellal, Limonene, Linalool, Lonones.'] | M32: 88 | P32: 0 | Q32: 0 | R32: 0 | S32: 0 | T32: 1 | U32: ['Vegan', 'Unisex/ Genderless Scent', 'Clean + Planet Positive', 'Without Phthalates', 'Hypoallergenic', 'Cruelty-Free'] | V32: Fragrance | W32: Women | X32: Perfume | Y32: 1 | Z32: 32 | AA32: 32 | AC32: =IF(F32="","Not Rated", IF(F32>4,"High Rated","Low Rated")) -> High Rated
A33: P500620 | B33: Mini Clay Play To-Go Cheek Palette | C33: 5648 | D33: tarte | E33: 25644 | F33: 4.303 | G33: 33 | L33: ['morning light:', 'Mica, Octyldodecyl Stearoyl Stearate, Synthetic Fluorphlogopite, Bis-Diglyceryl Polyacyladipate-2, Dimethicone, Pentaerythrityl Tetraisostearate, Phenoxyethanol, Silica, Ethylhexylglycerin, Tin Oxide, Kaolin, Tocopherol, Titanium Dioxide (CI 77891), Iron Oxides (CI 77491, CI 77492, CI 77499).', 'elements:', 'Mica, Octyldodecyl Stearoyl Stearate, Bis-Diglyceryl Polyacyladipate-2, Dimethicone, Pentaerythrityl Tetraisostearate, Phenoxyethanol, Silica, Ethylhexylglycerin, Tin Oxide, Kaolin, Tocopherol. (+/-): Titanium Dioxide (CI 77891), Iron Oxides (CI 77491, CI 77492, CI 77499), Red 7 Lake (CI 15850).', 'matte bronzer:', 'Mica, Dimethicone, Dimethicone/Vinyl Dimethicone Crosspolymer, Silica, Bis-Diglyceryl Polyacyladipate-2, Octyldodecyl Stearoyl Stearate, Pentaerythrityl Tetraisostearate, Phenoxyethanol, Ethylhexylglycerin, Kaolin, Tocopherol, Iron Oxides (CI 77491, CI 77492, CI 77499), Red 40 Lake (CI 16035), Titanium Dioxide (CI 77891).'] | M33: 25 | P33: 1 | Q33: 0 | R33: 0 | S33: 0 | T33: 0 | V33: Makeup | W33: Cheek | X33: Cheek Palettes | Y33: 0 | AC33: =IF(F33="","Not Rated", IF(F33>4,"High Rated","Low Rated")) -> High Rated
A34: P427314 | B34: Curl Control Mousse | C34: 6182 | D34: Moroccanoil | E34: 7535 | F34: 3.4146 | G34: 41 | H34: 5.1 oz/ 150 mL | I34: Size | J34: 5.1 oz/ 150 mL | L34: ['Water, Cocamidopropyl Hydroxysultaine, Polysorbate 20, Peg-40 Hydrogenated Castor Oil, Polyquaternium-72, Parfum/Fragrance, Argania Spinosa (Argan) Kernel Oil, Hydrolyzed Vegetable Protein PG-Propyl Silanetriol, Polyquaternium-11, Dipropylene Glycol, Phenoxyethanol, Tetrasodium EDTA, Citric Acid, Chlorphenesin, Polyquaternium-70, Caprylyl Glycol.'] | M34: 30 | P34: 0 | Q34: 0 | R34: 1 | S34: 0 | T34: 0 | V34: Hair | W34: Hair Styling & Treatments | X34: Hair Styling Products | Y34: 0 | AC34: =IF(F34="","Not Rated", IF(F34>4,"High Rated","Low Rated")) -> Low Rated
A35: P471553 | B35: Legendary Conditioner | C35: 6162 | D35: IGK | E35: 1374 | F35: 4.3511 | G35: 262 | H35: 8 oz/ 236 mL | I35: Size | J35: 8 oz/ 236 mL | L35: ['Water (Aqua/Eau), Cetearyl Alcohol, Glycerin, Cetyl Esters, Butyrospermum Parkii (Shea) Butter, Behentrimonium Chloride, Fragrance (Parfum), Chondrus Crispus Extract, Eriophorum Spissum Flower/Stem Extract, Panthenol, Phenoxyethanol, Tilia Tomentosa Extract, Dimethicone, Dimethiconol, BHT, Disodium EDTA, Ethylhexylglycerin, Butyl Methoxydibenzoylmethane, Ethylhexyl Methoxycinnamate, Ethylhexyl Salicylate, Hydroxypropyltrimonium Hydrolyzed Corn Starch, Citric Acid, Sodium Hydroxide, Potassium Sorbate, Tocopherol, Sodium Benzoate, Sorbic Acid, Limonene.'] | M35: 32 | P35: 0 | Q35: 0 | R35: 0 | S35: 0 | T35: 0 | U35: ['Vegan', 'All Hair Types', 'Good for: Dryness', 'Without Parabens', 'Increases Shine'] | V35: Hair | W35: Shampoo & Conditioner | X35: Conditioner | Y35: 0 | AC35: =IF(F35="","Not Rated", IF(F35>4,"High Rated","Low Rated")) -> High Rated
A36: P385350 | B36: â€™REPLICAâ€™ Jazz Club | C36: 7038 | D36: Maison Margiela | E36: 62769 | F36: 4.5857 | G36: 980 | H36: 3.4 oz/ 100 mL | I36: Size + Concentration + Formulation | J36: 3.4 oz/ 100 mL | L36: ['Alcohol, Water, Fragrance, Ethylhexyl Methoxycinnamate, Coumarin, Limonene, Ethylhexyl Salicylate, Butyl Methoxydibenzoylmethane, Linalool, Citral, Geraniol, Ci 15985/Yellow 6, Cinnamal, Hydroxycitronellal, Eugenol Citronellol, Ci 19140/Yellow 5, Ci 17200/Red 33, Ci 42090/Blue 1, C162585/2.'] | M36: 160 | P36: 0 | Q36: 0 | R36: 0 | S36: 0 | T36: 0 | U36: ['Unisex/ Genderless Scent', 'Warm &Spicy Scent'] | V36: Fragrance | W36: Women | X36: Perfume | Y36: 2 | Z36: 85 | AA36: 35 | AC36: =IF(F36="","Not Rated", IF(F36>4,"High Rated","Low Rated")) -> High Rated
A37: P483696 | B37: Gentle Micellar Antioxidant Cleanser | C37: 6488 | D37: The Outset | E37: 3860 | F37: 4.6937 | G37: 111 | H37: 5 oz / 150 mL | I37: Size | J37: 5 oz / 150 mL | L37: ['Water (Aqua, Eau), Propanediol, Glycerin, Triheptanoin, Coco-Caprylate/Caprate, Sodium Polyacryloyldimethyl Taurate, Capryloyl Glycerin/Sebacic Acid Copolymer, Cassia Angustifolia Seed Polysaccharide, Helianthus Annuus (Sunflower) Seed Oil, Heterotheca Inuloides Flower Extract, Chenopodium Quinoa Seed Extract, Poncirus Trifoliata Fruit Extract, Hydrolyzed Brassica Napus Seedcake Extract, SR-Hydrozoan Polypeptide-1, Castor Oil/IPDI Copolymer, Diheptyl Succinate, Phenoxyethanol, Dilinoleic Acid/Butanediol Copolymer, Caprylyl Glycol, Hydrolyzed Jojoba Esters, Lysolecithin, Sclerotium Gum, Tetrahexyldecyl Ascorbate, Tocopheryl Acetate, Tetrasodium Glutamate Diacetate, Pullulan, Xanthan Gum, Jojoba Esters, Silica, Citric Acid, Sodium Benzoate, Sodium Formate, Sodium Glycolate, Sodium Hydroxide, Sodium PCA, Potassium Hydroxide, Potassium Sorbate.'] | M37: 32 | P37: 0 | Q37: 0 | R37: 0 | S37: 0 | T37: 1 | U37: ['Vegan', 'Clean + Planet Positive', 'Hydrating', 'Fragrance Free', 'Hypoallergenic', 'Cruelty-Free'] | V37: Skincare | W37: Cleansers | X37: Face Wash & Cleansers | Y37: 0 | AC37: =IF(F37="","Not Rated", IF(F37>4,"High Rated","Low Rated")) -> High Rated
A38: P504312 | B38: Donna Born In Roma Intense Eau de Parfum | C38: 1169 | D38: Valentino | E38: 13815 | F38: 4.6988 | G38: 581 | H38: 0.34 oz / 10 mL | I38: Size + Concentration + Formulation | J38: 0.34 oz / 10 mL eau de parfum spray | L38: ['Alcohol, Parfum/Fragrance, Aqua/Water/Eau, Benzyl Salicylate, Benzyl Alcohol, Ethylhexyl Salicylate, Butyl Methoxydibenzoylmethane, Hydroxycitronellal, Coumarin, Limonene, Linalool, Alpha-Isomethyl Ionone, Anise Alcohol, Isoeugenol, Methyl Anthranilate, Benzyl Benzoate, Citronellol, Geraniol, Benzyl Cinnamate, Tris (Tetramethylhydroxypiperidinol) Citrate, Citral, Cinnamal, Eugenol, Farnesol, CI 14700/Red 4, CI 17200/Red 33, CI 60730/Ext. Violet 2.'] | M38: 35 | P38: 0 | Q38: 1 | R38: 0 | S38: 0 | T38: 0 | U38: ['Layerable Scent', 'Floral Scent'] | V38: Fragrance | W38: Women | X38: Perfume | Y38: 3 | Z38: 156 | AA38: 85 | AC38: =IF(F38="","Not Rated", IF(F38>4,"High Rated","Low Rated")) -> High Rated
A39: P501243 | B39: GOOPGLOW Exfoliating Dark Spot Sleep Serum | C39: 6309 | D39: goop | E39: 2143 | F39: 4.0598 | G39: 251 | H39: 1 oz / 30 mL | I39: Size | J39: 1 oz / 30 mL | L39: ['Aqua/Water/Eau, Caprylic/Capric Triglyceride, Glycolic Acid, Squalane, Sodium Hydroxide, Behenyl Alcohol, Gluconolactone, Lactic Acid, Glycerin, Polyglyceryl-10 Dioleate, Pentylene Glycol, Propanediol, Magnesium Aluminum Silicate, Sodium Hyaluronate, Aloe Barbadensis Leaf Juice, Salicornia Herbacea Extract, Hydrogenated Lecithin, Hibiscus Sabdariffa Flower Extract, Piperonyl Glucoside, Polyglutamic Acid, Avena Sativa (Oat) Bran Extract, Tamarindus Indica Seed Polysaccharide, Simmondsia Chinensis (Jojoba) Seed Oil, Adansonia Digitata Seed Oil, Citrullus Lanatus (Watermelon) Seed Oil, Phospholipids, Adansonia Digitata Fruit Extract, Cyclodextrin, Xanthan Gum, Glyceryl Undecylenate, Glyceryl Caprylate, Tetrasodium Glutamate Diacetate, Caprylyl Glycol, Ethylhexylglycerin, Sclerotium Gum, 1,2-Hexanediol, Polyglyceryl-10 Dipalmitate, Sodium Benzoate, Potassium Sorbate, Citric Acid.'] | M39: 98 | P39: 0 | Q39: 0 | R39: 0 | S39: 0 | T39: 0 | U39: ['Good for: Dullness/Uneven Texture', 'Hyaluronic Acid', 'Clean at Sephora', 'AHA/Glycolic Acid', 'Best for Dry, Combo, Normal Skin', 'Good for: Dark spots'] | V39: Skincare | W39: Treatments | X39: Face Serums | Y39: 0 | AC39: =IF(F39="","Not Rated", IF(F39>4,"High Rated","Low Rated")) -> High Rated
A40: P426000 | B40: Mini Texturizing Hair Spray | C40: 6144 | D40: OUAI | E40: 14727 | F40: 3.2632 | G40: 95 | H40: 1.4 oz | I40: Size | J40: 1.4 oz | L40: ['Hydrofluorocarbon 152A, Dimethyl Ether, Alcohol Denat., VP/VA Copolymer, Panthenol, Tocopheryl Acetate, Actinidia Chinensis (Kiwi) Fruit Extract, Aloe Barbadensis (Aloe Vera) Leaf Extract, Hedychium Coronarium (Ginger) Root Extract, Mangifera Indica (Mango) Fruit Extract, Passiflora Incarnata (Passion Flower) Extract, Helianthus Annuus (Sunflower) Seed Extract, Glycerin, Acetyl Triethyl Citrate, Fragrance, Zeolite, Butylene Glycol, Water, PEG/PPG-17/18 Dimethicone, Benzoic Acid, Sorbic Acid, Phenoxyethanol, Chlorphenesin, Benzyl Salicylate, Hexyl Cinnamal, Limonene, Butylphenyl Methylpropional, Linalool, Hydroxycitronellal.'] | M40: 14 | P40: 1 | Q40: 0 | R40: 0 | S40: 0 | T40: 0 | V40: Mini Size | W40: Hair | Y40: 0 | AC40: =IF(F40="","Not Rated", IF(F40>4,"High Rated","Low Rated")) -> Low Rated
A41: P504797 | B41: Mini Color Care Conditioner | C41: 6182 | D41: Moroccanoil | E41: 163 | F41: 4.848 | G41: 171 | H41: 2.4 oz / 70 mL | I41: Size | J41: 2.4 oz / 70 mL | L41: ['Aqua/Water/Eau, Cetearyl Alcohol, PEG/PPG-20/20 Phenylisopropyl Caprylyl Dimethicone, Cetyl Alcohol, Stearamidopropyl Dimethylamine, Behentrimonium Chloride, Quaternium-91, Argania Spinosa (Argan) Kernel Oil, Helianthus Annuus (Sunflower) Seed Oil, Parfum/Fragrance, Pyrus Malus (Apple) Fruit Extract, Punica Granatum (Pomegranate) Fruit Extract, Prunus Armeniaca (Apricot) Kernel Oil, Glycerin, PPG-3 Benzyl Ether Myristate, Isopropyl Alcohol, Panthenol, Quaternium-95, Caprylic/Capric Triglyceride, Hydroxyacetophenone, Caprylyl Glycol, Chitosan, Guar Hydroxypropyltrimonium Chloride, Citric Acid, EDTA, PEG-12 Allyl Ether, PEG-12 Dimethicone, Amodimethicone/Morpholinomethyl Silsesquioxane Copolymer, Trideceth-5, Silica Dimethyl Silylate, Algin, Pentaerythrityl Tetra-Di-T-Butyl Hydroxyhydrocinnamate, Chlorphenesin, C12-13 Pareth-9, Propanediol, Sodium Benzoate, Potassium Sorbate, Phenoxyethanol, Sorbic Acid.'] | M41: 12 | P41: 0 | Q41: 1 | R41: 1 | S41: 0 | T41: 0 | U41: ['Sustainable Packaging', 'Good for: Color Care', 'Prevents Color Fading', 'Without Sulfates SLS & SLES', 'Increases Shine', 'Cruelty-Free'] | V41: Mini Size | W41: Hair | Y41: 0 | AC41: =IF(F41="","Not Rated", IF(F41>4,"High Rated","Low Rated")) -> High Rated
A42: P429981 | B42: Dylan Blue Pour Femme | C42: 2084 | D42: Versace | E42: 36867 | F42: 4.1516 | G42: 310 | H42: 1.7 oz/ 50 mL | I42: Size + Concentration + Formulation | J42: 1.7 oz/ 50 mL | L42: ['Alcohol Denat. (Sd Alcohol 39-C), Fragrance, Water, Benzyl Salicylate,', 'Limonene, Citronellol, Hydroxycitronellal, Alpha-Isomethyl Ionone, Ethylhexyl', 'Methoxycinnamate, Linalool, Benzyl Benzoate, Hexyl Cinnamal, Ethylhexyl Salicylate,', 'Butyl Methoxydibenzoylmethane, Geraniol, Citral, Benzyl Alcohol, Farnesol, Cinnamyl Alcohol.'] | M42: 98 | P42: 0 | Q42: 0 | R42: 0 | S42: 0 | T42: 0 | U42: ['allure 2020 Best of Beauty Award Winner', 'Floral Scent'] | V42: Fragrance | W42: Women | X42: Perfume | Y42: 3 | Z42: 74 | AA42: 32 | AC42: =IF(F42="","Not Rated", IF(F42>4,"High Rated","Low Rated")) -> High Rated
A43: P425840 | B43: Mini Ambient Lighting Powder | C43: 5879 | D43: Hourglass | E43: 65833 | F43: 4.086 | G43: 314 | H43: 0.049 oz/ 1.4 g | I43: Color | J43: Diffused Light | K43: soft, warm pale yellow powder | L43: ['Mica, Synthetic Fluorphlogopite, Boron Nitride, Hdi/Trimethylol Hexyllactone Crosspolymer, Polymethyl Methacrylate, Octyldodecanol, Benzoic Acid, C13-14 Isoparaffin, Dehydroacetic Acid, Diamond Powder, Dimethicone, Ethylhexylglycerin, Laureth-7, Magnesium Aluminum Silicate, Phenoxyethanol, Polyacrylamide, Polymethylsilsesquioxane, Potassium Sorbate, Silica, Sodium Dehydroacetate, Sorbic Acid, Sorbitan Sesquioleate, Trimethylsiloxysilicate. May Contain (+/-): Bismuth Oxychloride (Ci 77163), Iron Oxides (Ci 77491, Ci 77492, Ci 77499), Titanium Dioxide (Ci 77891).'] | M43: 28 | P43: 0 | Q43: 0 | R43: 0 | S43: 0 | T43: 1 | U43: ['Without Parabens', 'Radiant Finish', 'Vegan'] | V43: Mini Size | W43: Makeup | Y43: 3 | Z43: 28 | AA43: 28 | AC43: =IF(F43="","Not Rated", IF(F43>4,"High Rated","Low Rated")) -> High Rated
A44: P504204 | B44: True Textures Curl Enhancing Cream | C44: 6315 | D44: Mizani | E44: 1437 | F44: 4.5227 | G44: 352 | H44: 10.89 oz / 325 mL | I44: Size | J44: 10.89 oz / 325 mL | L44: ['Aqua/Water/Eau, Propylene Glycol, Dimethicone, Phenoxyethanol, Polyquaternium-11, Guar Hydroxypropyltrimonium Chloride, Cetearyl Alcohol, Parfum/Fragrance, Hydroxypropyl Guar, Caprylyl Glycol, Styrene/Acrylates Copolymer, Laureth-4, Dicetyl Phosphate, Laureth-23, Ceteth-10 Phosphate, Olea Europaea Oil/Olive Fruit Oil, Sclerocarya Birrea Seed Oil, Cocos Nucifera Oil/Coconut Oil, Benzophenone-4, Disodium EDTA, Sodium Citrate, Limonene, Coumarin, 2-Oleamido-1, 3-Octadecanediol, Linalool, Benzyl Alcohol, Hydroxycitronellal, Sodium Lauryl Sulfate, Citral, Geraniol, Disodium Laureth Sulfosuccinate, CI 19140/Yellow 5, CI 15985/Yellow 6.'] | M44: 25 | P44: 0 | Q44: 1 | R44: 0 | S44: 0 | T44: 0 | U44: ['Long-wearing', 'Curl-Enhancing', 'Good for: Frizz', 'Curly Hair', 'Good for: Dryness'] | V44: Hair | W44: Hair Styling & Treatments | X44: Hair Styling Products | Y44: 0 | AC44: =IF(F44="","Not Rated", IF(F44>4,"High Rated","Low Rated")) -> High Rated
A45: P417212 | B45: Peony & Blush Suede Body CrÃ¨me | C45: 6202 | D45: Jo Malone London | E45: 5073 | F45: 4.4706 | G45: 17 | H45: 5.9 oz/ 175 mL | I45: Size + Concentration + Formulation | J45: 5.9 oz/ 175 mL Body Cream | L45: ['Water, Glycerin, Cetearyl Alcohol, Simmondsia Chinensis (Jojoba) Seed Oil, Glyceryl Stearate, Stearic Acid, Fragrance, Triethanolamine, Isopropyl Palmitate, Theobroma Cacao (Cocoa) Seed Butter, Prunus Amygdalus Dulcis (Sweet Almond) Oil, Aloe Barbadensis Leaf Extract, Dimethicone, Caffeine, Caprylyl Glycol, Bisabolol, Hexylene Glycol, Disodium Edta, Benzyl Alcohol, Benzyl Salicylate, Geraniol, Hydroxycitronellal, Citronellol, Linalool, Alpha-Isomethyl Ionone, Eugenol, Cinnamyl Alcohol, Limonene, Phenoxyethanol <ILN40189>.'] | M45: 90 | P45: 0 | Q45: 0 | R45: 0 | S45: 0 | T45: 0 | V45: Bath & Body | W45: Body Moisturizers | X45: Body Lotions & Body Oils | Y45: 1 | Z45: 38 | AA45: 38 | AC45: =IF(F45="","Not Rated", IF(F45>4,"High Rated","Low Rated")) -> High Rated
A46: P482060 | B46: Mini RESIST Youth-Extending Daily Hydrating Fluid SPF 50 | C46: 6341 | D46: Paula's Choice | E46: 15303 | F46: 4.3966 | G46: 58 | H46: .5 oz / 15 mL | I46: Size | J46: .5 oz / 15 mL | L46: ['Avobenzone 2%, Octinoxate 7.5%, Octisalate 5%, Octocrylene 2%, Water (Aqua), Glycerin, Silica, Dimethicone, Tocopherol, Chamomilla Recutita (Matricaria) Flower Extract, Vitis Vinifera (Grape) Seed Extract, Camellia Sinensis (Green Tea) Leaf Extract, Camellia Oleifera (Green Tea) Leaf Extract, Peucedanum Graveolens (Dill) Extract, Sambucus Nigra (Black Elderberry) Fruit Extract, Avena Sativa (Oat) Bran Extract, Punica Granatum (Pomegranate) Extract, Lycium Barbarum (Goji) Fruit Extract, Hydrogenated Lecithin, Titanium Dioxide, Dimethicone/Vinyl Dimethicone Crosspolymer, Diethylhexyl Syringylidenemalonate, Hydroxyethyl Acrylate/Sodium Acryloyldimethyl Taurate Copolymer, Xanthan Gum, Sodium Carbomer, Benzyl Alcohol, Sodium Benzoate, Potassium Sorbate, Phenoxyethanol.'] | M46: 12 | P46: 0 | Q46: 0 | R46: 0 | S46: 0 | T46: 0 | U46: ['Good for: Anti-Aging', 'Matte Finish', 'Oil Free', 'Best for Oily, Combo, Normal Skin', 'SPF'] | V46: Mini Size | W46: Skincare | Y46: 0 | AC46: =IF(F46="","Not Rated", IF(F46>4,"High Rated","Low Rated")) -> High Rated
A47: P480178 | B47: Apple Brandy Eau de Parfum Travel Spray | C47: 6240 | D47: KILIAN Paris | E47: 10759 | F47: 4.4 | G47: 25 | H47: 0.24 oz/ 7.5 mL | I47: Size + Concentration + Formulation | J47: 0.24 oz/ 7.5 mL parfum spray | L47: ['Alcohol Denat., Water/Aqua/Eau, Fragrance (Parfum), Limonene, Linalool, Evernia Prunastri (Oakmoss) Extract, Citral, Geraniol, Citronellol, Tocopherol <Iln49607>.'] | M47: 50 | P47: 0 | Q47: 0 | R47: 0 | S47: 0 | T47: 1 | V47: Fragrance | W47: Women | X47: Rollerballs & Travel Size | Y47: 0 | AC47: =IF(F47="","Not Rated", IF(F47>4,"High Rated","Low Rated")) -> High Rated
A48: P393325 | B48: Beyond Perfecting Foundation + Concealer | C48: 1254 | D48: CLINIQUE | E48: 112957 | F48: 3.7543 | G48: 2572 | H48: 1 oz/ 30 mL | I48: Color | J48: CN 0.5 Shell | K48: fairest shade; with a cool neutral undertone | L48: ['Water\\Aqua\\Eau, Isostearyl Neopentanoate, Dimethicone, Isohexadecane, Trimethylsiloxysilicate, Butylene Glycol, Glycerin, Lauryl Peg-9 Polydimethylsiloxyethyl Dimethicone, Disteardimonium Hectorite, Trehalose, Peg-10 Dimethicone, Hdi/Trimethylol Hexyllactone Crosspolymer, Dimethicone/Peg-10/15 Crosspolymer, Triethoxycaprylylsilane, Sodium Hyaluronate, Hydrolyzed Soy Protein, Tocopheryl Acetate, Polymethyl Methacrylate, Propylene Carbonate, Lecithin, Laureth-7, Hydrogenated Lecithin, Dimethicone Silylate, Xanthan Gum, Dipropylene Glycol, Sodium Chloride, Magnesium Aluminum Silicate, Silica, Coconut Acid, Disodium Edta, Phenoxyethanol, [+/- Mica, Iron Oxides (Ci 77491), Iron Oxides (Ci 77492), Iron Oxides (Ci 77499), Titanium Dioxide (Ci 77891), Zinc Oxide (Ci 77947), Bismuth Oxychloride (Ci 77163).'] | M48: 37 | P48: 0 | Q48: 0 | R48: 0 | S48: 0 | T48: 0 | V48: Makeup | W48: Face | X48: Foundation | Y48: 34 | Z48: 37 | AA48: 36 | AC48: =IF(F48="","Not Rated", IF(F48>4,"High Rated","Low Rated")) -> Low Rated
A49: P409630 | B49: SEA Pack Your Bags Undereye Patches | C49: 5648 | D49: tarte | E49: 56808 | F49: 4.1779 | G49: 298 | H49: 4 x 2 single use patches | I49: Size | J49: 4 x 2 single use patches | L49: ['Water, Glycerin, Butylene Glycol, Mannitol, Sodium Polyglutamate, Algin, Chondrus Crispus Powder, Laureth-21, Polyglyceryl-10 Laurate, Cocos Nucifera (Coconut) Oil, Carbomer, Sodium Lactate, Polysorbate 20, Hydroxypropyl Cyclodextrin, Algae Extract, Gardenia Taitensis Flower Extract, Palmaria Palmata Extract, Palmitoyl Pentapeptide-4, Tocopherol, Phenoxyethanol, Iodopropynyl Butylcarbamate.'] | M49: 22 | O49: 11 | P49: 0 | Q49: 0 | R49: 0 | S49: 1 | T49: 1 | U49: ['Clean at Sephora', 'Vegan'] | V49: Skincare | W49: Eye Care | X49: Eye Masks | Y49: 0 | AC49: =IF(F49="","Not Rated", IF(F49>4,"High Rated","Low Rated")) -> High Rated
A50: P474338 | B50: Specifique Divalent Hydrating Gel-Mask for Oily Hair | C50: 6259 | D50: KÃ©rastase | E50: 3130 | F50: 4.2647 | G50: 68 | L50: ['Aqua/Water/Eau, Hydroxypropyl Starch Phosphate, Quaternium-87, Stearyl Alcohol, Behentrimonium Chloride, Propylene Glycol, Isononyl Isononanoate, Cetyl Esters, Caprylyl Glycol, Capryloyl Glycine, Candelilla Cera/Candelilla Wax/Cire De Candelilla, Isopropyl Alcohol, Phenoxyethanol, Sodium Hydroxide, Linalool, Limonene, Geraniol, Citronellol, Alpha-Isomethyl Ionone, 2-Oleamido-1,3-Octadecanediol, CI 42090/Blue 1, CI 19140/Yellow 5, Parfum/Fragrance.'] | M50: 68 | P50: 0 | Q50: 0 | R50: 1 | S50: 0 | T50: 0 | U50: ['Hydrating', 'Fresh Scent', 'All Hair Types', 'Good for: Dryness', 'Increases Shine', 'Good for: Oily Scalp'] | V50: Hair | W50: Hair Styling & Treatments | X50: Hair Masks | Y50: 0 | AC50: =IF(F50="","Not Rated", IF(F50>4,"High Rated","Low Rated")) -> High Rated
A51: P454990 | B51: Mini babassu foundcealer skincare foundation SPF 20 | C51: 5648 | D51: tarte | E51: 9262 | F51: 3.52 | G51: 25 | H51: 0.33 oz/ 10 mL | I51: Color | J51: 13N fair neutral | K51: fair skin with neutral undertones | L51: ['Water, Phenyl Trimethicone, Butylene Glycol, Dimethicone, Butylene Glycol Dicaprylate/Dicaprate, Butyloctyl Salicylate, Cyclohexasiloxane, Cetyl PEG/PPG-10/1 Dimethicone, Bis-Diglyceryl Polyacyladipate-2, Aluminum Hydroxide, Methyl Methacrylate Crosspolymer, Orbignya Oleifera (Babassu) Seed Oil, Polypropylsilsesquioxane, Sodium Chloride, Stearic Acid, Polyglyceryl-4 Isostearate, Hexyl Laurate, Dimethicone/Vinyl Dimethicone Crosspolymer, Calcium Stearate, Disteardimonium Hectorite, Triethoxycaprylylsilane, Sodium Benzoate, Potassium Sorbate, Tocopherol, Polyhydroxystearic Acid, Helianthus Annuus (Sunflower) Seed Oil, Ethylhexyl Palmitate, Isopropyl Myristate, Isostearic Acid, Lecithin, Disodium EDTA, Cyclopentasiloxane, Polyglyceryl-3 Polyricinoleate, Kaolin, Cyclotetrasiloxane, Phenoxyethanol, Sodium Hyaluronate, Ethylhexylglycerin, Hydrolyzed Hyaluronic Acid, Titanium Dioxide, Iron Oxides.'] | M51: 16 | P51: 0 | Q51: 0 | R51: 0 | S51: 0 | T51: 0 | V51: Makeup | W51: Face | X51: Foundation | Y51: 3 | Z51: 16 | AA51: 16 | AC51: =IF(F51="","Not Rated", IF(F51>4,"High Rated","Low Rated")) -> Low Rated
A52: P502055 | B52: Dolce Nourishing Shampoo | C52: 6159 | D52: Rossano Ferretti Parma | E52: 346 | F52: 5 | G52: 3 | H52: 1.7 oz / 50 mL | I52: Size | J52: 1.7 oz / 50 mL | L52: ['Aqua/Water/Eau, Laureth-5 Carboxylic Acid, Disodium Laureth Sulfosuccinate, Cocamidopropyl Betaine, Sodium Lauryl Sulfoacetate, Sodium Lauroyl Methyl Isethionate, Sodium Methyl Cocoyl Taurate, Sodium Hyaluronate, Aloe Barbadensis Leaf Juice, Hydrogenated Palm Glycerides Citrate, Vitis Vinifera (Grape) Leaf Extract, Panax Ginseng Root Extract, Paullinia Cupana Seed Extract, Serine, Pullulan, Tocopherol, Algin, Trehalose, Lauryl/Myristyl Polyricinoleate, Polyquaternium-7, Coco-Glucoside, Laureth-4, Caprylyl Glycol, Glyceryl Polyacrylate, Potassium Phosphate, Disodium Phosphate, Pentylene Glycol, Glyceryl Oleate, Glycol Distearate, Glycerol, Urea, Glycerin, Peg-120 Methyl Glucose Dioleate, Methoxy Peg/Ppg-7/3 Aminopropyl Dimethicone, Citric Acid, Sodium Benzoate, Potassium Sorbate, Gluconolactone, Calcium Gluconate, Phenoxyethanol, Limonene, Linalool, Parfum (Fragrance).'] | M52: 16 | P52: 0 | Q52: 0 | R52: 1 | S52: 0 | T52: 0 | U52: ['Vegan', 'Hyaluronic Acid', 'Good for: Frizz', 'Good for: Dryness', 'Without Sulfates SLS & SLES', 'Cruelty-Free'] | V52: Hair | W52: Shampoo & Conditioner | X52: Shampoo | Y52: 1 | Z52: 39 | AA52: 39 | AC52: =IF(F52="","Not Rated", IF(F52>4,"High Rated","Low Rated")) -> High Rated
A53: P502170 | B53: Hold Up Soft Set Creamy Eyebrow Wax | C53: 6246 | D53: LAWLESS | E53: 10006 | F53: 4.7289 | G53: 284 | H53: 0.24 oz / 7 mL | I53: Color | J53: Light/Medium | K53: flexible light/medium | L53: ['Water (Aqua), Euphorbia Cerifera (Candelilla) Wax [Euphorbia Cerifera Cera], Steareth-21, Glyceryl Stearate, Mica, Butylene Glycol, Acacia Senegal Gum [Acacia Senegal], Silica, Butyrospermum Parkii (Shea) Butter [Butyrospermum Parkii Butter], Cellulose, Dimer Dilinoleyl Dimer Dilinoleate, Simmondsia Chinensis (Jojoba) Seed Oil [Simmondsia Chinensis Seed Oil], Copernicia Cerifera (Carnauba) Wax [Copernicia Cerifera Wax], Argania Spinosa Kernel Oil, Cetyl Alcohol, Polyglyceryl-10 Myristate, Oryza Sativa (Rice) Starch [Oryza Sativa Starch], Phenoxyethanol, Caprylyl Glycol, Sodium Benzoate, Potassium Sorbate, Arginine, Chondrus Crispus Powder, Tocopherol, Simethicone, Titanium Dioxide (Ci 77891), Iron Oxides (Ci 77491, Ci 77492, Ci 77499).'] | M53: 21 | P53: 0 | Q53: 0 | R53: 0 | S53: 0 | T53: 1 | U53: ['Vegan', 'allure 2022 Best of Beauty Award Winner', 'Clean at Sephora', 'Long-wearing', 'Without Silicones', 'Cruelty-Free'] | V53: Makeup | W53: Eye | X53: Eyebrow | Y53: 1 | Z53: 21 | AA53: 21 | AC53: =IF(F53="","Not Rated", IF(F53>4,"High Rated","Low Rated")) -> High Rated
A54: P427385 | B54: Shimmer & Glow Liquid Eye Shadow | C54: 3865 | D54: stila | E54: 183848 | F54: 4.6466 | G54: 1197 | H54: 0.153 oz | I54: Color | J54: Grace | K54: shimmering rosey taupe | L54: ['Water, Mica (Ci 77019), Hydroxyethyl Acrylate/Sodium Acryloyldimethyl Taurate Copolymer, Squalane, Synthetic Fluorphlogopite, Calcium Sodium Borosilicate, Polysorbate 60, Caprylyl Glycol, Phenoxyethanol, Glycerin, Triethanolamine, Carbomer, Sorbitan Isostearate, Hexylene Glycol, Silica, Tin Oxide. (+/-) Titanium Dioxide (Ci 77891), Iron Oxides (Ci 77491, Ci 77499), Carmine (Ci 75470), Ferric Ferrocyanide (Ci 77510).'] | M54: 25 | P54: 0 | Q54: 0 | R54: 0 | S54: 0 | T54: 0 | U54: ['Liquid Formula', 'Medium Coverage', 'Shimmer Finish'] | V54: Makeup | W54: Eye | X54: Eyeshadow | Y54: 3 | Z54: 25 | AA54: 25 | AC54: =IF(F54="","Not Rated", IF(F54>4,"High Rated","Low Rated")) -> High Rated
A55: P429434 | B55: You Glow Girl Iridescent Jelly | C55: 6235 | D55: INC.redible | E55: 27977 | F55: 3.8776 | G55: 147 | H55: 0.32 oz/ 9.35 g | I55: Color | J55: Show Glow | K55: gold | L55: ['Water, Butylene Glycol, Glycerin, Calcium Sodium Borosilicate, Phenoxyethanol, PEG-240/HDI Copolymer Bis-Decyltetradeceth-20 Ether, Mica, Silica, Sodium Hyaluronate, Tin Oxide. May Contain (+/-): Titanium Dioxide (Ci 77891), Iron Oxides (Ci 77491).'] | M55: 12 | P55: 0 | Q55: 0 | R55: 0 | S55: 0 | T55: 0 | V55: Makeup | W55: Face | X55: Highlighter | Y55: 0 | AC55: =IF(F55="","Not Rated", IF(F55>4,"High Rated","Low Rated")) -> Low Rated
A56: P383054 | B56: Do Not Age with Dr. Brandt Transforming Pearl Serum | C56: 4372 | D56: Dr. Brandt Skincare | E56: 3259 | F56: 4.1852 | G56: 54 | H56: 1.35 oz/ 40 mL | I56: Size | J56: 1.35 oz/ 40 mL | L56: ['Water (Aqua), Caprylic /Capric Triglyceride, Propanediol, Glycerin, Pentylene Glycol, Alcohol Denat., Prunus Armeniaca (Apricot) Kernel Oil, Phenoxyethanol, Hydroxyethylpiperazine Ethane Sulfonic Acid, Sodium Hydroxide, Xanthan Gum, Sodium Hyaluronate, Hydroxyethylcellulose, Carrageenan, Algin, Decarboxy Carnosine Hcl, Synthetic Fluorphlogopite, Butylene Glycol, Spilanthes Acmella Flower Extract, Titanium Dioxide (Ci 77891), Alaria Esculenta Extract, Geranylgeranylisopropanol, Silica, Mica, Sodium Acetate, Bht, Sodium Lauryl Sulfate, Cellulose, Citrus Aurantium Dulcis (Orange) Peel Oil, Citrus Aurantium Dulcis (Orange) Fruit Extract, Cananga Odorata Flower Oil, Vanillin, Lavandula Hybrida Oil, Litsea Cubeba Fruit Oil, Vanilla Planifolia Fruit Extract, Jasminum Sambac (Jasmine) Flower Extract, Tin Oxide, Limonene.'] | M56: 152 | P56: 0 | Q56: 0 | R56: 0 | S56: 0 | T56: 0 | V56: Skincare | W56: Treatments | X56: Face Serums | Y56: 0 | AC56: =IF(F56="","Not Rated", IF(F56>4,"High Rated","Low Rated")) -> High Rated
A57: P504319 | B57: Golden Nectar Perfume Set | C57: 7025 | D57: NEST New York | E57: 2443 | F57: 4.1667 | G57: 6 | L57: ['Alcohol Denat., Fragrance (Parfum), Water (Aqua), Alpha-Isomethyl Ionone, Cinnamyl Alcohol, Citral, Citronellol, Coumarin, Farnesol, Geraniol, Limonene, Linalool.'] | M57: 86 | P57: 1 | Q57: 1 | R57: 0 | S57: 1 | T57: 0 | V57: Fragrance | W57: Value & Gift Sets | X57: Perfume Gift Sets | Y57: 0 | AC57: =IF(F57="","Not Rated", IF(F57>4,"High Rated","Low Rated")) -> High Rated
A58: P461217 | B58: Illuminator Liquid Highlight | C58: 6331 | D58: Iconic London | E58: 46623 | F58: 4.4943 | G58: 87 | H58: 0.45 oz/ 13.5 mL | I58: Color | J58: Blush | K58: peachy antique-rose based shimmer that adds a warm rosy glow | L58: ['Hydrogenated Didecene Isododecane Hydrogenated Polyisobutene Mica Hydrogenated Polycyclopentadiene Hydrogenated Styrene/Isoprene Copolymer Triethoxycaprylylsilane 1,2-Hexanediol Caprylyl Glycol May Contain: CI 77491 (Iron Oxides) CI 77891 (Titanium Dioxide).'] | M58: 40 | P58: 0 | Q58: 0 | R58: 0 | S58: 0 | T58: 0 | U58: ['Liquid Formula', 'High Shine Finish', 'Alcohol Free', 'Oil Free', 'Vegan'] | V58: Makeup | W58: Face | X58: Highlighter | Y58: 2 | Z58: 40 | AA58: 40 | AC58: =IF(F58="","Not Rated", IF(F58>4,"High Rated","Low Rated")) -> High Rated
A59: P501520 | B59: Noir Extreme Parfum | C59: 5869 | D59: TOM FORD | E59: 1838 | F59: 4.6117 | G59: 273 | H59: 3.4 oz / 100 mL | I59: Size + Concentration + Formulation | J59: 3.4 oz / 100 mL parfum spray | L59: ['Alcohol Denat., Fragrance (Parfum), Water\\Aqua\\Eau, Benzyl Salicylate, Hydroxycitronellal, Alpha-Isomethyl Ionone, Coumarin, Limonene, Linalool, Eugenol, Farnesol, Cinnamal, Geraniol, Citronellol, Benzyl Benzoate, Amyl Cinnamal, Cinnamyl Alcohol, Citral, Pentaerythrityl Tetra-Di-T-Butyl Hydroxyhydrocinnamate, Phenoxyethanol <ILN50363>'] | M59: 235 | P59: 0 | Q59: 0 | R59: 0 | S59: 0 | T59: 0 | U59: ['Unisex/ Genderless Scent', 'Layerable Scent', 'Warm &Spicy Scent'] | V59: Fragrance | W59: Men | X59: Cologne | Y59: 1 | Z59: 180 | AA59: 180 | AC59: =IF(F59="","Not Rated", IF(F59>4,"High Rated","Low Rated")) -> High Rated
A60: P500426 | B60: Solar Radiance Hydrating Cream Highlighter Refill | C60: 6367 | D60: ROSE INC | E60: 902 | F60: 4 | G60: 2 | H60: 0.2 oz / 6 mL | I60: Color | J60: Glancing | K60: rosy bronze | L60: ['Caprylic/Capric Triglyceride, C13-15 Alkane, Silica, Octyldodecanol, Ricinus Communis (Castor) Seed Oil, Euphorbia Cerifera (Candelilla) Wax, Copernicia Cerifera (Carnauba) Wax, Glyceryl Hydrogenated Rosinate, Squalane, Eryngium Maritimum Callus Culture Filtrate, Ascorbyl Palmitate, Tocopherol, Rosa Damascena Flower Oil, Rosa Damascena Flower Water, Pentaerythrityl Tetra-di-t-butyl Hydroxyhydrocinnamate, Boron Nitride, Pentylene Glycol, Caprylyl Glycol, Tin Oxide, [+/-: Mica, Titanium Dioxide (CI 77891), Iron Oxides (CI 77491, CI 77499), Manganese Violet (CI 77742), Ultramarines (CI 77007)].'] | M60: 18 | P60: 0 | Q60: 0 | R60: 0 | S60: 0 | T60: 1 | U60: ['Vegan', 'Radiant Finish', 'Refill Available', 'Cream Formula', 'Clean + Planet Positive', 'Hydrating'] | V60: Makeup | W60: Face | X60: Highlighter | Y60: 4 | Z60: 18 | AA60: 18 | AC60: =IF(F60="","Not Rated", IF(F60>4,"High Rated","Low Rated")) -> Low Rated
A61: P475590 | B61: MINI GINZING VITAMIN C EYE CREAM TO BRIGHTEN AND DEPUFF | C61: 3733 | D61: Origins | E61: 18284 | F61: 3.45 | G61: 40 | H61: .34 oz/ 10 mL | I61: Color | J61: Original | L61: ['Water/Aqua/Eau, Butylene Glycol, PEG-100 Stearate, Dimethicone, Silica, Cetyl Ricinoleate, Olea Europaea (Olive) Fruit Oil, Glycerin, Panax Ginseng (Ginseng) Root Extract, Coffea Arabica (Coffee) Seed Oil, Caffeine, Citrus Aurantium Dulcis (Orange) Peel Extract, Aminopropyl Ascorbyl Phosphate, Caprylic/Capric Triglyceride, Hypnea Musciformis (Algae) Extract, Gelidiella Acerosa Extract, Sigesbeckia Orientalis (St. Paul Wort) Extract, Ascophyllum Nodosum Extract, Chrysanthellum Indicum Extract, Asparagopsis Armata Extract, Cucumis Sativus (Cucumber) Fruit Extract, Pyrus Malus (Apple) Fruit Extract, Scutellaria Baicalensis Root Extract, Molasses Extract/Saccharum Officinarum/Extrait De MÃ©lasse, Butyrospermum Parkii (Shea) Butter, Simmondsia Chinensis (Jojoba) Seed Oil, Sodium Hyaluronate, Niacinamide, Linoleic Acid, Phytosphingosine, Tocopheryl Acetate, Methyl Trimethicone, Trehalose, Tribehenin, Inulin, Sorbitol, Ethylhexylglycerin, Caprylyl Glycol, Tocopherol, Myristyl Alcohol, Hydrogenated Lecithin, Jojoba Wax PEG-120 Esters, Carbomer, Behenyl Alcohol, Sodium Hydroxide, BHT, Hydroxyacetophenone, Sodium Metabisulfite, Sodium Sulfite, Disodium EDTA, Phenoxyethanol, Chlorphenesin, Sorbic Acid, Potassium Sorbate, [+/- Mica, Titanium Dioxide (CI 77891), Iron Oxides (CI 77491), Iron Oxides (CI 77492), Bismuth Oxychloride (CI 77163)].'] | M61: 29 | P61: 0 | Q61: 0 | R61: 1 | S61: 0 | T61: 0 | U61: ['Vegan', 'Good for: Dullness/Uneven Texture', 'Vitamin C', 'Good for: Dark Circles', 'Good for: Dryness', 'Niacinamide'] | V61: Skincare | W61: Eye Care | X61: Eye Creams & Treatments | Y61: 0 | AC61: =IF(F61="","Not Rated", IF(F61>4,"High Rated","Low Rated")) -> Low Rated
A62: P470507 | B62: The Cream with TFC8 Face Moisturizer | C62: 6356 | D62: Augustinus Bader | E62: 11428 | F62: 4.3605 | G62: 430 | H62: 1 oz/ 30 mL | I62: Size | J62: 1 oz/ 30 mL | L62: ['Aqua (Water), Caprylic/Capric Triglyceride, Pentylene Glycol, Propylene Glycol, Hydrogenated Phosphatidylcholine, Glycerin, Sorbitol, Tocopheryl Acetate, Butyrospermum Parkii (Shea) Butter, Xanthan Gum, Butylene Glycol, Panthenol, Sodium Carbomer, Aloe Barbadensis Leaf Juice, Alcohol, Hydrolyzed Rice Protein, Squalane, Helianthus Annuus (Sunflower) Seed Oil, Phenoxyethanol, Sodium Hydroxide, Carbomer, Lecithin, Cholesterol, Hydrogenated Lecithin, Ascorbyl Palmitate, Ceramide NP, Glycine Soja (Soybean) Protein, Superoxide Dismutase, Citric Acid, Dextran, Palmitoyl Tripeptide-8, Alanyl Glutamine, Arginine, Ceramide NG, Glycine, Lysine, Oleic Acid, Palmitic Acid, Phenylalanine, Proline, Scenedesmus Rubescens Extract, Ascorbic Acid, Retinyl Palmitate, Sodium Benzoate, Potassium Sorbate, Ethylhexylglycerin, Sodium Dextran Sulfate, Brassica Alba Oil, Disodium EDTA, Oligopeptide-177, Sodium Ascorbate, Tocopherol.'] | M62: 180 | P62: 0 | Q62: 0 | R62: 0 | S62: 0 | T62: 0 | U62: ['Vitamin C', 'Good for: Anti-Aging', 'Good for: Loss of firmness', 'Good for: Dullness/Uneven Texture', 'Good for: Dark spots', 'Best for Oily, Combo, Normal Skin'] | V62: Skincare | W62: Moisturizers | X62: Moisturizers | Y62: 2 | Z62: 290 | AA62: 92 | AC62: =IF(F62="","Not Rated", IF(F62>4,"High Rated","Low Rated")) -> High Rated
A63: P477798 | B63: Nail Prep Set | C63: 3902 | D63: SEPHORA COLLECTION | E63: 4153 | F63: 4.3333 | G63: 6 | M63: 20 | O63: 10 | P63: 0 | Q63: 0 | R63: 0 | S63: 0 | T63: 1 | V63: Makeup | W63: Nail | Y63: 0 | AC63: =IF(F63="","Not Rated", IF(F63>4,"High Rated","Low Rated")) -> High Rated
A64: P501474 | B64: The Youth Vault: 13-Piece Vegan Skincare + Apparel Set | C64: 6169 | D64: Youth To The People | E64: 8989 | F64: 4.875 | G64: 8 | L64: ['Superfood Antioxidant Cleanser:', 'Water/Aqua/Eau, Cocamidopropyl Hydroxysultaine, Sodium Cocoyl Glutamate, Sorbeth-230 Tetraoleate, Polysorbate 20, Sodium Chloride, Aloe Barbadensis Leaf (Aloe Vera) Juice Powder, Brassica Oleracea Acephala (Kale) Leaf Extract, Spinacia Oleracea (Spinach) Leaf Extract, Camellia Sinensis (Green Tea) Leaf Extract, Medicago Sativa (Alfalfa) Extract, Chamomilla Recutita (Matricaria) Flower Extract, Tetrahexyldecyl Ascorbate (Vitamin C), Glycerin, Panthenol (Vitamin B5), Tocopheryl Acetate (Vitamin E), Decyl Glucoside, Sorbitan Laurate, Tetrasodium Glutamate Diacetate, Gluconolactone, Ethylhexylglycerin, Maltodextrin, Citric Acid, Phenoxyethanol, Potassium Sorbate, Sodium Benzoate, Gardenia Jasminoides (Jasmine) Fruit Extract, Fragrance/Parfum, Sodium Hydroxide, Sodium Glycolate, Sodium Formate, Hexyl Cinnamal, Linalool, Limonene, Chlorophyllin-Copper Complex (CI 75810).', 'Triple Peptide + Cactus Oasis Serum:', 'Water/Aqua/Eau, Butylene Glycol, Glycerin, Pentylene Glycol, Opuntia Ficus-Indica Stem (Prickly Pear Cactus) Extract, Palmitoyl Tripeptide-1, Palmitoyl Tetrapeptide-7, Palmitoyl Tripeptide-28, Sodium Hyaluronate, Hydrolyzed Sodium Hyaluronate, Sodium Hyaluronate Crosspolymer, Sodium Acetylated Hyaluronate, Synthetic Sapphire, Citrullus Lanatus (Watermelon) Fruit Extract, Lens Esculenta (Lentil) Fruit Extract, Pyrus Malus (Apple) Fruit Extract, Nephelium Lappaceum Peel (Rambutan) Extract, Sodium Pca, Glutathione, Malachite Extract, Citric Acid, Hydroxypropyl Methylcellulose, Tetrasodium Glutamate Diacetate, Polyglutamic Acid, 1,2-Hexandiol, Caprylyl Glycol, Sodium Lactate, Carbomer, Propanediol, Polysorbate 20, Hydroxyethylcellulose, Xanthan Gum, Phenoxyethanol, Ethylhexylglycerin, Sodium Benzoate, Potassium Sorbate, Disodium Phosphate, Polysorbate 60, Benzyl Alcohol, Sodium Hydroxide, Glyceryl Caprylate, Sodium Formate, Sodium Glycolate, Sodium Phosphate, Benzoic Acid.', 'Superfood Air-Whip Moisture Cream:', 'Water/Aqua/Eau, Helianthus Annuus (Sunflower) Seed Oil, Glyceryl Stearate, Cetyl Alcohol, Glycerin, Lecithin, Butylene Glycol, Panthenol (Vitamin B5), Sodium Hyaluronate Crosspolymer, Tocopheryl Acetate (Vitamin E), Phenoxyethanol, Ascorbic Acid (Vitamin C), Hydroxyethylcellulose, Brassica Oleracea Capitata (Kale) Leaf Extract, Camellia Sinensis (Green Tea) Leaf Extract, Chamomilla Recutita (Matricaria) Flower Extract, Medicago Sativa (Alfalfa) Leaf Extract, Spinacia Oleracea (Spinach) Leaf Extract, Hyaluronic Acid, Potassium Sorbate, Pentylene Glycol, Aloe Barbadensis (Aloe Vera) Leaf Extract, Ethylhexylglycerin, Tocopherol, Sodium Acetate, Isopropyl Alcohol, Propylene Glycol, Cellulose, Sodium Hydroxymethylglycinate, Sodium Benzoate, Benzyl Benzoate, Natural Fragrance/Parfum, Citronellol, Hexyl Cinnamal, Limonene, Linalool, Chlorophyll (CI 75810).', 'Polypeptide-121 Future Cream:', 'Water/Aqua/Eau, Dicaprylyl Carbonate, Hydrolyzed Hyaluronic Acid, Trimethylolpropane Tricaprylate/Tricaprate, Tridecyl Trimellitate, Propanediol, Sh-Polypeptide-121, Polyglyceryl-3 Methylglucose Distearate, Panthenol, Niacinamide, Proline, Tocopheryl Acetate, Aloe Barbadensis Leaf Juice, Hydrolyzed Cannabis Sativa (Hemp) Seed Extract, Hydrolyzed Rice Protein, Hydrolyzed Pea Protein, Salvia Hispanica (Chia) Seed Extract, Acetyl Tetrapeptide-11, Acetyl Tetrapeptide-9, Acetyl Tetrapeptide-2, Hibiscus Sabdariffa Fruit Extract, Ammonium Acryloyldimethyltaurate/Beheneth-25 Methacrylate Crosspolymer, Hydrolyzed Linseed Seed, Castor Oil/IPDI Copolymer, Ceramide AP, Ceramide NP, Cetearyl Alcohol, Cetearyl Glucoside, Glycerin, Hydrolyzed Sodium Hyaluronate, Coco-Caprylate/Caprate, Dilinoleic Acid/Propanediol/Pdi Crosspolymer, Benzyl Alcohol, Zingiber Officinale (Ginger) Root Extract, Bisabolol, Caprylyl Glycol, Carbomer, Dimethyl Isosorbide, Dipropylene Glycol, Erythritol, Ethylhexylglycerin, Glucose, 1,2-Hexanediol, Trisodium Ethylenediamine Disuccinate, Glyceryl Monostearate, Phytospingosine, Polyacrylate Crosspolymer-6, Polysorbate 20, Caprylhydroxamic Acid, Potassium Sorbate, Glycine, Hydroxyacetophenone, Sodium Benzoate, T-Buty Alcohol, Citric Acid, Sodium Citrate, Sodium Lactate, Triheptanoin, Xanthan Gum.', 'Superberry Hydrate + Glow Dream Mask:', 'Water/Aqua/Eau, Glycerin, Helianthus Annuus (Sunflower) Seed Oil, Isopropyl Myristate, Glyceryl Stearate, Betaine, Cetyl Alcohol, Stearic Acid, Tetrahexyldecyl Ascorbate (Vitamin C), Opuntia Tuna (Prickly Pear) Flower/Stem Extract, Euterpe Oleracea (AcaÃ¬) Fruit Extract, Lycium Barbarum (Goji) Fruit Extract, Aristotelia Chilensis (Maqui) Fruit Extract, Moringa Oleifera Leaf Extract, Glyceryl Stearate Citrate, Tocopheryl Acetate (Vitamin E), Glyceryl Laurate, Squalane, Carbomer, Hyaluronic Acid, Allantoin, Panthenol (Vitamin B5), Ethylhexylglycerin, Xanthan Gum, Phenoxyethanol, Riboflavin (Vitamin B2), Triethyl Citrate, Citrus Aurantium Dulcis Peel Oil, Gamma-Undecalactone, Gamma-Decalactone, Tocopherol, Limonene.', 'Retinal + Niacinamide Youth Serum:', 'Water/Aqua/Eau, Butylene Glycol, Triethylhexanoin, Niacinamide, Squalane, Cyclodextrin, Glycerin, Hydrogenated Lecithin, Polyglyceryl-10 Myristate, Grifola Frondosa Fruiting Body Extract, Rubus Chamaemorus (Cloudberry) Seed Oil, Arginine, Retinal, Withania Somnifera (Ashwagandha) Root Extract, Helianthus Annuus (Sunflower) Seed Oil, Hordeum Vulgare Extract, Ganoderma Lucidum (Reishi Mushroom) Stem Extract, Sodium Hyaluronate Crosspolymer, Cucumis Sativus (Cucumber) Seed Oil, Lonicera Japonica (Honeysuckle) Flower Extract, Ceramide NP, Ceramide AP, Phytosphingosine, Cholesterol, Letinus Edodes Mycelium Extract, Lonicera Caprifolium (Honeysuckle) Flower Extract, Butyrospermum Parkii (Shea) Oil, Ceramide EOP, Sodium Lauroyl Lactylate, Acrylates/C10-30 Alkyl Acrylate Crosspolymer, Capryloyl Glycerin/Sebacic Acid Copolymer, Xanthan Gum, Tocopherol, Carbomer, Hydrolyzed Glycosaminoglycans, Sodium Hyaluronate, Hyaluronic Acid, Pentylene Glycol, Hydrolyzed Sodium Hyaluronate, Diheptyl Succinate, Phenoxyethanol, Ethylhexylglycerin, Phytosterols, Propanediol, Benzyl Glycol, Raspberry Ketone.', 'Adaptogen Deep Moisture Cream:', 'Aqua/Water/Eau, Helianthus Annuus (Sunflower) Seed Oil, Ethylhexyl Palmitate, Propanediol, Glyceryl Stearate, Stearic Acid, Glycerin, Aloe Barbadensis Leaf Juice, Glyceryl Laurate, Squalane, Pentapeptide-59, Withania Somnifera (Ashwagandha) Leaf Extract, Ganoderma Lucidum (Reishi Mushroom) Extract, Ocimum Tenuiflorum (Holy Basil) Extract, Simmondsia Chinensis (Jojoba) Seed Oil, Prunus Amygdalus (Sweet Almond) Dulcis Oil, Butyrospermum Parkii (Shea) Butter, Borago Officinalis Seed Oil, Hydrogenated Lecithin, Rhodiola Rosea Extract, Phenethyl Alcohol, Xanthan Gum, Carbomer, Ethylhexylglycerin, Panthenol, Tocopherol, Maltodextrin, Phenoxyethanol, Potassium Sorbate, Allantoin, Caramel.', 'Mandelic Acid + Superfood Unity Exfoliant:', 'Water/Aqua/Eau (Aqua), Helianthus Annuus (Sunflower) Seed Oil, Stearic Acid, Glycerin, Glyceryl Stearate, Cetyl Alcohol, Ascorbic Acid (Vitamin C), Lecithin, Panthenol (Vitamin B5), Sodium Hyaluronate Crosspolymer, Tocopheryl Acetate (Vitamin E), Phenoxyethanol, Hydroxyethylcellulose, Potassium Sorbate, Aloe Barbadensis (Aloe) Leaf Extract*, Brassica Oleracea Capitata (Kale) Leaf Extract*, Camellia Sinensis (Green Tea) Leaf Extract*, Chamomilla Recutita (Matricaria) Flower Extract*, Medicago Sativa (Alfalfa) Leaf Extract*, Spinacia Oleracea (Spinach) Leaf Extract*, Natural Fragrance, Pentylene Glycol, Ethylhexylglycerin, Magnesium Chloride, Palmitoyl Dipeptide-5 Diaminobutyroyl Hydroxythreonine, Palmitoyl Tripeptide-5, Tetradecyl Aminobutyroylvalylaminobutyric Urea Trifluoroacetate, Benzyl Benzoate, Citronellol, Hexyl Cinnamal, Limonene, Linalool.', 'Superclay Purify + Clear Power Mask:', 'Aqua/Water/Eau, Kaolin, Stearyl Alcohol,Propanediol,Glycerin, Glyceryl Stearate, Niacinamide, Oryza Sativa (Rice) Starch, Bentonite (Volcanic Clay), Cetyl Alcohol, Magnesium Aluminum Silicate, Montmorillonite (French Green Clay), Illite, Calcite, Salicylic Acid, Salix Purpurea (Red Willow) Bark Extract, Saccharomyces/Xylinum/Black Tea Ferment, Allantoin, Carthamus Tinctorius (Safflower) Seed Oil, Phycocyanin (Blue Green Algae), Aloe Barbadensis Leaf Juice, Glyceryl Acrylate/Acrylic Acid Copolymer, Cetearyl Olivate, Sorbitan Olivate, Triticum Aestivum (Wheatgrass) Leaf Extract, Lactic Acid, Sorbitan Stearate, Caprylhydroxamic Acid, Charcoal Powder, Sodium Citrate, 1,2-Hexanediol, Phenoxyethanol, Quartz, Silica, Sodium Benzoate, Potassium Sorbate, Maltodextrin, Gardenia Florida Fruit Extract', 'Dream Eye Cream:', 'Water/Aqua/Eau, Dicaprylyl Carbonate, Butyrospermum Parkii (Shea) Butter, Cetearyl Alcohol, Glycerin, Squalane, Glyceryl Stearate, Avena Sativa (Oat) Bran Extract, Citrus Aurantium Dulcis (Orange) Peel Extract, Moringa Oleifera Seed Oil, Opuntia Ficus-Indica (Prickly Pear) Seed Oil*, Lycium Barbarum (Goji) Callus Culture Extract, Gardenia Jasminoides (Gardenia) Fruit Extract, Sodium Stearoyl Glutamate, Carbomer, Cetearyl Glucoside, Isomalt, Sodium Benzoate, Tetrahexyldecyl Ascorbate (Vitamin C), Tocopheryl Acetate, Tetrasodium Glutamate Diacetate, Betaine, Ceramide NP, Phospholipids, Sodium Hyaluronate, Maltodextrin, Sodium Hydroxide, Phenoxyethanol, Glucose, Lecithin, Tocopherol, Sodium Glycolate, Sodium Formate, Ethylhexylglycerin, Citric Acid.', 'Yerba Mate Resurfacing Energy Facial:', 'Water/Aqua/Eau, Bambusa Arundinacea (Bamboo) Stem Extract, Diatomaceous Earth, Carthamus Tinctorius (Safflower) Seed Oil, Propanediol, Aloe Barbadensis (Aloe Vera) Leaf Juice, Cetyl Alcohol, Glyceryl Stearate Se, Glycerin, Lactic Acid, Sodium Acrylate/Sodium Acryloyldimethyl Taurate Copolymer, Niacinamide, C15-19 Alkane, Ilex Paraguariensis (Yerba Mate) Leaf Extract, Ilex Guayusa (Guayusa) Leaf Extract, Potassium Sorbate, Polyglyceryl-6 Laurate, Tocopherol, Ethylhexylglycerin, Bromelain (Pineapple), Sodium Phytate, Papain (Papaya), Polyglycerin-6, Zingiber Officinale (Ginger) Root Oil, Passiflora Edulis (Passion Fruit) Extract, Xanthan Gum, Curcuma Longa (Turmeric) Root Powder, Hylocereus Undatus (Dragon Fruit) Fruit Extract, Sorbitan Oleate, Helianthus Annus (Sunflower) Seed Oil, Sorbitan Isostearate, Phenoxyethanol, Sodium Benzoate.'] | M64: 340 | N64: 420 | O64: 320 | P64: 1 | Q64: 0 | R64: 1 | S64: 0 | T64: 1 | U64: ['Clean at Sephora', 'Hydrating', 'Good for: Anti-Aging', 'Retinol', 'AHA/Glycolic Acid', 'Good for: Acne/Blemishes'] | V64: Skincare | W64: Value & Gift Sets | Y64: 0 | AC64: =IF(F64="","Not Rated", IF(F64>4,"High Rated","Low Rated")) -> High Rated
A65: P483677 | B65: Mini Himalayan Salt & Rosewater Candle | C65: 7025 | D65: NEST New York | E65: 2154 | F65: 5 | G65: 2 | H65: 2 oz / 70 g | I65: Size + Concentration + Formulation | J65: 2 oz / 70 g candle | M65: 18 | P65: 0 | Q65: 0 | R65: 1 | S65: 0 | T65: 0 | U65: ['Vegan', 'Without Phthalates', 'Without Parabens', 'Without Sulfates SLS & SLES', 'Cruelty-Free'] | V65: Fragrance | W65: Candles & Home Scents | X65: Candles | Y65: 0 | AC65: =IF(F65="","Not Rated", IF(F65>4,"High Rated","Low Rated")) -> High Rated
A66: P470049 | B66: Clearcalm Clarifying Clay Cleanser | C66: 5857 | D66: REN Clean Skincare | E66: 4303 | F66: 4.6 | G66: 40 | H66: 5.1 oz/ 150 mL | I66: Size | J66: 5.1 oz/ 150 mL | L66: ['Aqua (Water), Kaolin, Cetearyl Alcohol, Caprylic/Capric Triglyceride, Sesamum Indicum (Sesame) Seed Oil, Cetearyl Glucoside, Glycerin, Benzyl Alcohol, Helianthus Annuus (Sunflower) Seed Oil, Salix Nigra (Willow) Bark Extract, Zinc Gluconate, Bisabolol, Oryzanol, Salvia Officinalis (Sage) Oil, Lavandula Angustifolia (Lavender) Oil, Linalool, Calendula Officinalis Flower Extract, Leptospermum Scoparium Oil, Tocopherol, Dehydroacetic Acid, Anthemis Nobilis (Chamomile) Flower Oil, Citral, Xanthan Gum, Lactic Acid, Citronellol, Farnesol, Limonene, Crataegus Oxyacantha Stem Extract, Glucose.'] | M66: 38 | P66: 0 | Q66: 0 | R66: 0 | S66: 0 | T66: 0 | U66: ['Good for: Acne/Blemishes', 'Fragrance Free', 'Gluten Free', 'Cruelty-Free', 'Clean at Sephora'] | V66: Skincare | W66: Cleansers | X66: Face Wash & Cleansers | Y66: 0 | AC66: =IF(F66="","Not Rated", IF(F66>4,"High Rated","Low Rated")) -> High Rated
A67: P502989 | B67: Total Coverage Body Makeup Sponge | C67: 3902 | D67: SEPHORA COLLECTION | E67: 1080 | F67: 4 | G67: 4 | M67: 14 | P67: 0 | Q67: 1 | R67: 0 | S67: 0 | T67: 1 | U67: ['Recyclable Packaging', 'Pressed Powder Formula', 'Cream Formula', 'Liquid Formula'] | V67: Makeup | W67: Brushes & Applicators | X67: Sponges & Applicators | Y67: 0 | AC67: =IF(F67="","Not Rated", IF(F67>4,"High Rated","Low Rated")) -> Low Rated
A68: P431192 | B68: Curl Corps Curl Enhancing Hair Gel | C68: 6004 | D68: amika | E68: 14341 | F68: 4.2192 | G68: 73 | H68: 6.7 oz/ 200 mL | I68: Size | J68: 6.7 oz/ 200 mL | L68: ['Water/Eau/Aqua, Glycerin, PEG-6 Caprylic/Capric Glycerides, Hippophae Rhamnoides (Sea Buckthorn/Argousier) Extract, Avena Sativa (Oat/Avoine) Peptide, Glycine Soja (Soybean/Soja) Protein, Hydrolyzed Wheat Protein, PEG-40 Hydrogenated Castor Oil, Guar Hydroxypropyltrimonium Chloride, Propylene Glycol, Caprylyl Glycol, Hydroxyethylcellulose, Butylene Glycol, 1,2-Hexanediol, Polysorbate 60, Glyoxal, Phenoxyethanol, Sodium Benzoate, Potassium Sorbate, Fragrance/Parfum, Citric Acid, Sodium Phosphate, Disodium Phosphate, Benzoic Acid, Benzyl Alcohol, Butylphenyl Methylpropional, Hydroxycitronellal, Hydroxyisohexyl 3-Cyclohexene Carboxaldehyde, Limonene.'] | M68: 28 | P68: 0 | Q68: 0 | R68: 1 | S68: 0 | T68: 0 | U68: ['Vegan', 'Clean at Sephora', 'Coily Hair', 'Good for: Frizz', 'Curly Hair', 'Good for: Dryness'] | V68: Hair | W68: Hair Styling & Treatments | X68: Hair Styling Products | Y68: 0 | AC68: =IF(F68="","Not Rated", IF(F68>4,"High Rated","Low Rated")) -> High Rated
A69: P417213 | B69: Nectarine Blossom & Honey Body CrÃ¨me | C69: 6202 | D69: Jo Malone London | E69: 4100 | F69: 4.5 | G69: 14 | H69: 5.9 oz/ 175 mL | I69: Size | J69: 5.9 oz/ 175 mL | L69: ['Water, Glycerin, Cetearyl Alcohol, Simmondsia Chinensis (Jojoba) Seed Oil, Fragrance, Glyceryl Stearate, Stearic Acid, Triethanolamine, Theobroma Cacao (Cocoa) Seed Butter, Prunus Amygdalus Dulcis (Sweet Almond) Oil, Isopropyl Palmitate, Dimethicone, Aloe Barbadensis Leaf Extract, Bisabolol, Caffeine, Cocamidopropyl Pg-Dimonium Chloride Phosphate, Glyceryl Laurate, Hexylene Glycol, Caprylyl Glycol, Disodium Edta, Citral, Limonene, Hydroxyisohexyl 3-Cyclohexene Carboxaldehyde, Citronellol, Linalool, Geraniol, Phenoxyethanol <ILN39546>.'] | M69: 90 | P69: 0 | Q69: 0 | R69: 0 | S69: 0 | T69: 0 | V69: Bath & Body | W69: Body Moisturizers | X69: Body Lotions & Body Oils | Y69: 0 | AC69: =IF(F69="","Not Rated", IF(F69>4,"High Rated","Low Rated")) -> High Rated
A70: P501767 | B70: Flor de la Virgen Eau de Parfum Travel Spray | C70: 7101 | D70: Boy Smells | E70: 1458 | F70: 4.4242 | G70: 66 | H70: .34 oz / 10 mL eau de parfum spray | I70: Size + Concentration + Formulation | J70: .34 oz / 10 mL eau de parfum spray | L70: ['Alcohol Denat., Parfum (Fragrance), Aqua (Water/Eau), Alpha-isomethyl Ionone, Benzyl Salicylate, Butylphenyl Methylpropional, Citral, Citronellol, Farnesol, Geraniol, Limonene, Linalool.'] | M70: 30 | P70: 0 | Q70: 0 | R70: 0 | S70: 0 | T70: 0 | U70: ['Vegan', 'Unisex/ Genderless Scent', 'Floral Scent', 'Without Phthalates', 'Without Parabens', 'Cruelty-Free'] | V70: Fragrance | W70: Women | X70: Rollerballs & Travel Size | Y70: 0 | AC70: =IF(F70="","Not Rated", IF(F70>4,"High Rated","Low Rated")) -> High Rated
A71: P446612 | B71: Instant Magic Facial Dry Sheet Mask | C71: 6236 | D71: Charlotte Tilbury | E71: 11527 | F71: 3.4906 | G71: 53 | H71: 1 mask | I71: Size | J71: 1 mask | L71: ['Stearic Acid, Butyrosperum Parkii (Shea) Butter, Glycerin, Olea Europeaea (Olive) Fruit Oil, Mangifera Indica (Mango) Seed Butter, Persea Gratissima (Avocado) Oil, Peg-20 Methyl Glucose Sesquistearate, Cetyl Ricinoleate, Hydrogenated Vegetable Oil, Cetyl Alcohol, Tocopheryl Acetate, Sorbitan Oleate, Sorbitan Stearate, Glyceryl Stearate, Glycine Soja (Soybean) Oil, Acacia Senegal Gum, Ethylhexylglycerin, Caprylyl Glycol, Cetearyl Olivate, Niacinamide, Benzyl Alcohol, Sorbitan Olivate, Butylene Glycol, Arginine, Leontopodium Alpinum Callus Culture Extract, Pentaerythrityl Tetra-Di-t-Butyl Hydroxyhydrocinnamate, Calcium Titanium Borosilicate, Disodium Edta, Magnolia Officinalis Bark Extract, Helianthus Annuus (Sunflower Seed Oil), Xanthan Gum, Dicaprylyl Ether, Rosmarinus Officinalis (Rosemary) Leaf Extract, Carbomer Algae (Dictyopteris Membranacca) Extract, Polysorbate 20, Sodium Lactate, Magnolia Gradiflora Bark Extract, Luaryl Alcohol, Crocus Sativus Flower Extract, Citric Acid, Tocopherol, Palmitoyl Tripeptide-1, Palmitoyl Tetrapeptide-7, Tin Oxide (Ci 77861), Titanium Dioxide (Ci 77891), Mica (Ci 77019), Carmine (Ci 75470).'] | M71: 25 | P71: 0 | Q71: 0 | R71: 0 | S71: 1 | T71: 0 | V71: Skincare | W71: Masks | X71: Sheet Masks | Y71: 0 | AC71: =IF(F71="","Not Rated", IF(F71>4,"High Rated","Low Rated")) -> Low Rated
A72: P136025 | B72: Burberry London | C72: 1179 | D72: BURBERRY | E72: 8056 | F72: 4.6875 | G72: 272 | H72: 3.3 oz/ 100 mL | I72: Size + Concentration + Formulation | J72: 3.3 oz/ 100 mL | L72: ['Alcohol Denat., Fragrance, Water, Benzyl Salicylate, Ethylhexyl Methoxycinnamate, Limonene, Butylphenyl Methylpropional, Linalool, Hexyl Cinnamal, Benzophenone-3, Ethylhexyl Salicylate, Butyl Methoxydibenzoylmethane, Citronellol, Alpha-Isomethyl Ionone, Geraniol, Eugenol, Isoeugenol, Benzyl Benzoate, Citral, Benzyl Alcohol, Bht, Ext. Violet 2 (Ci 60730), Red 33 (Ci 17200), Yellow 5 (Ci 19140).'] | M72: 112 | P72: 0 | Q72: 0 | R72: 0 | S72: 0 | T72: 0 | V72: Fragrance | W72: Women | X72: Perfume | Y72: 1 | Z72: 90 | AA72: 90 | AC72: =IF(F72="","Not Rated", IF(F72>4,"High Rated","Low Rated")) -> High Rated
A73: P434402 | B73: Nutritive Heat Protecting Leave-In Treatment For Dry Hair | C73: 6259 | D73: KÃ©rastase | E73: 40523 | F73: 4.6966 | G73: 323 | H73: 5.1 oz/ 150 mL | I73: Size | J73: 5.1 oz/ 150 mL | L73: ['Water, C13-16 Isoparaffin, Propylene Glycol, Dimethicone, Triethanolamine, Phenoxyethanol, Peg/Ppg-17/18 Dimethicone, Carbomer, Potato Starch Modified, Behentrimonium Chloride, Hydroxypropyl Guar, Caprylyl Glycol, Polyquaternium-4, Amodimethicone, Poly(Linseed Oil), Linalool, Butylphenyl Methylpropional, Benzophenone-4, Hexyl Cinnamal, Benzyl Salicylate, Benzyl Alcohol, Citronellol, Alpha-Isomethyl Ionone, Trideceth-6, 2-Oleamido-1,3-Octadecanediol, Xylose, Hydroxycitronellal, Coumarin, Limonene, Iris Florentina / Iris Florentina Root Extract, Cetrimonium Chloride, Royal Jelly / Royal Jelly Extract, Fragrance.'] | M73: 45 | P73: 0 | Q73: 0 | R73: 0 | S73: 0 | T73: 1 | U73: ['Hydrating', 'Heat Protection', 'All Hair Types', 'Good for: Frizz', 'Good for: Dryness', 'Increases Shine'] | V73: Hair | W73: Hair Styling & Treatments | X73: Hair Primers | Y73: 0 | AC73: =IF(F73="","Not Rated", IF(F73>4,"High Rated","Low Rated")) -> High Rated
